Workbook

Sheet Dashboard
A1: DSA TRAINING DASHBOARD - NVIDIA & AI-INFRASTRUCTURE SYSTEMS
A2: Started: 01 Oct 2026 | Ends: 17 Mar 2027 | Target: NVIDIA, Hyperscalers & AI-Infra Systems | Fill ProblemDB & DayPlan honestly
A3: TODAY'S WORKFLOW | D3: Failure Category | E3: Count | G3: QUICK-START DAILY PROTOCOL
A4: Current day | B4: =MIN(168,COUNTIF(DayPlan!$W$2:$W$169,"Yes")+1) | D4: F1-Understand | E4: =COUNTIF(FailureLog!$D$2:$D$500,D4)+COUNTIF(ProblemDB!$M$2:$M$750,D4) | G4: 1. Open DayPlan -> go to 'Current day' row. Do exactly that row.
A5: Current week | B5: =ROUNDUP($B4/7,0) | D5: F2-Pattern | E5: =COUNTIF(FailureLog!$D$2:$D$500,D5)+COUNTIF(ProblemDB!$M$2:$M$750,D5) | G5: 2. Write target TC from constraints BEFORE touching the keyboard.
A6: TODAY: objective | B6: =IFERROR(INDEX(DayPlan!$D$2:$D$169,$B4),"") | D6: F3-Derive | E6: =COUNTIF(FailureLog!$D$2:$D$500,D6)+COUNTIF(ProblemDB!$M$2:$M$750,D6) | G6: 3. Obey the Stuck Protocol (see README): 0 -> 10 -> 20 -> 30 min checkpoints.
A7: TODAY: pattern | B7: =IFERROR(INDEX(DayPlan!$E$2:$E$169,$B4),"") | D7: F4-WrongDS | E7: =COUNTIF(FailureLog!$D$2:$D$500,D7)+COUNTIF(ProblemDB!$M$2:$M$750,D7) | G7: 4. Log every problem in ProblemDB the same day. Review dates auto-compute.
A8: TODAY: mode / help | B8: =IFERROR(INDEX(DayPlan!$J$2:$J$169,$B4)&" | "&INDEX(DayPlan!$K$2:$K$169,$B4),"") | D8: F5-Complexity | E8: =COUNTIF(FailureLog!$D$2:$D$500,D8)+COUNTIF(ProblemDB!$M$2:$M$750,D8) | G8: 5. Log every failure in FailureLog with a category + one preventive rule.
A9: TODAY: problems | B9: =IFERROR(INDEX(DayPlan!$L$2:$L$169,$B4)&" | "&INDEX(DayPlan!$O$2:$O$169,$B4),"") | D9: F6-Implementation | E9: =COUNTIF(FailureLog!$D$2:$D$500,D9)+COUNTIF(ProblemDB!$M$2:$M$750,D9) | G9: 6. Sunday: fill WeeklyAssessment. Let the data steer the next week.
A10: TODAY: tutorial? | B10: =IFERROR(IF(INDEX(DayPlan!$G$2:$G$169,$B4)="YES",INDEX(DayPlan!$H$2:$H$169,$B4)&" ("&INDEX(DayPlan!$I$2:$I$169,$B4)&" min)","NO tutorial - struggle first"),"") | D10: F7-EdgeCase | E10: =COUNTIF(FailureLog!$D$2:$D$500,D10)+COUNTIF(ProblemDB!$M$2:$M$750,D10) | G10: 7. Diagnostics on Days 28/56/84/98. Unlabelled. Timed. No hints. Real measurements.
A11: Days completed | B11: =COUNTIF(DayPlan!$W$2:$W$169,"Yes") | D11: F8-Debugging | E11: =COUNTIF(FailureLog!$D$2:$D$500,D11)+COUNTIF(ProblemDB!$M$2:$M$750,D11) | G11: 8. Master YouTube Directory: Check 'YouTubeChannels' sheet for flagship playlists.
A12: Program progress | B12: =IFERROR($B11/168,0) | D12: F9-Forgot | E12: =COUNTIF(FailureLog!$D$2:$D$500,D12)+COUNTIF(ProblemDB!$M$2:$M$750,D12)
A13: SOLVE QUALITY METRICS | D13: F10-Pressure | E13: =COUNTIF(FailureLog!$D$2:$D$500,D13)+COUNTIF(ProblemDB!$M$2:$M$750,D13) | G13: SIGNS THE PLAN IS WORKING
A14: Problems attempted | B14: =COUNTA(ProblemDB!$A$2:$A$750) | D14: F11-HintDependent | E14: =COUNTIF(FailureLog!$D$2:$D$500,D14)+COUNTIF(ProblemDB!$M$2:$M$750,D14) | G14: [OK] Time-to-pattern dropping at each diagnostic
A15: Solved independently | B15: =COUNTIF(ProblemDB!$G$2:$G$750,"Yes") | D15: F12-CantExplain | E15: =COUNTIF(FailureLog!$D$2:$D$500,D15)+COUNTIF(ProblemDB!$M$2:$M$750,D15) | G15: [OK] Hint-dependency rate below 25% by week 8
A16: Solved with hints | B16: =COUNTIFS(ProblemDB!$I$2:$I$750,">0",ProblemDB!$J$2:$J$750,"<>Yes") | G16: [OK] Can reconstruct any pattern without notes 3 days later
A17: Needed the solution | B17: =COUNTIF(ProblemDB!$J$2:$J$750,"Yes") | D17: MASTER YOUTUBE DIRECTORY | G17: [OK] Mock scores increasing
A18: Independent-solve rate | B18: =IFERROR($B15/$B14,0) | D18: =HYPERLINK("#'YouTubeChannels'!A1", "📺 Open Master YouTube Directory (10 Creators) ↗")
A19: Hint-dependency rate | B19: =IFERROR(($B16+$B17)/$B14,0) | D19: Striver • Aditya Verma • Pratyush • Babbar • NeetCode | G19: SIGNS YOU NEED TO ADJUST
A20: Problems mastered | B20: =COUNTIF(ProblemDB!$S$2:$S$750,"Yes") | G20: [NO] Same failure category 3+ weeks in a row
A21: Avg solve time (min) | B21: =IFERROR(ROUND(AVERAGE(ProblemDB!$H$2:$H$750),0),0) | G21: [NO] Hint-dependency above 40% for 2+ weeks
A22: 2nd solutions found | B22: =COUNTIF(ProblemDB!$X$2:$X$750,"Yes") | G22: [NO] Time-to-pattern not dropping between diagnostics
A23: INTERVIEW READINESS | G23: [NO] Can solve only when problem is labelled with the pattern
A24: Mock/diagnostic avg (/10) | B24: =IFERROR(ROUND(AVERAGE(MockInterviews!$N$2:$N$30),1),0) | G24: [NO] Cannot reconstruct a solution 2 days after solving it
A25: Avg time-to-pattern (min) | B25: =IFERROR(ROUND(AVERAGE(MockInterviews!$J$2:$J$30),1),0)
A26: Avg pattern mastery (/5) | B26: =IFERROR(ROUND(AVERAGE(PatternLibrary!$J$2:$J$43),2),0)
A27: Reviews due today | B27: =COUNTIFS(ProblemDB!$P$2:$P$750,"<="&TODAY(),ProblemDB!$S$2:$S$750,"<>Yes")
A28: INTERVIEW READINESS SCORE | B28: =IF($B14<5,0,ROUND(30*MIN(1,MAX(0,IFERROR($B18/0.80,0)))+25*MIN(1,MAX(0,IFERROR((1-$B19)/0.80,0)))+25*MIN(1,MAX(0,IFERROR($B24/10,0)))+20*IF($B25=0,0,MIN(1,MAX(0,IFERROR((12-$B25)/8,0)))),0))
A29: PATTERN MASTERY & HEALTH
A30: Strongest pattern (self-rated) | B30: =IFERROR(INDEX(PatternLibrary!$A$2:$A$43,MATCH(MAX(PatternLibrary!$J$2:$J$43),PatternLibrary!$J$2:$J$43,0)),"Rate patterns first")
A31: Weakest pattern (self-rated) | B31: =IFERROR(INDEX(PatternLibrary!$A$2:$A$43,MATCH(MINIFS(PatternLibrary!$J$2:$J$43,PatternLibrary!$J$2:$J$43,">0"),PatternLibrary!$J$2:$J$43,0)),"Rate patterns first")
A32: Most failure-prone category | B32: =IF(MAX($E$4:$E$15)=0,"No failures logged yet",INDEX($D$4:$D$15,MATCH(MAX($E$4:$E$15),$E$4:$E$15,0))&" ("&MAX($E$4:$E$15)&" failures)")
A33: Current level | B33: =IF($B14<10,"Unmeasured - solve 10+ logged problems first",IF($B28<35,"Beginner: knows topics but pattern-blind",IF($B28<55,"Intermediate: recognises common patterns",IF($B28<75,"Strong: derives most solutions independently","Expert-level: can derive unfamiliar problems under pressure"))))
A34: SYSTEM OPERATING GUIDE

Sheet README
A1: DSA TRAINING SYSTEM - AI INFRASTRUCTURE (168 DAYS / 24 WEEKS)
A2: The real metric: how fast you turn an unfamiliar problem into a correct, efficient algorithm. Not how many problems you have solved.
A4: THE ONLY METRIC THAT MATTERS
A5: Problem count is a lagging metric and a vanity number. The metric that predicts interview success: * Time-to-pattern on UNLABELLED problems (target: <5 min for Medium by week 10) * Independent-solve rate (target: >70% by week 12) * Hint-dependency rate (target: <20% by week 10) * Ability to reconstruct any solved problem from memory 3 days later Dashboard tracks all four. Fill it honestly or it becomes useless.
A7: DAILY BLOCK STRUCTURE (1-2 hours total)
A8: A) RETRIEVAL [10-15 min] From memory, no notes: state yesterday's pattern trigger + invariant + complexity. If you cannot, add it to ReviewQueue immediately. B) CONCEPT / TUTORIAL [0-25 min - ONLY if DayPlan says YES] Read the DayPlan tutorial column. If it says NO, do not watch anything. The urge to watch a tutorial instead of struggling is a productivity trap. C) DEEP SOLVING [45-70 min - the real training block] Obey the STUCK PROTOCOL below. No shortcuts. D) RECONSTRUCTION [10 min] Close your solution. Open a blank file. Rebuild it from memory. If you cannot reconstruct it, you did not learn it. E) FAILURE ANALYSIS [5 min] Log every failure in FailureLog with an honest category + one preventive rule. F) REVIEW [10 min] Top item from ReviewQueue. Retrieval only - no re-reading.
A10: THE STUCK PROTOCOL (non-negotiable, enforced in DayPlan column)
A11: 0-10 min -> NO help. Restate the problem in your own words. Write constraints. Write brute-force + its TC. Write target TC. Write 2-3 candidate approaches. 10-20 min -> ONE conceptual hint only. No code. No data-structure name if avoidable. Hint = a question that points you toward the right abstraction. 20-30 min -> Stronger hint: name the pattern or the key invariant. Still no implementation. 30+ min -> Read ONLY the core approach (2-3 sentences). Then close it. Implement entirely from scratch - never copy code. If you read code -> problem is auto-logged as "Solution Viewed = Yes" and re-queued at +1 day. If you solve with hints -> re-queued at +3 days, not +7. The goal: "I understand WHY this solution exists." NOT "I understood it after being shown."
A13: PHASE SEQUENCE FOR EVERY IMPORTANT PROBLEM
A14: 1. UNDERSTAND - What is asked? What are constraints? What changes? What is reusable? 2. PREDICT - Write target TC from constraints. List 2-3 approaches. Name the bottleneck. 3. DERIVE - Attempt yourself. Use stuck protocol if needed. 4. IMPLEMENT - Write clean code. 5. ATTACK - Test: empty input, single element, all duplicates, max n, negatives, overflow, adversarial order. 6. OPTIMIZE - Can TC improve? If no, can SC improve? Is there a hidden invariant? 7. RECONSTRUCT - Close everything. Rebuild from memory and explain aloud. 8. SCHEDULE - ProblemDB auto-computes review dates based on your performance.
A16: TUTORIAL RULES (35 curated tutorials across 168 days)
A17: Watch BEFORE a problem only when the mental model is genuinely new (DayPlan marks these explicitly). Do NOT watch because a specific problem is hard. Struggle first. Watch AFTER only when you failed to recognise the SAME pattern twice. Rewatch only if you cannot reconstruct the concept from memory. For every tutorial, extract: * The TRIGGER (what wording in a problem should activate this pattern?) * The INVARIANT (what remains true throughout the algorithm?) * The COMPLEXITY ARGUMENT (why is it O(n)? O(n log n)? - derive it, do not accept it) Do NOT memorise the presenter's code. That is passive consumption, not learning.
... A50: Curated tutorial channels: - Striver (take U forward) - algorithmic patterns & technical interview rigor - Aditya Verma - intuition & recurrence templates (DP, Stack, Sliding Window, BS) - Love Babbar (CodeHelp) - clear structural breakdowns & Hindi explanations - Padho with Pratyush - pattern-based DSA mastery, algorithmic pattern recognition & FAANG problem archetypes - NeetCode (neetcode.io) - concise visual problem walkthroughs & clean code - Specialized channels: Abdul Bari (algorithms), WilliamFiset (graphs), Errichto (range trees), Martin Thompson (lock-free), CMU DB (paging) See the dedicated 'YouTubeChannels' sheet tab in this workbook for direct 1-click links to master playlists and channel URLs.

Sheet DayPlan
A1: Day | B1: Week | C1: Date | D1: Objective | E1: Pattern | F1: Concept | G1: Tutorial? | H1: Tutorial Topic | I1: Tut min | J1: Mode | K1: Help / Stuck Protocol | L1: Problem 1 | M1: P1 Diff | N1: P1 Target min | O1: Problem 2 | P1: P2 Diff | Q1: P2 Target min | R1: Review Problem | S1: Reconstruction Task | T1: Assessment Question | U1: AI-Infra Connection | V1: Skill Gained | W1: Completed? | X1: Actual min | Y1: Notes | Z1: Failure Category | AA1: 2nd-Sol? | AB1: YouTube Tutorial ↗
A2: 1 | B2: 1 | C2: 46296 | D2: Set up C++ environment, learn syntax, types, and get your very first green Accepted checkmark on LeetCode without intimidation | E2: C++ Fundamentals & I/O | F2: Basic syntax, #include <iostream>, int main(), primitive types, cin/cout, LeetCode function signatures | G2: YES | H2: =HYPERLINK("https://www.youtube.com/watch?v=EAR7De6Goz4", "C++ Setup, Syntax & LeetCode Workflow") | I2: 30 | J2: Untimed | K2: Tutorial & step-by-step guidance | L2: LC 2235 Add Two Integers | M2: E | N2: 5 | O2: LC 2469 Convert the Temperature | P2: E | Q2: 10 | R2: - | S2: Write a minimal C++ program with main(), cin/cout, and basic type declarations from memory | T2: Did your code compile without syntax errors and pass all tests on LeetCode? Yes/No | U2: Every GPU kernel in CUDA and AI engine is written in static, strongly-typed C++ | V2: C++ syntax & environment setup | AB2: =HYPERLINK("https://www.youtube.com/watch?v=EAR7De6Goz4", "▶ Watch (Striver) ↗")
A3: 2 | B3: 1 | C3: 46297 | D3: Master if-else logic and loop mechanics (for, while); learn to step-trace variables on paper before typing | E3: Conditionals & Loops | F3: if/else branching; for and while loop bounds; step-tracing variables on paper; digit extraction via % 10 and / 10 | G3: YES | H3: =HYPERLINK("https://www.youtube.com/watch?v=p3YUQB9-B1g", "Loop Mechanics & Tracing on Paper") | I3: 25 | J3: Untimed | K3: Step trace on paper first | L3: LC 9 Palindrome Number | M3: E | N3: 15 | O3: LC 1480 Running Sum of 1d Array | P3: E | Q3: 10 | R3: LC 2235 Add Two Integers | S3: Trace loop states on paper for n = 121 (x % 10, x / 10, rev) without running code | T3: Did you trace the loop iteration by iteration on paper before submitting? | U3: Loop bounds and stepping control thread-grid execution in GPU blocks | V3: Loop execution & state tracing | AB3: =HYPERLINK("https://www.youtube.com/watch?v=p3YUQB9-B1g", "▶ Watch (Gate Smashers) ↗")
A4: 3 | B4: 1 | C4: 46298 | D4: Demystify Big-O through loop iterations: 1 loop = O(N), nested loops = O(N^2), 10^8 operations/sec CPU limit | E4: Complexity calibration | F4: Loop counting: 1 loop = O(N), 2 nested loops = O(N^2), binary halving = O(log N); modern CPUs do ~10^8 ops/sec; why N=10^5 causes TLE on O(N^2) | G4: YES | H4: =HYPERLINK("https://www.youtube.com/watch?v=9TlHvipP5yA", "Time & Space Complexity from Loops") | I4: 30 | J4: Untimed | K4: Count loop operations | L4: LC 1929 Concatenation of Array | M4: E | N4: 10 | O4: LC 2011 Final Value of Variable After Operations | P4: E | Q4: 10 | R4: LC 9 Palindrome Number | S4: Write the 10^8 rule: given N = 20, 500, 5000, 10^5, 10^6, 10^9, state max feasible Big-O | T4: Can you calculate Big-O of a nested loop without guessing? | U4: Latency budgets in NVIDIA GPU kernels depend on input scale, not intuition | V4: Constraint-first thinking | AB4: =HYPERLINK("https://www.youtube.com/watch?v=9TlHvipP5yA", "▶ Watch (Abdul Bari) ↗")
A5: 4 | B5: 1 | C5: 46299 | D5: Understand memory passing: pass-by-value vs pass-by-reference (&), and dynamic arrays (std::vector) | E5: Memory References & Vectors | F5: Pass by value vs reference (&); std::vector<int>, push_back(), size(), indexing; range-based for loops; avoiding copy overhead | G5: YES | H5: =HYPERLINK("https://www.youtube.com/watch?v=WgMPrLX-zsA", "C++ Vectors & Pass-by-Reference (&)") | I5: 25 | J5: Untimed | K5: Understand memory passing | L5: LC 27 Remove Element | M5: E | N5: 15 | O5: LC 26 Remove Duplicates from Sorted Array | P5: E | Q5: 15 | R5: LC 1480 Running Sum of 1d Array | S5: Explain why passing vector<int>& avoids an O(N) memory copy in RAM/cache | T5: Did you use in-place write pointer without creating an auxiliary vector? | U5: Zero-copy pointer passing is mandatory in high-performance GPU tensor engines | V5: In-place array manipulation | AB5: =HYPERLINK("https://www.youtube.com/watch?v=WgMPrLX-zsA", "▶ Watch (CodeHelp - by Babbar) ↗")
A6: 5 | B6: 1 | C6: 46300 | D6: Learn to maintain running state (min, max, count) in a single pass without extra memory | E6: Array Traversal & Running State | F6: Initializing sentinel bounds (INT_MAX, INT_MIN); single-pass running tracking; in-place array shifting | G6: YES | H6: =HYPERLINK("https://www.youtube.com/watch?v=37E9ckMDdTk", "Array Traversal & In-Place Shifts") | I6: 20 | J6: Untimed | K6: Single-pass invariant | L6: LC 283 Move Zeroes | M6: E | N6: 15 | O6: LC 1752 Check if Array Is Sorted and Rotated | P6: E | Q6: 20 | R6: LC 26 Remove Duplicates from Sorted Array | S6: Write Move Zeroes with 2 pointers without using an auxiliary vector from memory | T6: Could you solve Move Zeroes in O(1) auxiliary space? | U6: In-place compaction mirrors zero-copy buffer compaction in network pipelines | V6: Single-pass running state | AB6: =HYPERLINK("https://www.youtube.com/watch?v=37E9ckMDdTk", "▶ Watch (Striver) ↗")
A7: 6 | B7: 1 | C7: 46301 | D7: Discover opposite-end two pointers: moving left and right pointers towards the center with clear termination | E7: Two pointers (opposite ends) | F7: left = 0, right = n - 1; while (left < right); inward convergence; alphanumeric filtering | G7: YES | H7: =HYPERLINK("https://www.youtube.com/watch?v=jJXJ16kPFWg", "Two Pointers: Inward Convergence") | I7: 20 | J7: Untimed | K7: Two pointers opposite ends | L7: LC 125 Valid Palindrome | M7: E | N7: 15 | O7: LC 344 Reverse String | P7: E | Q7: 10 | R7: LC 283 Move Zeroes | S7: Prove why left < right terminates correctly and what happens on odd vs even lengths | T7: Did you handle punctuation and uppercase without extra array allocation? | U7: Bidirectional stream compaction in ring buffers | V7: Inward pointer convergence | AB7: =HYPERLINK("https://www.youtube.com/watch?v=jJXJ16kPFWg", "▶ Watch (NeetCode) ↗")
A8: 7 | B8: 1 | C8: 46302 | D8: Lock in Week 1 patterns: syntax, loop mechanics, vectors, and in-place pointers without looking at solutions | E8: Review/audit | F8: Retention without notes: C++ syntax, loops, vectors, in-place pointer shifts | G8: NO | H8: - | J8: Untimed | K8: Notes forbidden | L8: LC 9 Palindrome Number | M8: E | N8: 15 | O8: LC 283 Move Zeroes | P8: E | Q8: 15 | R8: All Week 1 problems | S8: Re-solve Palindrome Number and Move Zeroes on a blank editor with zero notes | T8: Can you write clean, compiling C++ vector code without syntax errors? | U8: Foundational fluency is required before hardware-aware optimization | V8: Retention + self-audit | AB8: —
A9: 8 | B9: 2 | C9: 46303 | D9: Turn counting into O(1) lookups: frequency arrays count[26] vs unordered_map | E9: Frequency/counting + hashing | F9: Direct index hashing via s[i] - 'a'; hash map as an index; O(1) average lookup vs O(N) linear search | G9: YES | H9: =HYPERLINK("https://www.youtube.com/watch?v=KEs5UyBJ39g", "Hashing & Frequency Counting") | I9: 30 | J9: Untimed | K9: Hash map as index | L9: LC 242 Valid Anagram | M9: E | N9: 15 | O9: LC 217 Contains Duplicate | P9: E | Q9: 12 | R9: LC 125 Valid Palindrome | S9: Explain why int count[26] is 10x faster than unordered_map due to L1 cache locality | T9: Could you design the frequency array yourself without hints? | U9: Direct index tables underpin GPU kernel launch lookup tables | V9: Hash key design | AB9: =HYPERLINK("https://www.youtube.com/watch?v=KEs5UyBJ39g", "▶ Watch (Striver) ↗")
A10: 9 | B10: 2 | C10: 46304 | D10: Master the complement lookup: transforming O(N^2) brute force into O(N) single-pass with a hash map | E10: Complement Lookup (Hash Map) | F10: For each x, check if target - x is in map; value -> index map; single-pass lookup | G10: YES | H10: =HYPERLINK("https://www.youtube.com/watch?v=KLlXCFG5TnA", "Two Sum & Stock Mental Model") | I10: 25 | J10: Untimed | K10: Complement lookup | L10: LC 1 Two Sum | M10: E | N10: 15 | O10: LC 121 Best Time to Buy & Sell Stock | P10: E | Q10: 15 | R10: LC 217 Contains Duplicate | S10: Derive Two Sum brute force O(N^2) vs hash map O(N) on paper; explain one-pass complement check | T10: Did you state why one-pass map prevents using the same element twice? | U10: Key-value indexing in high-throughput inference caches | V10: Complement lookup | AB10: =HYPERLINK("https://www.youtube.com/watch?v=KLlXCFG5TnA", "▶ Watch (NeetCode) ↗")
A11: 10 | B11: 2 | C11: 46305 | D11: Learn when sorting unlocks two pointers: achieving O(N) time and O(1) space without hash map memory overhead | E11: Two pointers (sorted input) | F11: If sorted: sum < target -> left++; sum > target -> right--; eliminating entire search halves | G11: YES | H11: =HYPERLINK("https://www.youtube.com/watch?v=cQ1Oz4ckceM", "Two Pointers on Sorted Arrays") | I11: 20 | J11: Untimed | K11: Sorted two pointers | L11: LC 167 Two Sum II | M11: E | N11: 15 | O11: LC 977 Squares of a Sorted Array | P11: E | Q11: 18 | R11: LC 1 Two Sum | S11: Prove why Two Sum II on sorted input never misses the answer with two pointers | T11: Did you avoid allocating an O(N) hash map when the input is sorted? | U11: Sorted shard scans and merge joins in distributed columnar databases | V11: Monotonic pointer proof | AB11: =HYPERLINK("https://www.youtube.com/watch?v=cQ1Oz4ckceM", "▶ Watch (NeetCode) ↗")
A12: 11 | B12: 2 | C12: 46306 | D12: Learn partial-sum precomputation to answer any range sum query in O(1) time | E12: Prefix/suffix reasoning | F12: prefix[i] = prefix[i-1] + nums[i]; range [L, R] = prefix[R] - prefix[L-1]; avoiding repeated O(N) scans | G12: YES | H12: =HYPERLINK("https://www.youtube.com/watch?v=DhFh8Kw7ymk", "Prefix Sum Fundamentals") | I12: 25 | J12: Untimed | K12: Precompute partial sums | L12: LC 724 Find Pivot Index | M12: E | N12: 15 | O12: LC 303 Range Sum Query - Immutable | P12: E | Q12: 15 | R12: LC 121 Best Time to Buy & Sell Stock | S12: Write the prefix sum formula for range [L, R] and explain the L=0 edge case from memory | T12: Can you state the loop invariant of the prefix sum array in one sentence? | U12: Cumulative metrics and rolling latency telemetry over time-series data | V12: Reuse of partial results | AB12: =HYPERLINK("https://www.youtube.com/watch?v=DhFh8Kw7ymk", "▶ Watch (Striver) ↗")
A13: 12 | B13: 2 | C13: 46307 | D13: Learn to slide a window of size K in O(1) per step by adding incoming and subtracting outgoing | E13: Sliding window (fixed) | F13: Fixed size K: compute initial window of size K; then loop i from K to N-1, updating sum += nums[i] - nums[i-K] | G13: YES | H13: =HYPERLINK("https://www.youtube.com/watch?v=EHCGAZBbB88", "Sliding Window: Fixed Size") | I13: 25 | J13: Untimed | K13: Fixed window slide | L13: LC 643 Maximum Average Subarray I | M13: E | N13: 15 | O13: LC 1876 Substrings of Size Three with Distinct Characters | P13: E | Q13: 15 | R13: LC 724 Find Pivot Index | S13: Write the sliding window sum update step: sum += incoming - outgoing from memory | T13: Did you avoid recomputing the sum of K elements at each step? | U13: Sliding rate-limit windows and token buckets in API gateways | V13: Fixed window sliding | AB13: =HYPERLINK("https://www.youtube.com/watch?v=EHCGAZBbB88", "▶ Watch (Aditya Verma) ↗")
A14: 13 | B14: 2 | C14: 46308 | D14: Understand dynamic window expansion and shrinking based on monotonic conditions | E14: Sliding window (variable) | F14: Expand right pointer; while (condition violated) shrink left pointer; tracking window metrics | G14: YES | H14: =HYPERLINK("https://www.youtube.com/watch?v=cyu_nuW5utA", "Sliding Window: Variable Size") | I14: 25 | J14: Untimed | K14: Expand right, shrink left | L14: LC 209 Minimum Size Subarray Sum | M14: M | N14: 25 | O14: LC 1004 Max Consecutive Ones III | P14: M | Q14: 25 | R14: LC 643 Maximum Average Subarray I | S14: Write the expand and shrink loop conditions for LC 209; explain why total steps is 2*N -> O(N) | T14: Did you understand why the nested while loop still yields O(N) amortized time? | U14: Dynamic queue window sizing under varying network packet congestion | V14: Variable window invariants | AB14: =HYPERLINK("https://www.youtube.com/watch?v=cyu_nuW5utA", "▶ Watch (Aditya Verma) ↗")
A15: 14 | B15: 2 | C15: 46309 | D15: Comprehensive test across all linear foundations: Vectors, Hashing, Two Pointers, Prefix Sum, Sliding Window | E15: Review/audit | F15: Pattern discrimination: recognizing whether a problem requires Hashing, Two Pointers, or Sliding Window | G15: NO | H15: - | J15: Timed-40 | K15: No hints | L15: LC 1 Two Sum | M15: E | N15: 12 | O15: LC 724 Find Pivot Index | P15: E | Q15: 15 | R15: ReviewQueue top 3 | S15: Draw a 3-way decision tree: When to use Two Pointers vs Sliding Window vs Hash Map | T15: Did you solve both problems within 30 minutes without looking at past code? | U15: Linear scan optimization is the foundation for GPU memory streaming | V15: Linear foundations mastery | AB15: —
A16: 15 | B16: 3 | C16: 46310 | D16: Binary search correctness from invariants, not from memory of a template | E16: Binary search (index) | F16: Half-open invariant; lower_bound vs upper_bound; off-by-one elimination | G16: YES | H16: =HYPERLINK("https://www.youtube.com/watch?v=DfljaUwZsOk", "Binary search boundaries: invariant-first approach") | I16: 25 | J16: Untimed | K16: Tutorial before | L16: LC 704 Binary Search | M16: E | N16: 10 | O16: LC 34 Find First and Last Position | P16: M | Q16: 25 | R16: LC 1004 Max Consecutive Ones III | S16: Write lower_bound AND upper_bound from memory with NO template; state the invariant of each | T16: Bug-free without a template? If no, that is F6 and it costs you in every future BS problem. | U16: Index lookups in sorted on-disk structures (SSTables, sorted file offsets) | V16: Boundary reasoning from invariants | AB16: =HYPERLINK("https://www.youtube.com/watch?v=DfljaUwZsOk", "▶ Watch (Padho with Pratyush) ↗")
A17: 16 | B17: 3 | C17: 46311 | D17: Binary search on broken monotonicity - rotated array | E17: Binary search (rotated) | F17: Detect the sorted half; prove the test is correct; handle duplicates | G17: NO | H17: - | J17: Untimed | K17: 1 hint @20min | L17: LC 33 Search in Rotated Sorted Array | M17: M | N17: 30 | O17: LC 153 Find Minimum in Rotated Sorted Array | P17: M | Q17: 20 | R17: LC 34 Find First and Last Position | S17: Explain which half is sorted, why the test is correct, and what breaks with duplicates (LC 81) | T17: Did you enumerate the 4 cases before coding, or debug into a solution? | U17: Circular buffers; ring-index math in lock-free queues | V17: Partial-order search | AB17: —
A18: 17 | B18: 3 | C18: 46312 | D18: Binary search ON THE ANSWER - the single highest-leverage pattern in this program | E18: Binary search on answer | F18: Monotone predicate feasible(x); search value space not index space | G18: YES | H18: =HYPERLINK("https://www.youtube.com/watch?v=C2apEw9pgtw", "Binary search on answer / parametric search") | I18: 25 | J18: Untimed | K18: Tutorial before, then solve alone with no help | L18: LC 875 Koko Eating Bananas | M18: M | N18: 25 | O18: LC 1011 Capacity to Ship Packages Within D Days | P18: M | Q18: 25 | R18: LC 33 Search in Rotated Sorted Array | S18: Write the 3 validity conditions for BS-on-answer: answer space bounded, predicate monotone, predicate fast | T18: Do 'minimize the maximum' and 'maximize the minimum' now trigger this pattern instantly? | U18: Capacity planning, autoscaling thresholds, batch-size selection, quota fitting, SLO optimization | V18: Parametric search | AB18: =HYPERLINK("https://www.youtube.com/watch?v=C2apEw9pgtw", "▶ Watch (Abdul Bari) ↗")
A19: 18 | B19: 3 | C19: 46313 | D19: [2-SOL] Harder predicate design - construct feasible() when it is not obvious | E19: Binary search on answer (hard predicates) | F19: feasible() construction; proving monotonicity | G19: NO | H19: - | J19: Untimed | K19: 1 hint @25min | L19: LC 410 Split Array Largest Sum | M19: H | N19: 40 | O19: LC 1482 Minimum Number of Days to Make m Bouquets | P19: M | Q19: 25 | R19: LC 875 Koko Eating Bananas | S19: Rederive feasible() for LC 410 with no notes; prove its monotonicity; find the DP alternative O(kn^2) | T19: Was your predicate actually monotone? Prove it - unproven predicates are guesses. | U19: Sharding load across workers under a max-per-worker bound; SLO-constrained batching | V19: Predicate construction + second solution (DP) | AB19: —
A20: 19 | B20: 3 | C20: 46314 | D20: Binary search where input is not a flat array; second solutions required | E20: Binary search (abstract) + partition | F20: count(<=x) counting search; binary search over a 2D structure | G20: NO | H20: - | J20: Untimed | K20: 1 hint @30min | L20: LC 378 Kth Smallest in a Sorted Matrix | M20: M | N20: 35 | O20: LC 4 Median of Two Sorted Arrays | P20: H | Q20: 45 | R20: LC 410 Split Array Largest Sum | S20: Explain BOTH: count(<=x) search and the O(log(min(m,n))) partition method for LC 4 | T20: Two genuinely different solutions found? If only one, you are template-locked. | U20: Quantile estimation over sorted shards; distributed k-th element queries | V20: Second-solution habit | AB20: —
A21: 20 | B21: 3 | C21: 46315 | D21: Blind mix: sort, window, or binary search - eliminate from constraints first | E21: Blind (W1-W3) | F21: Approach elimination from constraint reading; recognition speed | G21: NO | H21: - | J21: Timed-50 | K21: None | L21: LC 162 Find Peak Element | M21: M | N21: 20 | O21: LC 2300 Successful Pairs of Spells and Potions | P21: M | Q21: 25 | R21: LC 4 Median of Two Sorted Arrays | S21: For each: write the single constraint clue that revealed the pattern | T21: Time-to-pattern < 4 min for both? Record both numbers in MockInterviews. | U21: Threshold queries over sorted metric arrays in monitoring systems | V21: Fast elimination from constraint reading | AB21: —
A22: 21 | B22: 3 | C22: 46316 | D22: Week 3 - complexity drilling as a first-class skill (10 reps, no coding) | E22: Review/complexity | F22: Estimate TC/SC BEFORE coding; lower bounds; 10 targeted dreps | G22: NO | H22: - | J22: Untimed | K22: None | L22: 10 complexity drills: read problem -> brute TC -> target TC -> SC -> lower bound. No coding. | M22: - | N22: 30 | O22: Retest your 2 worst W3 problems | P22: M | Q22: 40 | R22: ReviewQueue top 3 | S22: Rederive the 3 BS-on-answer validity conditions; write 3 problems where it does NOT apply | T22: Complexity accuracy /10. Below 7 means F5 is your bottleneck, not algorithms. | U22: - | V22: Complexity fluency | AB22: —
A23: 22 | B23: 4 | C23: 46317 | D23: Sorting as preprocessing: what invariant does the sort create? | E23: Sort + linear scan | F23: Sort manufactures monotonicity you can exploit greedily; sort KEY matters | G23: NO | H23: - | J23: Untimed | K23: 1 hint @20min | L23: LC 56 Merge Intervals | M23: M | N23: 25 | O23: LC 435 Non-Overlapping Intervals | P23: M | Q23: 25 | R23: LC 2300 Successful Pairs of Spells and Potions | S23: State exactly what invariant the sort created in each problem, and why the sort key (start vs end) matters | T23: Did you justify the sort key, or try both until tests passed? | U23: Log compaction ordering; dedup windows; merging of sorted shard outputs in LSM-trees | V23: Preprocessing mindset | AB23: —
A24: 23 | B24: 4 | C24: 46318 | D24: Interval reasoning and sweep line - two equivalent views | E24: Intervals/sweep line | F24: Events +1/-1; heap-of-end-times as equivalent model | G24: YES | H24: =HYPERLINK("https://www.youtube.com/watch?v=Nq7ok-OyEpg", "Sweep line and event counting") | I24: 20 | J24: Untimed | K24: Tutorial before | L24: LC 253 Meeting Rooms II | M24: M | N24: 30 | O24: LC 1094 Car Pooling | P24: M | Q24: 20 | R24: LC 56 Merge Intervals | S24: Prove heap-of-ends and sweep-line give identical answers; state both complexities; derive the tie-breaking rule | T24: Two solutions for one problem - that is the target habit from today forward. | U24: Concurrent resource counting (GPU slots, DB connections); admission control | V24: Sweep-line modelling | AB24: =HYPERLINK("https://www.youtube.com/watch?v=Nq7ok-OyEpg", "▶ Watch (Striver) ↗")
A25: 24 | B25: 4 | C25: 46319 | D25: Monotonic stack from first principles - the amortized argument is everything | E25: Monotonic stack | F25: A pop resolves one answer; total pops <= n -> amortized O(n); stack holds invariant | G25: YES | H25: =HYPERLINK("https://www.youtube.com/watch?v=wiOo4DC5GGA", "Monotonic stack from first principles (amortized)") | I25: 25 | J25: Untimed | K25: Tutorial before | L25: LC 739 Daily Temperatures | M25: M | N25: 25 | O25: LC 503 Next Greater Element II (circular) | P25: M | Q25: 20 | R25: LC 253 Meeting Rooms II | S25: Explain the amortized bound out loud; state what the stack contains at any moment (the invariant) | T25: Could you explain the amortization to an interviewer in 60 seconds? Practise aloud. | U25: Detecting monotone breaks in metric streams (backpressure onset, latency spikes) | V25: Amortized analysis | AB25: =HYPERLINK("https://www.youtube.com/watch?v=wiOo4DC5GGA", "▶ Watch (Padho with Pratyush) ↗")
A26: 25 | B26: 4 | C26: 46320 | D26: Monotonic stack on spans and areas - boundary-span thinking | E26: Monotonic stack (boundaries) | F26: previous-smaller / next-smaller -> span formula; equal-element handling | G26: NO | H26: - | J26: Untimed | K26: 1 hint @30min | L26: LC 84 Largest Rectangle in Histogram | M26: H | N26: 40 | O26: LC 907 Sum of Subarray Minimums | P26: M | Q26: 35 | R26: LC 739 Daily Temperatures | S26: Derive width = right - left - 1 yourself; explain the equal-element double-counting fix for LC 907 | T26: Did you handle equal elements correctly BY DESIGN, or by trial and error? | U26: Peak-utilization rectangles over time-series capacity graphs; histogram-based alerting | V26: Boundary-span thinking | AB26: —
A27: 26 | B27: 4 | C27: 46321 | D27: [2-SOL] Monotonic deque + solve LC 42 Trapping Rain Water three ways | E27: Monotonic deque | F27: Deque holds only viable candidates in decreasing order; window max in O(n) | G27: NO | H27: - | J27: Untimed | K27: 1 hint @25min | L27: LC 239 Sliding Window Maximum | M27: H | N27: 30 | O27: LC 42 Trapping Rain Water (3 solutions) | P27: M | Q27: 30 | R27: LC 84 Largest Rectangle in Histogram | S27: Solve LC 42 three ways: prefix-max arrays, two pointers, monotonic stack. Compare TC/SC for each. | T27: How many of the three did you find WITHOUT help? That is your second-solution score. | U27: Rolling max latency over stream windows; watermarking in streaming pipelines | V27: Multi-solution flexibility | AB27: —
A28: 27 | B28: 4 | C28: 46322 | D28: Blind mix across weeks 1-4 - cross-pattern discrimination under time | E28: Blind (W1-W4 cross) | F28: Speed of pattern recognition; avoiding false pattern matches | G28: NO | H28: - | J28: Timed-55 | K28: None | L28: LC 621 Task Scheduler | M28: M | N28: 30 | O28: LC 452 Minimum Number of Arrows to Burst Balloons | P28: M | Q28: 20 | R28: LC 239 Sliding Window Maximum | S28: Write one-line recognition cues for ALL patterns from weeks 1-4 (~14 cues total) | T28: First-try correct pattern rate this week. Below 60% -> recognition, not knowledge, is the gap. | U28: Cooldown-constrained job scheduling = real scheduler behaviour in ML training systems | V28: Recognition speed | AB28: —
A29: 28 | B29: 4 | C29: 46323 | D29: MONTH 1 DIAGNOSTIC - 3 unlabelled, 90 min, zero hints, verbal explanation required | E29: Diagnostic | F29: Measure, do not learn. No pattern labels. No hints. | G29: NO | H29: - | J29: Diagnostic | K29: None | L29: LC 918 Max Sum Circular Subarray | M29: M | N29: 30 | O29: LC 795 Number of Subarrays with Bounded Max + LC 581 Shortest Unsorted Continuous Subarray (unlabelled) | P29: M | Q29: 60 | R29: - | S29: For each: log time-to-pattern, final TC/SC, correctness, hint-free, explanation quality | T29: Fill MockInterviews rows now. This is your baseline - do not soften any score. | U29: - | V29: Baseline measurement | AB29: —
A30: 29 | B30: 5 | C30: 46324 | D30: Heap mental model: partial order is enough; when to use heap vs sort | E30: Heap/top-K | F30: Why heap beats full sort when k<<n; heapify is O(n); min-heap vs max-heap | G30: YES | H30: =HYPERLINK("https://www.youtube.com/watch?v=NXOOYYwpbg4", "Heaps: sift-up/down, heapify, cost comparison") | I30: 25 | J30: Untimed | K30: Tutorial before | L30: LC 215 Kth Largest Element in Array | M30: M | N30: 25 | O30: LC 973 K Closest Points to Origin | P30: M | Q30: 20 | R30: LC 621 Task Scheduler | S30: State when sorting beats a heap and vice versa, with both complexities written out explicitly | T30: Can you compute and compare both costs, including constants? That is the skill. | U30: Top-K hot keys, request prioritisation, eviction candidate selection in caches | V30: Cost comparison reasoning | AB30: =HYPERLINK("https://www.youtube.com/watch?v=NXOOYYwpbg4", "▶ Watch (Aditya Verma) ↗")
A31: 30 | B31: 5 | C31: 46325 | D31: Two-heap invariants for streaming statistics | E31: Heap (streaming/online) | F31: Balanced max-heap/min-heap invariant; maintain the balance on every insert | G31: NO | H31: - | J31: Untimed | K31: 1 hint @25min | L31: LC 295 Find Median from Data Stream | M31: H | N31: 35 | O31: LC 1046 Last Stone Weight | P31: E | Q31: 15 | R31: LC 215 Kth Largest Element | S31: Write the two-heap invariant and rebalance rule BEFORE writing any code | T31: Did you define the invariant FIRST? That is the whole skill in streaming structure design. | U31: Online p50/p99 latency estimation without storing all samples; streaming quantiles | V31: Streaming state design | AB31: —
A32: 31 | B32: 5 | C32: 46326 | D32: Heap for k-way merging and greedy scheduling | E32: Heap (k-way merge) | F32: k-way merge; heap of active cursors; where the log k factor comes from | G32: NO | H32: - | J32: Untimed | K32: 1 hint @20min | L32: LC 23 Merge k Sorted Lists | M32: H | N32: 30 | O32: LC 767 Reorganize String | P32: M | Q32: 25 | R32: LC 295 Find Median from Data Stream | S32: Explain where log k comes from; give the divide-and-conquer merge alternative and its TC | T32: Correct TC derived, not guessed? Two algorithms compared? | U32: LSM-tree compaction; merging sorted shard outputs in distributed ML data pipelines | V32: Merge algorithms | AB32: —
A33: 32 | B33: 5 | C33: 46327 | D33: Greedy: the exchange argument - proof, not vibes | E33: Greedy invariants | F33: Exchange argument and staying-ahead argument; constructing counterexamples | G33: YES | H33: =HYPERLINK("https://www.youtube.com/watch?v=2Rr2tW9zvRg", "Proving greedy correctness: exchange and staying-ahead") | I33: 20 | J33: Untimed | K33: Tutorial before | L33: LC 45 Jump Game II | M33: M | N33: 30 | O33: LC 134 Gas Station | P33: M | Q33: 25 | R33: LC 23 Merge k Sorted Lists | S33: Write a full exchange-argument proof for LC 45; write the unique-start argument for LC 134 | T33: Did you PROVE it or trust it? Unproven greedy is the most common hard-interview failure. | U33: Chunked transfer decisions; admission control; retry budget allocation in ML serving | V33: Greedy proof technique | AB33: =HYPERLINK("https://www.youtube.com/watch?v=2Rr2tW9zvRg", "▶ Watch (Abdul Bari) ↗")
A34: 33 | B34: 5 | C34: 46328 | D34: Greedy vs DP - find where greedy breaks by constructing a counterexample | E34: Greedy vs DP | F34: Counterexample construction as a design discipline | G34: NO | H34: - | J34: Untimed | K34: 1 hint @30min | L34: LC 763 Partition Labels | M34: M | N34: 20 | O34: LC 871 Minimum Number of Refueling Stops | P34: H | Q34: 40 | R34: LC 45 Jump Game II | S34: Construct an input where a plausible greedy fails on LC 871; state why the heap-greedy is correct | T34: Can you break your own solution? If you cannot, you cannot trust it. | U34: Checkpoint placement in long ML training runs; spot-instance restart strategy | V34: Adversarial self-testing | AB34: —
A35: 34 | B35: 5 | C35: 46329 | D35: Blind mix: heap vs sort vs greedy vs simulation | E35: Blind (W5 mix) | F35: Cost-based structure selection under time pressure | G35: NO | H35: - | J35: Timed-60 | K35: None | L35: LC 2402 Meeting Rooms III | M35: H | N35: 40 | O35: LC 1834 Single-Threaded CPU | P35: M | Q35: 30 | R35: LC 871 Minimum Number of Refueling Stops | S35: Name the invariant each heap maintains in these problems and why two heaps are needed | T35: Simulation bugs count as F6, not F2 - the pattern is correct, the implementation failed. | U35: This IS a real scheduler: ready-queue + busy-resource queue with release events | V35: Simulation discipline | AB35: —
A36: 35 | B36: 5 | C36: 46330 | D36: Week 5 assessment: weakness-targeted retest | E36: Review/targeted repair | F36: Attack your dominant failure category directly | G36: NO | H36: - | J36: Untimed | K36: Hints allowed | L36: 3 problems from your most frequent failure category this week | M36: M | N36: 45 | O36: WeeklyAssessment + write preventive rules | P36: - | Q36: 20 | R36: ReviewQueue top 4 | S36: Rebuild two-heap median and k-way merge from a blank file | T36: Is your top failure category shrinking week over week? If not, the plan changes. | U36: - | V36: Targeted repair | AB36: —
A37: 36 | B37: 6 | C37: 46331 | D37: Pointer surgery: linked-list invariants - reason before running, no debugger | E37: Linked list pointers | F37: Dummy head; prev/curr discipline; draw state transitions before coding | G37: NO | H37: - | J37: Untimed | K37: 1 hint @20min | L37: LC 206 Reverse Linked List | M37: E | N37: 12 | O37: LC 143 Reorder List | P37: M | Q37: 25 | R37: LC 1834 Single-Threaded CPU | S37: Draw pointer states before/after EACH statement for LC 143 - no debugger allowed | T37: Did you reason through it, or print-debug your way into a solution? | U37: Free lists and intrusive linked lists in memory allocators | V37: Precise state mutation | AB37: —
A38: 37 | B38: 6 | C38: 46332 | D38: [2-SOL] O(1) cache design: compose hashmap + doubly linked list | E38: Design (LRU) | F38: Composing two structures for O(1) on all ops; API drives structure choice | G38: YES | H38: =HYPERLINK("https://www.youtube.com/watch?v=R_Mfw4ew-Vo", "LRU cache design: structure composition from requirements") | I38: 20 | J38: Untimed | K38: Tutorial before | L38: LC 146 LRU Cache | M38: M | N38: 35 | O38: LC 142 Linked List Cycle II | P38: M | Q38: 25 | R38: LC 143 Reorder List | S38: Rebuild LRU from an empty file with no notes; then explain Floyd's cycle detection proof | T38: Can you write a clean LRU in under 20 minutes? This is a baseline infra expectation. | U38: Page cache eviction; KV-store eviction; embedding/feature cache in ML serving | V38: Structure composition from API requirements | AB38: =HYPERLINK("https://www.youtube.com/watch?v=R_Mfw4ew-Vo", "▶ Watch (Striver) ↗")
A39: 38 | B39: 6 | C39: 46333 | D39: Frequency-aware eviction: LFU - minFreq pointer invariant | E39: Design (LFU) | F39: Bucketing by frequency; minFreq can only increase by 1 on access | G39: NO | H39: - | J39: Untimed | K39: 1 hint @30min | L39: LC 460 LFU Cache | M39: H | N39: 45 | O39: LC 362 Design Hit Counter | P39: M | Q39: 20 | R39: LC 146 LRU Cache | S39: Explain the minFreq invariant and why it increases by at most 1 on any access | T39: For an ML feature cache: LRU or LFU? Defend with an access-pattern argument. | U39: Feature-store caching; embedding cache eviction; hot-shard detection in key-value systems | V39: Advanced structure design | AB39: —
A40: 39 | B40: 6 | C40: 46334 | D40: Bit manipulation as set/state encoding | E40: Bit manipulation | F40: Masks as tiny sets; XOR invariants; popcount; iterate subsets | G40: YES | H40: =HYPERLINK("https://www.youtube.com/watch?v=xXKL9YBWgCY", "Bit tricks that actually recur in interviews") | I40: 20 | J40: Untimed | K40: Tutorial before | L40: LC 137 Single Number II | M40: M | N40: 25 | O40: LC 371 Sum of Two Integers | P40: M | Q40: 20 | R40: LC 460 LFU Cache | S40: Explain XOR/counting-bits invariant; write mask ops for add/remove/test/iterate-all-subsets | T40: Do you now see bitmask=tiny-set automatically? You will need this in week 13. | U40: Bitmaps; feature flags; GPU lane masks; bloom-filter bit operations | V40: State compression | AB40: =HYPERLINK("https://www.youtube.com/watch?v=xXKL9YBWgCY", "▶ Watch (Errichto) ↗")
A41: 40 | B41: 6 | C41: 46335 | D41: Design under constraints: iterators, lazy evaluation, rate limits | E41: Design/simulation | F41: Amortized design; lazy vs eager work; iterator cost analysis | G41: NO | H41: - | J41: Untimed | K41: 1 hint @20min | L41: LC 341 Flatten Nested List Iterator | M41: M | N41: 25 | O41: LC 359 Logger Rate Limiter | P41: M | Q41: 20 | R41: LC 137 Single Number II | S41: State the amortized cost of your iterator and why worst-case next() is not O(1) | T41: Was amortized reasoning explicit and stated, or hand-waved? | U41: API rate limiting; streaming iterators; data-loader prefetch in ML training | V41: Amortized design | AB41: —
A42: 41 | B42: 6 | C42: 46336 | D42: Blind mix: pick structures from API requirements, not from habit | E42: Blind (design) | F42: Requirement -> structure mapping; API analysis | G42: NO | H42: - | J42: Timed-60 | K42: None | L42: LC 981 Time Based Key-Value Store | M42: M | N42: 25 | O42: LC 355 Design Twitter | P42: H | Q42: 40 | R42: LC 460 LFU Cache | S42: Write the requirement -> structure -> complexity table you used for each design | T42: Did each structure choice come from a stated API requirement? If not, that is F4. | U42: Versioned KV store = MVCC; social feed fanout = merge of k sorted streams | V42: API-driven design | AB42: —
A43: 42 | B43: 6 | C43: 46337 | D43: Week 6 assessment + MOCK INTERVIEW #1 (2 hints allowed, narrate everything) | E43: Mock interview #1 | F43: Verbal reasoning under observation; explanation quality | G43: NO | H43: - | J43: Timed-45 | K43: 2 hints max | L43: Mock #1: 1 medium problem, narrate every decision aloud, state TC/SC unprompted | M43: M | N43: 45 | O43: WeeklyAssessment + MockInterviews row | P43: - | Q43: 20 | R43: ReviewQueue top 3 | S43: Explain LRU aloud in 3 minutes with no notes; record yourself and listen back once | T43: Score explanation quality 1-5. Silent thinking during a mock is a failure mode. | U43: - | V43: Communication under pressure | AB43: —
A44: 43 | B44: 7 | C44: 46338 | D44: Recursion contracts: write exactly what your function returns, before coding | E44: Tree recursion (contract) | F44: Write the contract; trust the recursion; call stack mental model | G44: YES | H44: =HYPERLINK("https://www.youtube.com/watch?v=jmy0LaGET1I", "Recursion as contract + call stack") | I44: 25 | J44: Untimed | K44: Tutorial before | L44: LC 104 Maximum Depth of Binary Tree | M44: E | N44: 10 | O44: LC 110 Balanced Binary Tree | P44: E | Q44: 20 | R44: LC 981 Time Based Key-Value Store | S44: Write the exact return contract (in plain English) for every recursive function today | T44: Contract before code, or code until tests pass? Be honest. | U44: Recursive dependency evaluation; nested config resolution in ML pipeline systems | V44: Recursive decomposition | AB44: =HYPERLINK("https://www.youtube.com/watch?v=jmy0LaGET1I", "▶ Watch (Striver) ↗")
A45: 44 | B45: 7 | C45: 46339 | D45: The return-more-than-the-answer trick - post-order aggregation | E45: Tree DP (post-order) | F45: Return value upward vs answer updated AT the node - these are different | G45: NO | H45: - | J45: Untimed | K45: 1 hint @25min | L45: LC 543 Diameter of Binary Tree | M45: E | N45: 25 | O45: LC 124 Binary Tree Maximum Path Sum | P45: H | Q45: 35 | R45: LC 110 Balanced Binary Tree | S45: Explain the difference between 'best path through this node' and 'best downward path from this node' | T45: Did you separate the two quantities BEFORE coding? | U45: Aggregating metrics up a topology/ownership tree in a distributed system | V45: Post-order aggregation | AB45: —
A46: 45 | B46: 7 | C46: 46340 | D46: BST invariant: the ordering IS the information | E46: BST/ordering | F46: Range constraints propagated top-down; in-order traversal is sorted | G46: NO | H46: - | J46: Untimed | K46: 1 hint | L46: LC 98 Validate Binary Search Tree | M46: M | N46: 25 | O46: LC 230 Kth Smallest Element in a BST | P46: M | Q46: 20 | R46: LC 124 Binary Tree Maximum Path Sum | S46: State the (low, high) range-invariant proof; construct the input that breaks parent-child comparison alone | T46: Did you exploit the ordering property, or brute-force with a set? | U46: Ordered indexes; range scans; B-tree node invariants | V46: Invariant exploitation | AB46: —
A47: 46 | B47: 7 | C47: 46341 | D47: Tree construction and structural identity | E47: Tree recursion (construct) | F47: Split by root; index map removes linear search; O(n) construction | G47: NO | H47: - | J47: Untimed | K47: 1 hint @25min | L47: LC 105 Construct Tree from Preorder and Inorder | M47: M | N47: 35 | O47: LC 572 Subtree of Another Tree | P47: E | Q47: 20 | R47: LC 98 Validate BST | S47: State TC before and after adding the inorder index map; verify correctness on an example | T47: Did you find the O(n) version yourself, or need a hint? | U47: Serialization formats; tree/config diffing; AST construction in compilers | V47: Recursive construction | AB47: —
A48: 47 | B48: 7 | C48: 46342 | D48: BFS on trees; designing an encoding for serialization | E48: BFS levels/serialization | F48: Level-order state; null markers as an encoding decision; grammar first | G48: NO | H48: - | J48: Untimed | K48: 1 hint @25min | L48: LC 199 Binary Tree Right Side View | M48: M | N48: 20 | O48: LC 297 Serialize and Deserialize Binary Tree | P48: H | Q48: 35 | R48: LC 105 Construct Tree from Preorder and Inorder | S48: Rebuild serialize/deserialize from memory; define the encoding grammar BEFORE coding | T48: Did you define the encoding format before writing any code, or improvise? | U48: Wire formats; checkpoint serialization; graph snapshotting in ML systems | V48: Encoding design | AB48: —
A49: 48 | B49: 7 | C49: 46343 | D49: Blind tree mix: DFS or BFS, and why - state your reason before implementing | E49: Blind (trees) | F49: Traversal choice driven by what information you need | G49: NO | H49: - | J49: Timed-50 | K49: None | L49: LC 236 Lowest Common Ancestor | M49: M | N49: 25 | O49: LC 1448 Count Good Nodes in Binary Tree | P49: M | Q49: 20 | R49: LC 297 Serialize and Deserialize Binary Tree | S49: Write a 3-line DFS-vs-BFS decision rule you will actually use from today | T49: First-try correctness on both? Log time-to-pattern. | U49: Ancestor/ownership queries in dependency trees; LCA in job-graph analysis | V49: Traversal selection | AB49: —
A50: 49 | B50: 7 | C50: 46344 | D50: Week 7 assessment - tree retention with zero notes | E50: Review/audit | F50: Deep tree retention check | G50: NO | H50: - | J50: Untimed | K50: None | L50: Retest 3 tree problems from W7, no notes | M50: M | N50: 45 | O50: WeeklyAssessment | P50: - | Q50: 20 | R50: ReviewQueue top 3 | S50: Rederive diameter (LC 543) and max-path-sum (LC 124) from scratch; write both contracts first | T50: Has the 'write the contract first' habit actually formed? Show evidence. | U50: - | V50: Retention | AB50: —
A51: 50 | B51: 8 | C51: 46345 | D51: Tries: exploit shared prefixes; know when a trie is NOT worth it | E51: Trie | F51: Character-indexed tree; memory vs lookup trade-off vs hashset | G51: YES | H51: =HYPERLINK("https://www.youtube.com/watch?v=p7-9UvDQZ3w", "Trie construction and use") | I51: 20 | J51: Untimed | K51: Tutorial before | L51: LC 208 Implement Trie (Prefix Tree) | M51: M | N51: 25 | O51: LC 139 Word Break | P51: M | Q51: 30 | R51: LC 236 Lowest Common Ancestor | S51: Compare trie vs hashset on memory and lookup TC; name a concrete case where hashset wins | T51: Do you know the TRADE-OFF, or just that tries exist? | U51: Autocomplete; tokenizer vocabularies; longest-prefix-match routing in networking | V51: Structure trade-offs | AB51: =HYPERLINK("https://www.youtube.com/watch?v=p7-9UvDQZ3w", "▶ Watch (Striver) ↗")
A52: 51 | B52: 8 | C52: 46346 | D52: Trie + DFS: pruning is the entire point | E52: Trie + backtracking | F52: Prune the search space using shared prefix structure | G52: NO | H52: - | J52: Untimed | K52: 1 hint @30min | L52: LC 212 Word Search II | M52: H | N52: 45 | O52: LC 211 Design Add and Search Words Data Structure | P52: M | Q52: 25 | R52: LC 208 Implement Trie | S52: Explain precisely how the trie prunes DFS branches and what the TC bound becomes with pruning | T52: Did you see pruning as the PURPOSE of the trie, or bolt it on afterwards? | U52: Prefix routing tables; vocabulary matching in tokenizers and NLP pipelines | V52: Search pruning | AB52: —
A53: 52 | B53: 8 | C53: 46347 | D53: Cross-pattern fusion: trees + prefix hashing (week-1 reappears in trees) | E53: Tree recursion + prefix-hash | F53: Prefix sums along root-to-node path; undo the count on backtrack | G53: NO | H53: - | J53: Untimed | K53: 1 hint @25min | L53: LC 437 Path Sum III | M53: M | N53: 35 | O53: LC 337 House Robber III | P53: M | Q53: 30 | R53: LC 212 Word Search II | S53: Explain the path-prefix map and why you must DECREMENT on the way back up the recursion | T53: Did you connect week-1 prefix hashing to trees ON YOUR OWN? | U53: Hierarchical cost accounting; per-path aggregation in distributed tracing | V53: Cross-pattern fusion | AB53: —
A54: 53 | B54: 8 | C54: 46348 | D54: Interleaving weeks 1-7, hard-leaning, unlabelled, timed | E54: Blind (W1-W7 cross) | F54: Full-range transfer recognition; unfamiliar problem structure | G54: NO | H54: - | J54: Timed-60 | K54: None | L54: LC 549 Binary Tree Longest Consecutive Sequence II | M54: M | N54: 30 | O54: LC 987 Vertical Order Traversal of a Binary Tree | P54: H | Q54: 35 | R54: LC 437 Path Sum III | S54: For each: which EARLIER pattern did it reuse? Name it explicitly. | T54: Cross-week transfer is the real test of retention vs surface memorisation. | U54: - | V54: Transfer | AB54: —
A55: 54 | B55: 8 | C55: 46349 | D55: Explanation training: compress 5 patterns to 90 seconds each - verbal clarity | E55: Communication | F55: Compression forces genuine understanding; verbal explanation tests mastery | G55: NO | H55: - | J55: Timed-40 | K55: None | L55: Explain 5 patterns aloud, recorded, 90s each (trigger, insight, invariant, TC) | M55: - | N55: 30 | O55: Retest 1 hard problem while narrating continuously | P55: H | Q55: 40 | R55: ReviewQueue top 3 | S55: No-notes verbal explanation of monotonic-stack amortization and BS-on-answer validity | T55: Would a sceptical interviewer follow your explanation? Listen to the recording once. | U55: Design reviews; RFC defence; on-call handover documentation | V55: Verbal clarity | AB55: —
A56: 55 | B56: 8 | C56: 46350 | D56: Failure-driven repair day - repair, do not explore new territory | E56: Targeted repair | F56: Fix the failure category, not a new pattern | G56: NO | H56: - | J56: Untimed | K56: Hints allowed | L56: 3 problems from your worst 2 failure categories | M56: M | N56: 50 | O56: Write/refresh preventive rules in FailureLog | P56: - | Q56: 20 | R56: All Mastered=No from W5-W7 | S56: Restate your 5 preventive rules from memory; verify they fired during today's solving | T56: Did the rules actually prevent the mistake? Rules that never fire are decoration. | U56: - | V56: Error correction | AB56: —
A57: 56 | B57: 8 | C57: 46351 | D57: MONTH 2 DIAGNOSTIC - 3 unlabelled, 100 min, verbal + complexity required | E57: Diagnostic | F57: Measure against Month 1. No pattern labels. No hints. | G57: NO | H57: - | J57: Diagnostic | K57: None | L57: LC 315 Count of Smaller Numbers After Self | M57: H | N57: 34 | O57: LC 1110 Delete Nodes and Return Forest + LC 1396 Design Underground System (unlabelled) | P57: M | Q57: 66 | R57: - | S57: Log time-to-pattern, TC/SC, hints used, explanation quality for each | T57: Compare ALL numbers to Month 1. Time-to-pattern must be dropping. If not, recognition training increases. | U57: - | V57: Progress measurement | AB57: —
A58: 57 | B58: 9 | C58: 46352 | D58: Graph modelling: what are the nodes and edges - model FIRST, algorithm second | E58: Graph traversal | F58: Grid-as-graph; visited discipline - mark on PUSH, not on pop | G58: YES | H58: =HYPERLINK("https://www.youtube.com/watch?v=13m9ZCB8gjw", "Graph representations + BFS/DFS; visited discipline") | I58: 25 | J58: Untimed | K58: Tutorial before | L58: LC 200 Number of Islands | M58: M | N58: 25 | O58: LC 133 Clone Graph | P58: M | Q58: 25 | R58: LC 437 Path Sum III | S58: State when to mark visited (push vs pop); construct the input that causes exponential blowup if wrong | T58: Did you avoid revisit bugs by design, or by luck? | U58: Topology discovery; cluster membership; service-graph crawling in MLOps | V58: Graph modelling | AB58: =HYPERLINK("https://www.youtube.com/watch?v=13m9ZCB8gjw", "▶ Watch (Padho with Pratyush) ↗")
A59: 58 | B59: 9 | C59: 46353 | D59: Multi-source BFS and reversing the direction of thought | E59: BFS (multi-source/reverse) | F59: Seed all sources at level 0; think from the boundary inward | G59: NO | H59: - | J59: Untimed | K59: 1 hint @20min | L59: LC 994 Rotting Oranges | M59: M | N59: 25 | O59: LC 417 Pacific Atlantic Water Flow | P59: M | Q59: 30 | R59: LC 200 Number of Islands | S59: Explain why multi-source BFS is still O(V+E); why reverse traversal simplifies LC 417 | T59: Did you reverse the direction yourself, or brute-force per cell? | U59: Failure propagation / blast-radius analysis in a distributed cluster | V59: Direction inversion | AB59: —
A60: 59 | B60: 9 | C60: 46354 | D60: Union-Find: connectivity without full traversal - write it cold in 5 minutes | E60: Union Find | F60: Path compression + union by size; near-O(1) amortized; write it from memory | G60: YES | H60: =HYPERLINK("https://www.youtube.com/watch?v=dBGUmUQhjaM", "DSU with both optimizations (path compression + union by size)") | I60: 25 | J60: Untimed | K60: Tutorial before | L60: LC 547 Number of Provinces | M60: M | N60: 20 | O60: LC 684 Redundant Connection | P60: M | Q60: 25 | R60: LC 994 Rotting Oranges | S60: Write DSU from memory in under 5 minutes; state amortized complexity; why compression alone is insufficient | T60: Can you write DSU cold? It reappears in weeks 10 and 13. | U60: Cluster membership; shard grouping; entity dedup; dynamic connectivity under edge streams | V60: Near-O(1) connectivity | AB60: =HYPERLINK("https://www.youtube.com/watch?v=dBGUmUQhjaM", "▶ Watch (Striver) ↗")
A61: 60 | B61: 9 | C61: 46355 | D61: DSU for grouping and incremental connectivity - when DSU beats repeated BFS | E61: Union Find (advanced) | F61: DSU with labels; offline/incremental processing; streaming edge sets | G61: NO | H61: - | J61: Untimed | K61: 1 hint @30min | L61: LC 721 Accounts Merge | M61: M | N61: 35 | O61: LC 827 Making a Large Island | P61: H | Q61: 40 | R61: LC 547 Number of Provinces | S61: Explain why DSU beats repeated BFS when edges ARRIVE over time | T61: Right structure for a streaming edge set? Distinguish this from F4. | U61: Incremental cluster formation; dynamic membership in ML job schedulers | V61: Incremental algorithms | AB61: —
A62: 61 | B62: 9 | C62: 46356 | D62: Topological order: dependency resolution - know TWO implementations | E62: Topological sort | F62: Kahn's in-degree invariant; DFS colours for cycle detection | G62: YES | H62: =HYPERLINK("https://www.youtube.com/watch?v=asbcE9mZz_U", "Topo sort: Kahn + DFS colours; cycle detection in both") | I62: 20 | J62: Untimed | K62: Tutorial before | L62: LC 207 Course Schedule | M62: M | N62: 25 | O62: LC 210 Course Schedule II | P62: M | Q62: 25 | R62: LC 721 Accounts Merge | S62: State the in-degree invariant; explain cycle detection in BOTH Kahn and DFS-colours | T62: Do you know two implementations, or one memorised loop? | U62: DAG job scheduling; build systems; ML pipeline orchestration (Airflow-style DAGs) | V62: Dependency reasoning | AB62: =HYPERLINK("https://www.youtube.com/watch?v=asbcE9mZz_U", "▶ Watch (Padho with Pratyush) ↗")
A63: 62 | B63: 9 | C63: 46357 | D63: Blind graph mix: traversal vs DSU vs topological - from problem shape only | E63: Blind (graphs) | F63: Selecting the graph tool from the structure of the question | G63: NO | H63: - | J63: Timed-60 | K63: None | L63: LC 269 Alien Dictionary | M63: H | N63: 45 | O63: LC 310 Minimum Height Trees | P63: M | Q63: 30 | R63: LC 210 Course Schedule II | S63: Which exact signal told you 'topological'? Which told you 'peel leaves layer by layer'? | T63: Recognition speed on graphs - log both times. | U63: Version-ordering inference; dependency inference from build observations | V63: Recognition | AB63: —
A64: 63 | B64: 9 | C64: 46358 | D64: Week 9 assessment - graph retention | E64: Review/audit | F64: Graph retention without notes | G64: NO | H64: - | J64: Untimed | K64: None | L64: Retest 3 graph problems, no notes | M64: M | N64: 45 | O64: WeeklyAssessment | P64: - | Q64: 20 | R64: ReviewQueue top 3 | S64: Rebuild Kahn's algorithm and DSU from a blank file; both under 10 minutes total | T64: Score graph modelling 1-5. Modelling errors cause more graph failures than algorithm errors. | U64: - | V64: Retention | AB64: —
A65: 64 | B65: 10 | C65: 46359 | D65: Unweighted shortest path = BFS - prove why first-visit is final | E65: BFS shortest path | F65: Layered distances; first-visit optimality argument; state-graph edge count | G65: NO | H65: - | J65: Untimed | K65: 1 hint @25min | L65: LC 127 Word Ladder | M65: H | N65: 40 | O65: LC 752 Open the Lock | P65: M | Q65: 30 | R65: LC 269 Alien Dictionary | S65: Explain why the first time BFS reaches a node the distance is final; state the implicit-graph edge count | T65: Was your bottleneck the modelling (edges) or the search algorithm? | U65: Network hop counts; dependency depth; minimum transformation steps in config migration | V65: State-graph modelling | AB65: —
A66: 65 | B66: 10 | C66: 46360 | D66: State-space search: state is more than position | E66: State-space BFS | F66: Compound state encoding; visited MUST be keyed on the FULL state | G66: YES | H66: =HYPERLINK("https://www.youtube.com/watch?v=iTBaI90lpDQ", "State-space search and encoding") | I66: 20 | J66: Untimed | K66: Tutorial before | L66: LC 1293 Shortest Path in Grid with Obstacles Elimination | M66: H | N66: 40 | O66: LC 433 Minimum Genetic Mutation | P66: M | Q66: 25 | R66: LC 127 Word Ladder | S66: Write your state tuple, count the state space size, and derive TC from the count | T66: Was visited keyed on the FULL state? This single mistake invalidates most attempts. | U66: Scheduler/config state exploration; rollout planning in deployment systems | V66: State design | AB66: =HYPERLINK("https://www.youtube.com/watch?v=iTBaI90lpDQ", "▶ Watch (take U forward) ↗")
A67: 66 | B67: 10 | C67: 46361 | D67: Dijkstra: greedy + priority queue - know the correctness proof | E67: Dijkstra | F67: Relaxation; popped distance is final (requires non-negative weights) | G67: YES | H67: =HYPERLINK("https://www.youtube.com/watch?v=EgI5nU9etnU", "Dijkstra: correctness proof and implementation") | I67: 25 | J67: Untimed | K67: Tutorial before | L67: LC 743 Network Delay Time | M67: M | N67: 30 | O67: LC 1514 Path with Maximum Probability | P67: M | Q67: 25 | R67: LC 752 Open the Lock | S67: Prove the popped-node invariant; construct a negative-weight counterexample | T67: Do you know WHY negative edges break Dijkstra? If not, you memorised an implementation. | U67: Latency-aware routing; cost-based placement; weighted service-dependency graphs | V67: Weighted shortest path | AB67: =HYPERLINK("https://www.youtube.com/watch?v=EgI5nU9etnU", "▶ Watch (NeetCode) ↗")
A68: 67 | B68: 10 | C68: 46362 | D68: [2-SOL] Dijkstra variants: change the objective - min-max, 0-1 BFS | E68: Dijkstra variants/0-1 BFS | F68: Min-max objectives; deque BFS for 0/1 weights; binary-search + BFS alternative | G68: NO | H68: - | J68: Untimed | K68: 1 hint @30min | L68: LC 778 Swim in Rising Water | M68: H | N68: 40 | O68: LC 1631 Path with Minimum Effort | P68: M | Q68: 30 | R68: LC 743 Network Delay Time | S68: Contrast sum-objective vs min-max objective; give binary-search+BFS alternative and its TC | T68: Did you find the second solution (BS + BFS) as well? | U68: Bottleneck-bandwidth routing; worst-link-aware placement in distributed ML clusters | V68: Objective transformation | AB68: —
A69: 68 | B69: 10 | C69: 46363 | D69: Constrained shortest paths: layers = DP over rounds | E69: Shortest path (constrained) | F69: Bellman-Ford rounds; k-stop constraint as a DP dimension | G69: NO | H69: - | J69: Untimed | K69: 1 hint @25min | L69: LC 787 Cheapest Flights Within K Stops | M69: M | N69: 35 | O69: LC 332 Reconstruct Itinerary | P69: H | Q69: 35 | R69: LC 778 Swim in Rising Water | S69: Explain why exactly k+1 relaxation rounds solve the k-stop constraint; state the full DP state | T69: Did you see it as DP over layers rather than 'Dijkstra with a hack'? | U69: Multi-hop routing under hop limits; bounded-retry path planning | V69: DP-graph bridge | AB69: —
A70: 69 | B70: 10 | C70: 46364 | D70: Blind hard mix: graphs + earlier patterns, hard-leaning | E70: Blind (hard W1-W10) | F70: Full-range recognition under time; composure on hards | G70: NO | H70: - | J70: Timed-60 | K70: None | L70: LC 773 Sliding Puzzle | M70: H | N70: 45 | O70: LC 802 Find Eventual Safe States | P70: M | Q70: 25 | R70: LC 787 Cheapest Flights Within K Stops | S70: For each: name the invariant the solution depends on, in one sentence | T70: Independent solve rate on hard problems - this is now tracked. | U70: - | V70: Hard-problem composure | AB70: —
A71: 70 | B71: 10 | C71: 46365 | D71: Week 10 assessment + MOCK INTERVIEW #2 (1 hint, 45 min) | E71: Mock interview #2 | F71: Medium-hard under pressure with narration | G71: NO | H71: - | J71: Timed-45 | K71: 1 hint max | L71: Mock #2: 1 medium-hard problem, narrate everything, state TC/SC, answer 1 follow-up | M71: H | N71: 45 | O71: WeeklyAssessment + failure clustering | P71: - | Q71: 25 | R71: ReviewQueue top 3 | S71: Explain Dijkstra in 2 minutes including why a priority queue is required | T71: Score TC/SC accuracy under pressure. Pressure-only errors are F10 - they need mock reps, not theory. | U71: - | V71: Pressure performance | AB71: —
A72: 71 | B72: 11 | C72: 46366 | D72: Backtracking skeleton: choose/explore/unchoose - count the leaves for TC | E72: Backtracking | F72: Decision tree; state restoration; count tree leaves to derive TC | G72: YES | H72: =HYPERLINK("https://www.youtube.com/watch?v=pcKY4hjDrxk", "Backtracking template + complexity counting") | I72: 25 | J72: Untimed | K72: Tutorial before | L72: LC 78 Subsets | M72: M | N72: 20 | O72: LC 39 Combination Sum | P72: M | Q72: 25 | R72: LC 802 Find Eventual Safe States | S72: Draw the recursion tree for a small input; count nodes/leaves; derive TC from the count | T72: Can you compute backtracking complexity? Writing 'exponential' and hoping is not enough. | U72: Config/hyperparameter enumeration; feasible-placement search in resource allocators | V72: Enumeration control | AB72: =HYPERLINK("https://www.youtube.com/watch?v=pcKY4hjDrxk", "▶ Watch (Abdul Bari) ↗")
A73: 72 | B73: 11 | C73: 46367 | D73: Duplicate handling and canonical order in backtracking | E73: Backtracking (dedup) | F73: Sort + skip-equal-at-same-depth rule; prove no distinct result is lost | G73: NO | H73: - | J73: Untimed | K73: 1 hint | L73: LC 90 Subsets II | M73: M | N73: 25 | O73: LC 47 Permutations II | P73: M | Q73: 25 | R73: LC 39 Combination Sum | S73: State the dedup rule precisely and argue no distinct result is lost | T73: Did you DERIVE the skip rule, or copy it from memory? Copied rules fail on variants. | U73: Deduplicating equivalent job configs; canonical representation of equivalent placements | V73: Canonical enumeration | AB73: —
A74: 73 | B74: 11 | C74: 46368 | D74: Pruning: the actual skill in backtracking - design it up front | E74: Backtracking (pruning) | F74: Constraint propagation; ordering heuristics; early exit conditions | G74: NO | H74: - | J74: Untimed | K74: 1 hint @25min | L74: LC 51 N-Queens | M74: H | N74: 35 | O74: LC 131 Palindrome Partitioning | P74: M | Q74: 30 | R74: LC 90 Subsets II | S74: List every pruning rule and estimate its effect on the search-tree size | T74: Was pruning designed up front, or added reactively after a timeout? | U74: Constraint solvers; packing/placement with conflict constraints in cluster schedulers | V74: Pruning design | AB74: —
A75: 74 | B75: 11 | C75: 46369 | D75: Grid backtracking + bitmask constraint tracking | E75: Backtracking (grid) | F75: Row/col/box bitmasks for O(1) legality checks; TC bound estimation | G75: NO | H75: - | J75: Untimed | K75: 1 hint @30min | L75: LC 37 Sudoku Solver | M75: H | N75: 45 | O75: LC 79 Word Search | P75: M | Q75: 25 | R75: LC 51 N-Queens | S75: Explain bitmask constraint tracking; give a defensible TC bound with pruning factored in | T75: Did you reuse week-6 bitmask thinking here WITHOUT being told to? | U75: Resource placement under conflict constraints; topology-aware scheduling in ML clusters | V75: Constraint encoding | AB75: —
A76: 75 | B76: 11 | C76: 46370 | D76: Blind mix: exponential backtracking vs polynomial DP vs greedy | E76: Blind (paradigm choice) | F76: Deciding the PARADIGM before the algorithm; recognise when memo helps | G76: NO | H76: - | J76: Timed-60 | K76: None | L76: LC 698 Partition to K Equal Sum Subsets | M76: M | N76: 40 | O76: LC 17 Letter Combinations of a Phone Number | P76: M | Q76: 20 | R76: LC 37 Sudoku Solver | S76: Explain why memoization helps one of these problems and not the other | T76: Correct paradigm chosen FIRST, or did you thrash between two options? | U76: Bin packing for GPU/memory allocation; NP-hard scheduling approximations | V76: Paradigm selection | AB76: —
A77: 76 | B77: 11 | C77: 46371 | D77: The recursion -> memoization bridge: overlapping subproblems + state identification | E77: Memoization/state identification | F77: Spot overlapping subproblems; name the state; count distinct states | G77: YES | H77: =HYPERLINK("https://www.youtube.com/watch?v=XB4MIexjvY0", "From recursion to memo: state identification (the entry gate to all DP)") | I77: 20 | J77: Untimed | K77: Tutorial before | L77: LC 140 Word Break II | M77: H | N77: 35 | O77: LC 494 Target Sum | P77: M | Q77: 25 | R77: LC 698 Partition to K Equal Sum Subsets | S77: For each: write the state, count distinct states, derive memoized TC | T77: How quickly do you spot overlapping subproblems? This skill gates all of DP. | U77: Compilation/plan caches; memoizing expensive model inferences | V77: State identification | AB77: =HYPERLINK("https://www.youtube.com/watch?v=XB4MIexjvY0", "▶ Watch (Abdul Bari) ↗")
A78: 77 | B78: 11 | C78: 46372 | D78: Week 11 assessment - backtracking retention | E78: Review/audit | F78: Backtracking retention check | G78: NO | H78: - | J78: Untimed | K78: None | L78: Retest N-Queens + 2 others from W11, no notes | M78: H | N78: 50 | O78: WeeklyAssessment | P78: - | Q78: 20 | R78: ReviewQueue top 3 | S78: Rebuild the backtracking skeleton and the dedup rule from memory | T78: Is pruning reasoning present in your retests, or did you regress to brute enumeration? | U78: - | V78: Retention | AB78: —
A79: 78 | B79: 12 | C79: 46373 | D79: DP as a graph of states: the 5-step method before any code | E79: DP (1D) | F79: State, transition, base case, evaluation order, answer location - in that ORDER | G79: YES | H79: =HYPERLINK("https://www.youtube.com/watch?v=ibjEGG7ylHk", "DP state design (5-step method, not templates)") | I79: 30 | J79: Untimed | K79: Tutorial before | L79: LC 70 Climbing Stairs + LC 198 House Robber | M79: E | N79: 25 | O79: LC 91 Decode Ways | P79: M | Q79: 30 | R79: LC 494 Target Sum | S79: Write the 5-step form for ALL THREE problems before coding any of them | T79: Did you define the STATE before the transition? Reversing causes most DP failures. | U79: Cost-optimal pipeline/config selection over stages; stage-wise optimisation | V79: DP formalism | AB79: =HYPERLINK("https://www.youtube.com/watch?v=ibjEGG7ylHk", "▶ Watch (WilliamFiset) ↗")
A80: 79 | B80: 12 | C80: 46374 | D80: Subsequence DP and the O(n log n) upgrade - two solutions required | E80: DP (LIS family) | F80: O(n^2) DP -> patience/tails + binary search; what tails[i] means | G80: NO | H80: - | J80: Untimed | K80: 1 hint @30min | L80: LC 300 Longest Increasing Subsequence | M80: M | N80: 35 | O80: LC 354 Russian Doll Envelopes | P80: H | Q80: 40 | R80: LC 91 Decode Ways | S80: Explain the tails array, what tails[i] MEANS, and why binary search is valid | T80: Two solutions with different complexities? Both must be explainable. | U80: Version/compatibility chains; monotone scheduling sequences | V80: DP optimization | AB80: —
A81: 80 | B81: 12 | C81: 46375 | D81: Knapsack family: capacity as a dimension - understand loop order | E81: DP (knapsack) | F81: 0/1 vs unbounded; what iteration direction MEANS; 1D rolling array | G81: YES | H81: =HYPERLINK("https://www.youtube.com/watch?v=4ZlRH0eK-qQ", "Knapsack variants and loop order (not the formula - the reasoning)") | I81: 25 | J81: Untimed | K81: Tutorial before | L81: LC 416 Partition Equal Subset Sum | M81: M | N81: 30 | O81: LC 322 Coin Change | P81: M | Q81: 25 | R81: LC 300 Longest Increasing Subsequence | S81: Explain why 1D 0/1 knapsack iterates capacity DESCENDING, using a concrete failing example | T81: Understanding of loop order, or memorised direction? Construct the failing test. | U81: Memory/GPU packing; budget and quota allocation across multiple dimensions | V81: Dimension design | AB81: =HYPERLINK("https://www.youtube.com/watch?v=4ZlRH0eK-qQ", "▶ Watch (Abdul Bari) ↗")
A82: 81 | B82: 12 | C82: 46376 | D82: Knapsack in disguise: reduction practice | E82: DP (knapsack variants) | F82: Rewrite the problem as: items, weights, capacity, value, objective | G82: NO | H82: - | J82: Untimed | K82: 1 hint @25min | L82: LC 518 Coin Change II | M82: M | N82: 25 | O82: LC 474 Ones and Zeroes | P82: M | Q82: 30 | R82: LC 322 Coin Change | S82: Write the explicit mapping for BOTH problems: items / weights / capacity / value / objective | T82: Did you spot the disguise independently, or start from scratch? | U82: Multi-resource quota allocation (CPU+RAM+GPU as two capacity dimensions) | V82: Problem reduction | AB82: —
A83: 82 | B83: 12 | C83: 46377 | D83: Two-sequence DP: alignment states over prefixes of both inputs | E83: DP (2 sequences) | F83: dp[i][j] over prefixes of both sequences; derive transitions from the definition | G83: NO | H83: - | J83: Untimed | K83: 1 hint @25min | L83: LC 1143 Longest Common Subsequence | M83: M | N83: 25 | O83: LC 72 Edit Distance | P83: M | Q83: 35 | R83: LC 518 Coin Change II | S83: Explain each Edit Distance transition in words; DERIVE them from the definition, do not recall them | T83: Could you rebuild the transitions from the problem definition alone? | U83: Diffing; log alignment; tokenizer/sequence alignment in NLP systems | V83: 2D state design | AB83: —
A84: 83 | B84: 12 | C84: 46378 | D84: Space optimization in DP - which previous states does the transition need? | E84: DP (space optimization) | F84: Rolling arrays; dependency direction determines what rows you can drop | G84: NO | H84: - | J84: Untimed | K84: 1 hint | L84: Rewrite LC 72 Edit Distance in O(min(m,n)) space | M84: M | N84: 25 | O84: LC 63 Unique Paths II + LC 64 Minimum Path Sum | P84: M | Q84: 25 | R84: LC 72 Edit Distance | S84: State exactly which previous states each transition needs; then justify the rolling array | T84: SC reduced without breaking correctness? Verify on the maximum-size test case. | U84: Memory-bound kernels; buffer reuse; activation checkpointing intuition in training | V84: Space optimization | AB84: —
A85: 84 | B85: 12 | C85: 46379 | D85: MONTH 3 DIAGNOSTIC - 3 unlabelled, 110 min, full interview conditions | E85: Diagnostic | F85: Full interview conditions. No labels. No hints. Verbal + TC/SC required. | G85: NO | H85: - | J85: Diagnostic | K85: None | L85: LC 1383 Maximum Performance of a Team | M85: H | N85: 37 | O85: LC 1326 Minimum Taps to Water a Garden + LC 2092 Find All People With Secret (unlabelled) | P85: H | Q85: 73 | R85: - | S85: Log every metric; compare Months 1, 2, 3 side by side in MockInterviews | T85: Use results to choose weak-pattern targets for weeks 13-14. Follow the data, not the plan blindly. | U85: - | V85: Measurement | AB85: —
A86: 85 | B86: 13 | C86: 46380 | D86: Interval DP: build answers from small ranges - choose the LAST operation | E86: DP (interval) | F86: Iterate by LENGTH; pick the LAST operation to keep subproblems independent | G86: YES | H86: =HYPERLINK("https://www.youtube.com/watch?v=tyB0ztf0DNY", "Interval DP: why last operation, not first") | I86: 20 | J86: Untimed | K86: 1 hint @30min | L86: LC 312 Burst Balloons | M86: H | N86: 45 | O86: LC 516 Longest Palindromic Subsequence | P86: M | Q86: 25 | R86: LC 63 Unique Paths II | S86: Explain why we iterate by length AND why 'last balloon burst' makes subproblems independent | T86: Did you find the reversal insight yourself? That insight IS the entire problem. | U86: Optimal chunking / merge ordering; compaction cost minimisation in storage systems | V86: Interval reasoning | AB86: =HYPERLINK("https://www.youtube.com/watch?v=tyB0ztf0DNY", "▶ Watch (Striver) ↗")
A87: 86 | B87: 13 | C87: 46381 | D87: DP on trees and DAGs - memoisation is valid exactly when the state graph is acyclic | E87: DP (tree/DAG) | F87: Memoisation valid on DAGs; acyclicity must be verified, not assumed | G87: NO | H87: - | J87: Untimed | K87: 1 hint @25min | L87: LC 329 Longest Increasing Path in a Matrix | M87: H | N87: 35 | O87: LC 979 Distribute Coins in Binary Tree | P87: H | Q87: 35 | R87: LC 312 Burst Balloons | S87: Explain why memoisation works on a DAG but not on a general graph; verify acyclicity in LC 329 | T87: Did you CHECK acyclicity, or assume it? | U87: Critical-path computation in ML pipeline DAGs; longest-path scheduling | V87: DP-graph fusion | AB87: —
A88: 87 | B88: 13 | C88: 46382 | D88: Bitmask DP: subsets as states - n<=20 is the signal | E88: DP (bitmask) | F88: 2^n states; (mask, position) state; transition over bits | G88: YES | H88: =HYPERLINK("https://www.youtube.com/watch?v=kvyShbFVaY8", "Bitmask DP: state design and TC derivation") | I88: 20 | J88: Untimed | K88: 1 hint @30min | L88: LC 847 Shortest Path Visiting All Nodes | M88: H | N88: 45 | O88: LC 473 Matchsticks to Square | P88: M | Q88: 30 | R88: LC 329 Longest Increasing Path in Matrix | S88: Compute the exact state count and TC; explain the (mask, position) state for LC 847 | T88: Did n<=20 immediately suggest bitmask? Constraint-reading is the entire skill here. | U88: Job-to-machine assignment; small-scale optimal placement in resource schedulers | V88: Constraint-driven recognition | AB88: =HYPERLINK("https://www.youtube.com/watch?v=kvyShbFVaY8", "▶ Watch (Aditya Verma) ↗")
A89: 88 | B89: 13 | C89: 46383 | D89: DP optimization: monotonic deque inside a DP transition - week-2 reappears | E89: DP + monotonic deque | F89: Sliding-window maximum hidden inside a DP recurrence; O(nk) -> O(n) | G89: NO | H89: - | J89: Untimed | K89: 1 hint @30min | L89: LC 1696 Jump Game VI | M89: M | N89: 30 | O89: LC 1425 Constrained Subsequence Sum | P89: H | Q89: 40 | R89: LC 847 Shortest Path Visiting All Nodes | S89: Write naive O(nk) transition first, then deque-optimised O(n) version; prove equivalence | T89: Did you see the sliding window HIDDEN inside the DP? That is week-2 reappearing in week-13. | U89: Streaming DP with bounded lookback; windowed online decisions in scheduling | V89: Transition optimization | AB89: —
A90: 89 | B90: 13 | C90: 46384 | D90: Counting DP and bounding the state space | E90: DP (counting) | F90: Count configurations; prune impossible states; modular arithmetic | G90: NO | H90: - | J90: Untimed | K90: 1 hint @25min | L90: LC 1269 Number of Ways to Stay in Same Place | M90: H | N90: 35 | O90: LC 1220 Count Vowels Permutation | P90: H | Q90: 30 | R90: LC 1425 Constrained Subsequence Sum | S90: Explain the state bound (why positions beyond steps/2 are unreachable) and the modular arithmetic | T90: Did you bound the state space, or allocate a giant table and hope? | U90: Counting valid configurations / reachable states in a job scheduler or planner | V90: State bounding | AB90: —
A91: 90 | B91: 13 | C91: 46385 | D91: Blind HARD mix: full range, 90 minutes - peak capability test | E91: Blind (hard W1-W13) | F91: Maximum capability test; no labels; no hints | G91: NO | H91: - | J91: Timed-90 | K91: None | L91: LC 1235 Maximum Profit in Job Scheduling (unlabelled) | M91: H | N91: 45 | O91: LC 862 Shortest Subarray with Sum at Least K (unlabelled) | P91: H | Q91: 45 | R91: LC 312 Burst Balloons | S91: Time-to-pattern for both; write PatternCards entries for any pattern you failed to recognise | T91: Independent solve on a hard, unlabelled, timed problem - the actual target behaviour. | U91: - | V91: Peak capability | AB91: —
A92: 91 | B92: 13 | C92: 46386 | D92: Week 13 assessment + reconstruction marathon - consolidation | E92: Review/consolidation | F92: Deep retention audit across all 13 weeks | G92: NO | H92: - | J92: Untimed | K92: None | L92: Reconstruct 6 anchor problems from memory - code, no notes | M92: H | N92: 60 | O92: WeeklyAssessment + update PatternLibrary mastery honestly | P92: - | Q92: 25 | R92: ReviewQueue top 5 | S92: Fill PatternCards for every pattern rated below mastery 4 | T92: Which patterns are still fragile? Those, and ONLY those, get week-14 repair time. | U92: - | V92: Consolidation | AB92: —
A93: 92 | B93: 14 | C93: 46387 | D93: MOCK INTERVIEW #3 - no hints, verbal reasoning required throughout | E93: Mock interview #3 | F93: Full simulation with follow-up; narrate every decision | G93: NO | H93: - | J93: Timed-50 | K93: None | L93: Mock #3: 1 medium + 1 hard follow-up question, narrated | M93: H | N93: 50 | O93: Self-review the recording against a rubric | P93: - | Q93: 20 | R93: ReviewQueue top 3 | S93: Rewrite the solution cleanly after the mock; note every place you stalled verbally | T93: Where did communication break down: restatement, approach pitch, or complexity explanation? | U93: - | V93: Interview execution | AB93: —
A94: 93 | B94: 14 | C94: 46388 | D94: Weak-pattern repair using mock + diagnostic data - repair, not exploration | E94: Targeted repair (W14) | F94: Repair the weakest pattern; evidence-driven, not intuition-driven | G94: NO | H94: - | J94: Untimed | K94: Hints allowed | L94: 2 problems in your single weakest pattern from diagnostics | M94: H | N94: 50 | O94: Update preventive rules in FailureLog | P94: - | Q94: 15 | R94: All Mastered=No rows | S94: Explain the weak pattern aloud for 2 minutes with no notes | T94: Did the repair hold on the SECOND problem? One success is noise. | U94: - | V94: Targeted repair | AB94: —
A95: 94 | B95: 14 | C95: 46389 | D95: Infra-flavoured design + algorithm session: build real systems | E95: Design + algorithms | F95: Algorithms living inside production systems; bottleneck analysis at scale | G95: NO | H95: - | J95: Untimed | K95: None | L95: Design: in-memory feature cache with TTL + LRU eviction + metrics - implement core ops | M95: H | N95: 45 | O95: Design: DAG task scheduler with priorities + worker limits - implement the ready-queue core | P95: H | Q95: 40 | R95: LC 146 LRU Cache | S95: For each design: list every data structure, its purpose, and the TC of each operation | T95: Could you defend these under 10x scale in an ML-infra systems interview? | U95: This IS the overlap between DSA and AI-infra engineering | V95: Systems-algorithm bridge | AB95: —
A96: 95 | B96: 14 | C96: 46390 | D96: MOCK INTERVIEW #4 - unfamiliar hard, no hints, 45 min, follow-up required | E96: Mock interview #4 | F96: Unfamiliar problem under full pressure; decision timeline analysis | G96: NO | H96: - | J96: Timed-45 | K96: None | L96: Mock #4: 1 unfamiliar hard from README pool | M96: H | N96: 45 | O96: Post-mortem: minute-by-minute decision timeline | P96: - | Q96: 25 | R96: ReviewQueue top 3 | S96: Write the decision timeline: what you thought at minutes 2, 5, 10, 20, 35 | T96: Where did you waste minutes? Time allocation is a trainable interview skill. | U96: - | V96: Time allocation | AB96: —
A97: 96 | B97: 14 | C97: 46391 | D97: [2-SOL] Second-solution day - force fundamentally different paradigms | E97: Multi-solution flexibility | F97: Prevent template lock; conditions favouring each approach | G97: NO | H97: - | J97: Untimed | K97: None | L97: Solve 2 previously-solved problems using a DIFFERENT paradigm (heap -> sort, DFS -> BFS, greedy -> DP, BS -> math) | M97: H | N97: 45 | O97: Compare TC/SC of both approaches and state when each is preferable | P97: - | Q97: 20 | R97: ReviewQueue top 3 | S97: Explain both solutions for both problems and the conditions favouring each | T97: Flexible, or template-locked? Template-locked candidates fail on variants. | U97: Trade-off analysis is core to ML system design documents | V97: Approach flexibility | AB97: —
A98: 97 | B98: 14 | C98: 46392 | D98: Pressure day: 3 problems in 75 minutes - endurance without accuracy collapse | E98: Blind (timed volume) | F98: Throughput without correctness collapse; triage decisions | G98: NO | H98: - | J98: Timed-75 | K98: None | L98: 3 unlabelled problems (E/M/H) from hard pool - 75 min total | M98: H | N98: 75 | O98: Failure clustering after | P98: - | Q98: 15 | R98: - | S98: Rank by speed of pattern recognition; explain the fastest one's recognition cue | T98: Where did speed cost correctness? That is your real interview risk profile. | U98: - | V98: Endurance | AB98: —
A99: 98 | B99: 14 | C99: 46393 | D99: FINAL DIAGNOSTIC + design your own next 4-week cycle | E99: Diagnostic/planning | F99: Exit measurement and self-directed plan v2 | G99: NO | H99: - | J99: Diagnostic | K99: None | L99: Final diagnostic: LC 1751, LC 2421, LC 1463 - 110 min, unlabelled, no hints | M99: H | N99: 110 | O99: Write your own next 4-week plan driven purely by weakness data | P99: - | Q99: 30 | R99: - | S99: Fill dashboard; compare all 4 diagnostics on time-to-pattern, hint-dependency, TC accuracy | T99: Are you at the 'derive unfamiliar problems' level? Cite concrete evidence. | U99: - | V99: Self-directed training | AB99: —
A100: 99 | B100: 15 | C100: 46394 | D100: Fenwick Tree (Binary Indexed Tree / BIT): point updates & prefix range sums | E100: Fenwick Tree (BIT) | F100: Lowest set bit (i & -i); 1-indexed tree array; partial sum decomposition in O(log n) | G100: YES | H100: =HYPERLINK("https://www.youtube.com/watch?v=RgITNht_f4Q", "Fenwick Tree (Binary Indexed Tree) from scratch") | I100: 25 | J100: Untimed | K100: 1 hint @20min | L100: LC 307 Range Sum Query - Mutable | M100: M | N100: 25 | O100: LC 315 Count of Smaller Numbers After Self | P100: H | Q100: 35 | R100: LC 304 Range Sum Query 2D - Immutable | S100: Write BIT add(i, delta) and query(i) from memory in 6 lines of code; explain the (i & -i) math | T100: Did you prove why (i & -i) isolates the lowest set bit? | U100: Cumulative billing meters; live request frequency counters over rolling numeric IDs | V100: Logarithmic prefix tracking | AB100: =HYPERLINK("https://www.youtube.com/watch?v=RgITNht_f4Q", "▶ Watch (WilliamFiset) ↗")
...

Sheet PatternLibrary
A1: Pattern | B1: Recognition Cues | C1: Typical Constraints | D1: Core Idea | E1: Key Data Structures | F1: Common Traps | G1: Complexity Target | H1: Example Problem Types | I1: AI-Infra Relevance | J1: Mastery (1-5) | K1: # times it appeared in plan | L1: Last practiced
A2: Complexity calibration | B2: Any problem with 'efficient' + a large n stated | C2: n in constraints | D2: Derive acceptable TC from n BEFORE designing anything; eliminate approaches that cannot fit | E2: None - pure reasoning | F2: Assuming O(n^2) passes at n=10^5; ignoring hash/recursion constants; never doing this step | G2: Pre-code decision | H2: Every single problem | I2: Latency budgets; SLO thresholds; batch-size selection | K2: =COUNTIF(DayPlan!$E$2:$E$169,"*Complexity*") | L2: =IF(MAXIFS(ProblemDB!$F$2:$F$750,ProblemDB!$D$2:$D$750,"*Complexity*")>0,MAXIFS(ProblemDB!$F$2:$F$750,ProblemDB!$D$2:$D$750,"*Complexity*"),"-")
A3: Frequency/counting + hashing | B3: 'anagram','k most frequent','duplicates','count of','appears more than once' | C3: values bounded or hashable; n up to 10^6 | D3: Replace repeated scans with one pass building counts; hash the KEY that captures the invariant | E3: hash map, count array, bucket array | F3: Counting when positions matter; wrong key granularity; using set when count needed | G3: O(n) time, O(k) space | H3: Group anagrams, top-K, majority element, first unique character | I3: Hot-key detection, metric counters, histogram-based alerting | K3: =COUNTIF(DayPlan!$E$2:$E$169,"*Frequency*") | L3: =IF(MAXIFS(ProblemDB!$F$2:$F$750,ProblemDB!$D$2:$D$750,"*Frequency*")>0,MAXIFS(ProblemDB!$F$2:$F$750,ProblemDB!$D$2:$D$750,"*Frequency*"),"-")
A4: Prefix/suffix reasoning | B4: 'subarray sum','range query','product except self','subarrays satisfying condition' | C4: static array, multiple queries, O(n) target | D4: Precompute cumulative info so any range is O(1); prefix+hash converts a condition into a lookup | E4: prefix array, hash map (prefix -> count or prefix -> first-index) | F4: Forgetting prefix[0]=0; using seen-set instead of count-map; applying to non-additive functions | G4: O(n) build, O(1) query | H4: Range sums, balanced subarrays, product except self, 2D regions | I4: Rolling aggregates, cumulative metrics, event-log windows | K4: =COUNTIF(DayPlan!$E$2:$E$169,"*Prefix*") | L4: =IF(MAXIFS(ProblemDB!$F$2:$F$750,ProblemDB!$D$2:$D$750,"*Prefix*")>0,MAXIFS(ProblemDB!$F$2:$F$750,ProblemDB!$D$2:$D$750,"*Prefix*"),"-")
A5: Two pointers (opposite ends) | B5: sorted or sortable input; 'pair/triplet sums to'; 'maximum area between' | C5: sorted or O(n log n) sort acceptable | D5: Move the pointer that provably cannot improve the answer; prove no valid pair is skipped | E5: two indices into the same array | F5: Moving the wrong pointer; skipping duplicates incorrectly; not proving the discard | G5: O(n) after sort | H5: Two Sum II, 3Sum, Container With Most Water | I5: Merging sorted shard scans; two-way join on sorted data | K5: =COUNTIF(DayPlan!$E$2:$E$169,"*opposite ends*") | L5: =IF(MAXIFS(ProblemDB!$F$2:$F$750,ProblemDB!$D$2:$D$750,"*opposite ends*")>0,MAXIFS(ProblemDB!$F$2:$F$750,ProblemDB!$D$2:$D$750,"*opposite ends*"),"-")
A6: Two pointers (same direction / read-write) | B6: 'in place','remove elements','partition','k-th from end' | C6: O(1) extra space required; array mutation allowed | D6: Separate a slow write-index from a fast read-index; maintain a region invariant | E6: two indices, optional dummy node for lists | F6: Overwriting needed elements; not stating the region invariant; off-by-one | G6: O(n) time, O(1) space | H6: Remove duplicates, Sort Colors, move zeros, linked-list operations | I6: In-place buffer compaction; zero-copy stream rewriting | K6: =COUNTIF(DayPlan!$E$2:$E$169,"*read/write*") | L6: =IF(MAXIFS(ProblemDB!$F$2:$F$750,ProblemDB!$D$2:$D$750,"*read/write*")>0,MAXIFS(ProblemDB!$F$2:$F$750,ProblemDB!$D$2:$D$750,"*read/write*"),"-")
A7: Sliding window (variable) | B7: 'longest/shortest subarray/substring satisfying condition'; contiguous required | C7: monotone feasibility must hold; n up to 10^5 | D7: Grow right pointer; shrink left while invalid. ONLY valid when extending cannot repair a violation. | E7: hash map or count array for window contents, two indices | F7: Applying to non-monotone conditions (e.g. sum>=k with negatives); wrong shrink condition | G7: O(n) | H7: Longest unique substring, minimum size subarray sum, fruit into baskets | I7: Rate limiting, windowed quotas, token bucket | K7: =COUNTIF(DayPlan!$E$2:$E$169,"*variable*") | L7: =IF(MAXIFS(ProblemDB!$F$2:$F$750,ProblemDB!$D$2:$D$750,"*variable*")>0,MAXIFS(ProblemDB!$F$2:$F$750,ProblemDB!$D$2:$D$750,"*variable*"),"-")
A8: Sliding window + counting | B8: 'at most K distinct','replace at most k characters','subarrays with exactly k' | C8: alphabet/cardinality bounded; n up to 10^5 | D8: Track frequency inside the window; exactly(K) = atMost(K) - atMost(K-1) | E8: hash map, freq array, maxFreq variable | F8: Recomputing maxFreq on every shrink; wrong atMost monotonicity assumption | G8: O(n) or O(n | |alphabet|) | H8: Longest repeating character replacement, K different integers, permutation in string | I8: Cardinality-bounded caches; distinct-key windows in streaming analytics | K8: =COUNTIF(DayPlan!$E$2:$E$169,"*frequency*") | L8: =IF(MAXIFS(ProblemDB!$F$2:$F$750,ProblemDB!$D$2:$D$750,"*frequency*")>0,MAXIFS(ProblemDB!$F$2:$F$750,ProblemDB!$D$2:$D$750,"*frequency*"),"-")
A9: Binary search (index) | B9: sorted array; 'first/last position'; 'O(log n) required' | C9: sorted, or search space has a monotone property; n up to 10^7 | D9: Maintain a half-open invariant (lo<=answer<hi); shrink systematically; no templates | E9: sorted array (or implicit sorted space) | F9: Off-by-one errors; lo<hi vs lo<=hi confusion; infinite loops; wrong mid formula | G9: O(log n) | H9: Binary search, first/last position, find minimum in rotated array | I9: SSTable lookups, sorted offset indexes, version search | K9: =COUNTIF(DayPlan!$E$2:$E$169,"*Binary search*") | L9: =IF(MAXIFS(ProblemDB!$F$2:$F$750,ProblemDB!$D$2:$D$750,"*Binary search*")>0,MAXIFS(ProblemDB!$F$2:$F$750,ProblemDB!$D$2:$D$750,"*Binary search*"),"-")
A10: Binary search on answer | B10: 'minimize the maximum','maximize the minimum','minimum capacity/speed/time'; large answer range | C10: answer <= 10^9, predicate check is O(n) or O(n log n) | D10: Search the ANSWER SPACE with a monotone feasible(x) predicate; 3 validity conditions must hold | E10: feasibility predicate function + binary search loop | F10: Non-monotone predicate; wrong search bounds; predicate accidentally O(n^2) | G10: O(n log(answer_range)) | H10: Koko eating bananas, ship packages, split array, min days for bouquets | I10: Capacity planning, autoscaling, SLO fitting, quota allocation | K10: =COUNTIF(DayPlan!$E$2:$E$169,"*Binary search on answer*") | L10: =IF(MAXIFS(ProblemDB!$F$2:$F$750,ProblemDB!$D$2:$D$750,"*Binary search on answer*")>0,MAXIFS(ProblemDB!$F$2:$F$750,ProblemDB!$D$2:$D$750,"*Binary search on answer*"),"-")
A11: Sort + linear scan (preprocessing) | B11: 'intervals','pairs','sorted input assumed'; O(n log n) acceptable | C11: n up to 10^5, no online queries | D11: Sorting creates a monotonicity you can then exploit with a single greedy pass | E11: sort + one or two pointers or a heap | F11: Wrong sort key (start vs end vs value); assuming stability; sorting when a heap suffices | G11: O(n log n) | H11: Merge intervals, non-overlapping intervals, sort colors, meeting rooms | I11: Log compaction ordering, sorted shard merging, LSM-tree compaction | K11: =COUNTIF(DayPlan!$E$2:$E$169,"*Sort*") | L11: =IF(MAXIFS(ProblemDB!$F$2:$F$750,ProblemDB!$D$2:$D$750,"*Sort*")>0,MAXIFS(ProblemDB!$F$2:$F$750,ProblemDB!$D$2:$D$750,"*Sort*"),"-")
A12: Interval / sweep line | B12: 'overlapping intervals','maximum concurrent events','resources needed at peak' | C12: intervals, events with timestamps; n up to 10^5 | D12: Convert intervals to +1/-1 events and sweep; or maintain a min-heap of active end times | E12: sorted events array, min-heap of end times | F12: Tie-breaking between end and start at the same time; off-by-one on closed intervals | G12: O(n log n) | H12: Meeting rooms II, car pooling, calendar, task scheduler | I12: Concurrent resource counting (GPU/CPU slots), admission control | K12: =COUNTIF(DayPlan!$E$2:$E$169,"*Interval*") | L12: =IF(MAXIFS(ProblemDB!$F$2:$F$750,ProblemDB!$D$2:$D$750,"*Interval*")>0,MAXIFS(ProblemDB!$F$2:$F$750,ProblemDB!$D$2:$D$750,"*Interval*"),"-")
A13: Monotonic stack | B13: 'next greater/smaller element','previous smaller','span','largest rectangle' | C13: array; n up to 10^5 | D13: Keep a monotone stack; each pop resolves one answer; total pops <= n -> amortized O(n) | E13: stack of indices (not values) | F13: Storing values not indices; equal-element double counting; missing sentinel flush at end | G13: O(n) amortized | H13: Daily temperatures, next greater element, largest rectangle in histogram, subarray minimums | I13: Monotone-break detection in metric streams, backpressure onset | K13: =COUNTIF(DayPlan!$E$2:$E$169,"*Monotonic stack*") | L13: =IF(MAXIFS(ProblemDB!$F$2:$F$750,ProblemDB!$D$2:$D$750,"*Monotonic stack*")>0,MAXIFS(ProblemDB!$F$2:$F$750,ProblemDB!$D$2:$D$750,"*Monotonic stack*"),"-")
A14: Monotonic deque | B14: 'maximum/minimum of every window of size k','sliding extremum','windowed DP' | C14: fixed or bounded window; n up to 10^6 | D14: Maintain a deque of indices in monotone order; evict out-of-window and dominated candidates | E14: deque of indices | F14: Not evicting expired indices; storing values not indices; wrong eviction order | G14: O(n) | H14: Sliding window maximum, jump game VI, constrained subsequence sum | I14: Rolling max latency, watermarks, windowed DP in schedulers | K14: =COUNTIF(DayPlan!$E$2:$E$169,"*Monotonic deque*") | L14: =IF(MAXIFS(ProblemDB!$F$2:$F$750,ProblemDB!$D$2:$D$750,"*Monotonic deque*")>0,MAXIFS(ProblemDB!$F$2:$F$750,ProblemDB!$D$2:$D$750,"*Monotonic deque*"),"-")
A15: Heap / top-K / streaming extremum | B15: 'k largest/smallest','median of stream','schedule next available resource' | C15: k<<n or online data; n up to 10^6 | D15: Partial order is enough; a heap gives the extreme in O(log n); heapify is O(n) | E15: min-heap or max-heap; two heaps for median; heap of (key, cursor) for merge | F15: Full sort when k is tiny; wrong polarity; not using lazy deletion for stale entries | G15: O(n log k) or O(log n) per operation | H15: Kth largest, k closest, find median from stream, merge k sorted lists, task scheduler | I15: Top-K hot keys, p99 estimation, eviction candidate selection, priority scheduling | K15: =COUNTIF(DayPlan!$E$2:$E$169,"*Heap*") | L15: =IF(MAXIFS(ProblemDB!$F$2:$F$750,ProblemDB!$D$2:$D$750,"*Heap*")>0,MAXIFS(ProblemDB!$F$2:$F$750,ProblemDB!$D$2:$D$750,"*Heap*"),"-")
A16: Greedy invariants | B16: 'maximum number of','minimum steps','locally safe choice'; often after sorting | C16: exchange argument must hold; usually O(n log n) | D16: Prove by exchange or staying-ahead that the local choice is in some optimal solution | E16: sort + counters, heap, or simple scan | F16: Unproven greedy; missing a counterexample that breaks it; using greedy where DP is required | G16: O(n log n) typically | H16: Jump game II, gas station, partition labels, refueling stops | I16: Admission control, retry budgets, checkpoint placement | K16: =COUNTIF(DayPlan!$E$2:$E$169,"*Greedy*") | L16: =IF(MAXIFS(ProblemDB!$F$2:$F$750,ProblemDB!$D$2:$D$750,"*Greedy*")>0,MAXIFS(ProblemDB!$F$2:$F$750,ProblemDB!$D$2:$D$750,"*Greedy*"),"-")
A17: Design / structure composition | B17: 'implement X with O(1) get/put/delete','LRU','LFU','getRandom' | C17: operation TC is the spec; n up to 10^5 ops | D17: Compose two structures so each required operation is O(1)/O(log n); API dictates structures | E17: hash map + doubly linked list (LRU), freq buckets + maps (LFU), array + index map (getRandom) | F17: Choosing structures by habit not by API; forgetting to keep both structures in sync on every path | G17: O(1) per operation | H17: LRU cache, LFU cache, RandomizedSet, TimeMap, hit counter | I17: Page/feature/embedding caches, KV stores, rate limiters, versioned stores | K17: =COUNTIF(DayPlan!$E$2:$E$169,"*Design*") | L17: =IF(MAXIFS(ProblemDB!$F$2:$F$750,ProblemDB!$D$2:$D$750,"*Design*")>0,MAXIFS(ProblemDB!$F$2:$F$750,ProblemDB!$D$2:$D$750,"*Design*"),"-")
A18: Bit manipulation | B18: 'subset of at most 20 items','XOR','without extra space','count bits','feature flags' | C18: n<=20 for subset enumeration; 32/64-bit word for bit tricks | D18: A bitmask is a tiny set with O(1) set operations; XOR cancels pairs; use popcount for size | E18: integer masks, popcount, __builtin_ctz | F18: Signed right-shifts; operator precedence bugs (use parentheses); overflow on mask<<1 | G18: O(1) per mask op; O(2^n) for full enumeration | H18: Single number II, sum without +, missing number, subset enumeration | I18: Bitmaps, feature flags, GPU lane/warp masks, bloom filter ops | K18: =COUNTIF(DayPlan!$E$2:$E$169,"*Bit*") | L18: =IF(MAXIFS(ProblemDB!$F$2:$F$750,ProblemDB!$D$2:$D$750,"*Bit*")>0,MAXIFS(ProblemDB!$F$2:$F$750,ProblemDB!$D$2:$D$750,"*Bit*"),"-")
A19: Tree recursion (contract-first) | B19: 'depth','balanced','path sum','subtree property','lowest common ancestor' | C19: n up to 10^5; beware recursion depth on skewed trees | D19: Define exactly what the function returns for a subtree; write it in English before coding; then trust it | E19: recursion, call stack, optional memoisation | F19: Vague contracts; mixing 'answer' with 'return value'; stack overflow on skewed trees | G19: O(n) | H19: Depth, balanced, diameter, max path sum, LCA, validate BST | I19: Recursive dependency evaluation, nested config resolution | K19: =COUNTIF(DayPlan!$E$2:$E$169,"*Tree recursion*") | L19: =IF(MAXIFS(ProblemDB!$F$2:$F$750,ProblemDB!$D$2:$D$750,"*Tree recursion*")>0,MAXIFS(ProblemDB!$F$2:$F$750,ProblemDB!$D$2:$D$750,"*Tree recursion*"),"-")
A20: Tree DP (post-order) | B20: 'max path','rob houses in tree','distribute coins','max sum with no adjacent' | C20: tree, single-pass wanted | D20: Combine children's return values at the parent; return one value upward; update global answer separately | E20: recursion + tuple return (gain upward, answer updated) | F20: Returning the global answer upward; double-counting the root node; forgetting to clamp negatives | G20: O(n) | H20: Diameter, max path sum, house robber III, distribute coins | I20: Aggregating metrics up a topology/ownership tree | K20: =COUNTIF(DayPlan!$E$2:$E$169,"*Tree DP*") | L20: =IF(MAXIFS(ProblemDB!$F$2:$F$750,ProblemDB!$D$2:$D$750,"*Tree DP*")>0,MAXIFS(ProblemDB!$F$2:$F$750,ProblemDB!$D$2:$D$750,"*Tree DP*"),"-")
A21: BST ordering | B21: 'validate BST','k-th smallest in BST','BST range queries' | C21: BST given, may be unbalanced | D21: In-order traversal is sorted; propagate valid range (lo, hi) top-down instead of comparing parent-child | E21: recursion with range bounds, iterative inorder stack | F21: Comparing only parent-child (misses deep violations); ignoring duplicate policy | G21: O(h) per operation | H21: Validate BST, kth smallest, insert/delete, range queries | I21: Ordered indexes, range scans, B-tree node invariants | K21: =COUNTIF(DayPlan!$E$2:$E$169,"*BST*") | L21: =IF(MAXIFS(ProblemDB!$F$2:$F$750,ProblemDB!$D$2:$D$750,"*BST*")>0,MAXIFS(ProblemDB!$F$2:$F$750,ProblemDB!$D$2:$D$750,"*BST*"),"-")
A22: BFS levels / shortest hops | B22: 'minimum steps','level order','nearest X','spread from source' | C22: unweighted graph or grid; n up to 10^5 | D22: First visit = shortest distance; seed all sources at level 0 for multi-source; expand in layers | E22: queue, visited set/array | F22: Marking visited on pop (causes exponential blowup); mixing level boundaries | G22: O(V+E) | H22: Rotting oranges, word ladder, open the lock, right side view, 01-matrix | I22: Hop counts, blast-radius analysis, BFS-based propagation | K22: =COUNTIF(DayPlan!$E$2:$E$169,"*BFS*") | L22: =IF(MAXIFS(ProblemDB!$F$2:$F$750,ProblemDB!$D$2:$D$750,"*BFS*")>0,MAXIFS(ProblemDB!$F$2:$F$750,ProblemDB!$D$2:$D$750,"*BFS*"),"-")
A23: Graph DFS / components | B23: 'islands','connected components','clone graph','cycle detection','safe states' | C23: grid or adjacency list; n up to 10^5 | D23: Explore exhaustively; component identity or cycle colour (white/grey/black) is the output | E23: recursion or explicit stack, visited array, colour array for directed cycles | F23: Recursion depth on large grids; not handling multiple components; directed vs undirected cycle logic | G23: O(V+E) | H23: Number of islands, clone graph, find eventual safe states, course schedule | I23: Topology discovery, cluster membership, service-graph crawling | K23: =COUNTIF(DayPlan!$E$2:$E$169,"*Graph*") | L23: =IF(MAXIFS(ProblemDB!$F$2:$F$750,ProblemDB!$D$2:$D$750,"*Graph*")>0,MAXIFS(ProblemDB!$F$2:$F$750,ProblemDB!$D$2:$D$750,"*Graph*"),"-")
A24: Union Find (DSU) | B24: 'connected components that grow','merge groups','edges arrive incrementally','redundant edge' | C24: n up to 10^6; many merges and find queries | D24: Maintain disjoint sets with path compression + union by size for near-O(1) amortized ops | E24: parent array + size array | F24: Forgetting BOTH optimizations; using DSU where order of nodes matters; O(n) find without compression | G24: O(alpha(n)) amortized per op | H24: Number of provinces, accounts merge, redundant connection, dynamic connectivity | I24: Cluster membership, shard grouping, entity dedup, dynamic edge-stream connectivity | K24: =COUNTIF(DayPlan!$E$2:$E$169,"*Union Find*") | L24: =IF(MAXIFS(ProblemDB!$F$2:$F$750,ProblemDB!$D$2:$D$750,"*Union Find*")>0,MAXIFS(ProblemDB!$F$2:$F$750,ProblemDB!$D$2:$D$750,"*Union Find*"),"-")
A25: Topological sorting | B25: 'prerequisites','build order','dependency resolution','detect cycle in directed graph' | C25: DAG (or detect if not); V+E up to 10^5 | D25: Remove in-degree-0 nodes repeatedly (Kahn); or DFS with 3 colours; cycle = fewer than n emitted | E25: in-degree array + queue (Kahn), or recursion + colour array (DFS) | F25: Not detecting cycles; assuming a unique ordering exists; skipping isolated nodes | G25: O(V+E) | H25: Course schedule I/II, alien dictionary, task order, build systems | I25: DAG job scheduling, ML pipeline orchestration, build dependency resolution | K25: =COUNTIF(DayPlan!$E$2:$E$169,"*Topological*") | L25: =IF(MAXIFS(ProblemDB!$F$2:$F$750,ProblemDB!$D$2:$D$750,"*Topological*")>0,MAXIFS(ProblemDB!$F$2:$F$750,ProblemDB!$D$2:$D$750,"*Topological*"),"-")
A26: Dijkstra / weighted shortest path | B26: 'minimum cost/time path','non-negative edge weights','network delay' | C26: weights >= 0; E up to 10^5 | D26: Greedily finalize the closest unfinished node; the popped distance is final (non-negative weights only) | E26: min-heap of (distance, node) + dist array | F26: Using on negative weights; not skipping stale heap entries; wrong objective (min-max vs min-sum) | G26: O(E log V) | H26: Network delay, path with max probability, min effort, cheapest flights | I26: Latency-aware routing, cost-based placement, weighted service graphs | K26: =COUNTIF(DayPlan!$E$2:$E$169,"*Dijkstra*") | L26: =IF(MAXIFS(ProblemDB!$F$2:$F$750,ProblemDB!$D$2:$D$750,"*Dijkstra*")>0,MAXIFS(ProblemDB!$F$2:$F$750,ProblemDB!$D$2:$D$750,"*Dijkstra*"),"-")
A27: State-space BFS/Dijkstra | B27: 'minimum moves with a resource budget','compound state','configuration reachability' | C27: state space bounded and enumerable; states up to ~10^6 | D27: Nodes are FULL STATES (not just position); encode the state tuple; visited keyed on the complete state | E27: queue or min-heap, visited set of encoded state tuples | F27: Visited keyed on partial state (silent wrong answer); unbounded state space; expensive encoding | G27: O(states * transitions) | H27: Sliding puzzle, obstacle elimination, open the lock, minimum genetic mutation | I27: Scheduler/config state exploration, rollout planning, deployment state machines | K27: =COUNTIF(DayPlan!$E$2:$E$169,"*State-space*") | L27: =IF(MAXIFS(ProblemDB!$F$2:$F$750,ProblemDB!$D$2:$D$750,"*State-space*")>0,MAXIFS(ProblemDB!$F$2:$F$750,ProblemDB!$D$2:$D$750,"*State-space*"),"-")
A28: Backtracking + pruning | B28: 'all combinations/permutations/partitions','place N items with constraints' | C28: n small (<=20) or with heavy pruning; exponential in theory | D28: Choose, explore, unchoose; the real skill is pruning branches that cannot lead to valid solutions | E28: recursion, path array, bitmasks for O(1) constraint checks | F28: No pruning; incorrect dedup; mutating shared state without restoring it | G28: Exponential with pruning factor | H28: Subsets, permutations, N-Queens, sudoku, palindrome partitioning, word search | I28: Config search, placement under conflict constraints, hyperparameter enumeration | K28: =COUNTIF(DayPlan!$E$2:$E$169,"*Backtracking*") | L28: =IF(MAXIFS(ProblemDB!$F$2:$F$750,ProblemDB!$D$2:$D$750,"*Backtracking*")>0,MAXIFS(ProblemDB!$F$2:$F$750,ProblemDB!$D$2:$D$750,"*Backtracking*"),"-")
A29: Trie / prefix tree | B29: 'prefix queries','dictionary of words','autocomplete','search with wildcards' | C29: alphabet size small (<=26); many words/queries | D29: Share prefixes to make prefix queries proportional to word length; enables DFS pruning | E29: trie nodes (array or hash map per node) with end flags | F29: Memory blowup on large alphabets; using a trie where a hashset is simpler and sufficient | G29: O(L) per operation (L = word length) | H29: Implement trie, word search II, add and search words, longest prefix match | I29: Autocomplete, tokenizer vocabularies, longest-prefix-match routing | K29: =COUNTIF(DayPlan!$E$2:$E$169,"*Trie*") | L29: =IF(MAXIFS(ProblemDB!$F$2:$F$750,ProblemDB!$D$2:$D$750,"*Trie*")>0,MAXIFS(ProblemDB!$F$2:$F$750,ProblemDB!$D$2:$D$750,"*Trie*"),"-")
A30: DP (1D state design) | B30: 'number of ways','min/max cost','can we reach target','decisions at each step' | C30: n up to 10^5; clear stages or positions | D30: Define state -> transition -> base case -> evaluation order -> answer location (in that exact order) | E30: 1D array or hash map | F30: Defining transition before state; wrong evaluation order; reading answer from wrong position | G30: O(n * states_per_position) | H30: Climbing stairs, house robber, decode ways, jump game, coin change | I30: Stage-wise cost optimisation, pipeline configuration selection | K30: =COUNTIF(DayPlan!$E$2:$E$169,"*DP (1D)*") | L30: =IF(MAXIFS(ProblemDB!$F$2:$F$750,ProblemDB!$D$2:$D$750,"*DP (1D)*")>0,MAXIFS(ProblemDB!$F$2:$F$750,ProblemDB!$D$2:$D$750,"*DP (1D)*"),"-")
A31: DP (knapsack family) | B31: 'subset sum','choose items under capacity budget','coin change','ways to make amount' | C31: capacity/sum bounded (pseudo-polynomial); n * capacity <= 10^7 | D31: Capacity is a DP dimension; loop order encodes 0/1 (descending) vs unbounded (ascending) | E31: 1D or 2D DP arrays | F31: Wrong loop order; counting permutations vs combinations; not handling 0-capacity base case | G31: O(n * capacity) | H31: Partition equal subset, coin change I/II, ones and zeroes, target sum | I31: Memory/GPU packing, multi-resource quota allocation | K31: =COUNTIF(DayPlan!$E$2:$E$169,"*knapsack*") | L31: =IF(MAXIFS(ProblemDB!$F$2:$F$750,ProblemDB!$D$2:$D$750,"*knapsack*")>0,MAXIFS(ProblemDB!$F$2:$F$750,ProblemDB!$D$2:$D$750,"*knapsack*"),"-")
A32: DP (two sequences) | B32: 'two strings','edit distance','common subsequence','interleaving' | C32: m, n up to ~1000 | D32: dp[i][j] over prefixes of both sequences; derive transitions from the problem definition | E32: 2D array or rolling 1D for space optimization | F32: Index confusion (i=0 means empty prefix); wrong base cases; optimizing space before correctness | G32: O(mn) time, O(min(m,n)) space with rolling | H32: LCS, edit distance, interleaving strings, distinct subsequences | I32: Diffing, log/sequence alignment, tokenizer alignment | K32: =COUNTIF(DayPlan!$E$2:$E$169,"*sequences*") | L32: =IF(MAXIFS(ProblemDB!$F$2:$F$750,ProblemDB!$D$2:$D$750,"*sequences*")>0,MAXIFS(ProblemDB!$F$2:$F$750,ProblemDB!$D$2:$D$750,"*sequences*"),"-")
A33: DP (interval) | B33: 'optimal order of operations on a range','merge/burst/remove from a subarray' | C33: n up to ~500 (O(n^3) acceptable) | D33: Solve shorter ranges first; pick the LAST operation (not first) to keep subproblems independent | E33: 2D DP array dp[left][right] | F33: Picking the first operation instead of the last; wrong iteration order (must go by length) | G33: O(n^3) | H33: Burst balloons, longest palindromic subsequence, matrix chain, minimum cost to merge stones | I33: Optimal chunking, merge ordering, compaction cost minimisation | K33: =COUNTIF(DayPlan!$E$2:$E$169,"*interval*") | L33: =IF(MAXIFS(ProblemDB!$F$2:$F$750,ProblemDB!$D$2:$D$750,"*interval*")>0,MAXIFS(ProblemDB!$F$2:$F$750,ProblemDB!$D$2:$D$750,"*interval*"),"-")
A34: DP (bitmask) | B34: 'n<=20','visit all nodes','assign items to groups','travelling salesman variant' | C34: n<=20 (2^n states must fit in memory) | D34: State includes a subset bitmask; transition adds one element; (mask, position) is the full state | E34: dp[mask][...] arrays | F34: Not recognising the n<=20 signal; state explosion; recomputing popcount in the inner loop | G34: O(2^n | n) or O(2^n | n^2) | H34: Shortest path visiting all nodes, matchsticks to square, assignment, TSP-variants | I34: Job-to-machine assignment, small-scale optimal placement | K34: =COUNTIF(DayPlan!$E$2:$E$169,"*bitmask*") | L34: =IF(MAXIFS(ProblemDB!$F$2:$F$750,ProblemDB!$D$2:$D$750,"*bitmask*")>0,MAXIFS(ProblemDB!$F$2:$F$750,ProblemDB!$D$2:$D$750,"*bitmask*"),"-")
A35: DP optimization (deque/heap in transition) | B35: naive DP transition is O(nk) or O(n^2) and n>10^3 | C35: tight time limit + large n | D35: Optimize the transition by hiding a sliding-window maximum/minimum (monotonic deque) inside it | E35: DP array + monotonic deque or heap or prefix max array | F35: Optimizing before the naive recurrence is correct and verified; breaking the window bound | G35: O(n) or O(n log n) | H35: Jump game VI, constrained subsequence sum, LIS in O(n log n) | I35: Streaming DP with bounded lookback; windowed online decisions | K35: =COUNTIF(DayPlan!$E$2:$E$169,"*deque*") | L35: =IF(MAXIFS(ProblemDB!$F$2:$F$750,ProblemDB!$D$2:$D$750,"*deque*")>0,MAXIFS(ProblemDB!$F$2:$F$750,ProblemDB!$D$2:$D$750,"*deque*"),"-")
A36: Fenwick Tree (BIT) | B36: 'mutable range sum','inversion count','point update + prefix query' | C36: values coordinate-compressed; n up to 10^6 | D36: Lowest set bit (i & -i) tree decomposition; O(log n) update and query with tiny constant factor | E36: 1D array (1-indexed) | F36: 0-indexing off-by-one; using when range updates needed without difference array | G36: O(log n) update/query | H36: Range sum query, smaller numbers after self, reverse pairs | I36: High-frequency telemetry counters, rolling latency meters | K36: =COUNTIF(DayPlan!$E$2:$E$169,"*Fenwick*") | L36: =IF(MAXIFS(ProblemDB!$F$2:$F$750,ProblemDB!$D$2:$D$750,"*Fenwick*")>0,MAXIFS(ProblemDB!$F$2:$F$750,ProblemDB!$D$2:$D$750,"*Fenwick*"),"-")
A37: Segment Tree (range query) | B37: 'range min/max/sum/gcd query','point or range updates'; associative function | C37: array size n up to 5 * 10^5, associative operator | D37: Divide-and-conquer binary tree over array intervals; 4n array representation; lazy propagation | E37: tree array, lazy array | F37: Size 2n instead of 4n; forgetting push_down before inspecting children; non-associative ops | G37: O(n) build, O(log n) update/query | H37: Skyline, falling squares, range module, calendar booking | I37: Distributed SLA monitoring, physical memory reservation maps | K37: =COUNTIF(DayPlan!$E$2:$E$169,"*Segment Tree*") | L37: =IF(MAXIFS(ProblemDB!$F$2:$F$750,ProblemDB!$D$2:$D$750,"*Segment Tree*")>0,MAXIFS(ProblemDB!$F$2:$F$750,ProblemDB!$D$2:$D$750,"*Segment Tree*"),"-")
A38: Tarjan's DFS (bridges & SCC) | B38: 'critical connections','single point of failure','strongly connected components' | C38: directed or undirected graph, O(V + E) target | D38: Discovery time tin[u] and lowest ancestor low[u]; back-edge detection; condensation DAG | E38: tin array, low array, visited stack | F38: Updating low[u] from parent edge in undirected graph; not popping stack up to u in SCC | G38: O(V + E) | H38: Critical connections, graph disconnect, condensation DAG | I38: Fault-domain isolation, deadlock detection, build dependency validation | K38: =COUNTIF(DayPlan!$E$2:$E$169,"*Tarjan*") | L38: =IF(MAXIFS(ProblemDB!$F$2:$F$750,ProblemDB!$D$2:$D$750,"*Tarjan*")>0,MAXIFS(ProblemDB!$F$2:$F$750,ProblemDB!$D$2:$D$750,"*Tarjan*"),"-")
A39: Hardware / Cache calibration | B39: high throughput, 10M+ QPS, low latency SLO, memory-constrained traversal | C39: CPU cache line 64 bytes, DRAM access 60ns vs L1 1ns | D39: Structure data contiguously (AOS vs SOA); eliminate pointer chasing; size blocks to L1/L2 cache | E39: flat contiguous buffers, cyclic arrays | F39: Using linked lists / pointer trees in hot paths; ignoring false sharing and cache-line bouncing | G39: O(n) with 10x lower constant factor | H39: Matrix transposition, ring buffers, flat hash tables | I39: Tensor memory layouts, GPU shared memory tiling, low-latency trading | K39: =COUNTIF(DayPlan!$E$2:$E$169,"*Hardware*") | L39: =IF(MAXIFS(ProblemDB!$F$2:$F$750,ProblemDB!$D$2:$D$750,"*Hardware*")>0,MAXIFS(ProblemDB!$F$2:$F$750,ProblemDB!$D$2:$D$750,"*Hardware*"),"-")
A40: High-performance hashing | B40: zero tail-latency, low collision variance, predictable lookup time | C40: in-memory key-value store, load factor 0.8 - 0.9 | D40: Robin Hood displacement or Cuckoo two-table hashing; bounded worst-case probe lengths | E40: flat key/value array + probe count byte | F40: Infinite loops during cuckoo cycles without stash; bad hash functions | G40: O(1) average and worst-case | H40: In-memory KV store, RocksDB cache, Swiss table | I40: Storage engine block caches, Memcached, Redis hash tables | K40: =COUNTIF(DayPlan!$E$2:$E$169,"*hashing*") | L40: =IF(MAXIFS(ProblemDB!$F$2:$F$750,ProblemDB!$D$2:$D$750,"*hashing*")>0,MAXIFS(ProblemDB!$F$2:$F$750,ProblemDB!$D$2:$D$750,"*hashing*"),"-")
A41: Adaptive Cache (ARC) | B41: dynamic workload with mixed scans and recurring loops; hit ratio optimization | C41: fixed cache memory budget c | D41: Balance recency (T1) and frequency (T2) dynamically using ghost history lists (B1, B2) | E41: 4 LRU lists (T1, T2, B1, B2) + hash map | F41: Losing ghost entries on eviction; incorrect target size p boundary clipping [0, c] | G41: O(1) per lookup and update | H41: ZFS storage ARC, buffer pool management, LLM prompt cache | I41: Database buffer managers, kernel page caches, multi-tenant AI caching | K41: =COUNTIF(DayPlan!$E$2:$E$169,"*ARC*") | L41: =IF(MAXIFS(ProblemDB!$F$2:$F$750,ProblemDB!$D$2:$D$750,"*ARC*")>0,MAXIFS(ProblemDB!$F$2:$F$750,ProblemDB!$D$2:$D$750,"*ARC*"),"-")
A42: Lock-free ring buffer | B42: high-speed inter-thread message passing; zero lock contention; producer-consumer | C42: single producer single consumer (SPSC) or MPMC; power-of-two size | D42: Head and tail indices advancing monotonically; masking with (size - 1); cache line padding (64 bytes) | E42: atomic size_t head, tail; contiguous array buffer | F42: False sharing between head and tail; missing memory barriers (acquire/release); ABA problem in MPMC | G42: O(1) wait-free SPSC / lock-free MPMC | H42: Circular queue, circular deque, bounded blocking queue | I42: LMAX Disruptor, GPU command rings, high-throughput network packet ingestion | K42: =COUNTIF(DayPlan!$E$2:$E$169,"*Lock-free*") | L42: =IF(MAXIFS(ProblemDB!$F$2:$F$750,ProblemDB!$D$2:$D$750,"*Lock-free*")>0,MAXIFS(ProblemDB!$F$2:$F$750,ProblemDB!$D$2:$D$750,"*Lock-free*"),"-")
A43: HNSW graph search | B43: approximate nearest neighbor (ANN), vector similarity, high dimensionality (d=128 to 1536) | C43: dataset N up to 10^8 vectors, query latency < 5ms | D43: Multi-layer proximity graph (skip-list concept); greedy routing on coarse upper layers, beam search on layer 0 | E43: layered adjacency list, candidate priority queue, visited set | F43: Local minima traps with too small efSearch; cyclic graph infinite loops without visited filter | G43: O(log N) average query time | H43: Vector embeddings, multimodal search, semantic retrieval | I43: Vector databases (Milvus, Pinecone, Qdrant, FAISS), RAG pipelines | K43: =COUNTIF(DayPlan!$E$2:$E$169,"*HNSW*") | L43: =IF(MAXIFS(ProblemDB!$F$2:$F$750,ProblemDB!$D$2:$D$750,"*HNSW*")>0,MAXIFS(ProblemDB!$F$2:$F$750,ProblemDB!$D$2:$D$750,"*HNSW*"),"-")

Sheet PatternCards
A1: Anchor Problem | B1: Pattern | C1: Trigger [pre-filled] | D1: Core Insight [YOU fill from memory] | E1: Data Structure + why [pre-filled] | F1: Invariant [YOU fill from memory] | G1: Complexity + argument [pre-filled] | H1: Failure Mode of average candidate | I1: Interviewer Variations | J1: Recognition Cue (next time) | K1: Last reconstructed | L1: Reconstruction score (1-5)
A2: LC 560 Subarray Sum Equals K | B2: Prefix + hash | C2: 'count subarrays with sum = k' + negatives present -> window fails | E2: hash map prefix -> count; store what you've seen; look up (prefix - k) | G2: O(n) time O(n) space: one pass, O(1) map ops | H2: F11: tries sliding window; fails because negatives break monotonicity | I2: Return the longest such subarray; 2D version; sum divisible by k | J2: Contiguous + sum + negatives = prefix hash, not window
A3: LC 76 Minimum Window Substring | B3: Sliding window + counting | C3: 'minimum window containing all characters of t' | E3: need/have counters + two pointers; expand right, shrink left when have==need | G3: O(n+m): amortized pointer movement | H3: F6: recomputes the whole counter check each step -> O(n^2) | I3: Multiple pattern strings; window over a stream; minimum window subsequence | J3: Shortest valid window = expand right first, shrink left aggressively
A4: LC 875 Koko Eating Bananas | B4: Binary search on answer | C4: 'minimum speed such that all piles eaten within h hours' | E4: feasible(speed) = all(ceil(p/speed) for p in piles) <= h; monotone decreasing as speed grows | G4: O(n log(max_pile)): predicate is O(n) | H4: F3: tries greedy or average; doesn't see the monotone predicate | I4: Non-integer speeds; per-pile costs; maximize instead of minimize | J4: 'minimum X such that condition holds' = BS on answer
A5: LC 84 Largest Rectangle in Histogram | B5: Monotonic stack | C5: 'largest rectangle area under bars' | E5: maintain increasing-height stack of indices; on each pop, compute the rectangle using right-left-1 | G5: O(n) amortized: each index pushed and popped exactly once | H5: F6: nested loops O(n^2); mishandles equal heights or the end-of-array flush | I5: Maximal rectangle in binary matrix; 3D variant; sum of subarray minimums | J5: Need previous-smaller and next-smaller boundaries simultaneously = monotonic stack
A6: LC 295 Find Median from Data Stream | B6: Two heaps (streaming) | C6: 'median of a stream' + online insertion | E6: max-heap for lower half + min-heap for upper half; rebalance so sizes differ by at most 1 | G6: O(log n) insert, O(1) median query | H6: F3: re-sorts on every query; O(n log n) per call | I6: Sliding-window median; arbitrary percentile; distributed streaming quantiles | J6: Online order statistic = two heaps or segment tree + BIT
A7: LC 146 LRU Cache | B7: Design composition | C7: 'O(1) get and put with LRU eviction' | E7: hash map for O(1) lookup + doubly linked list for O(1) move-to-front and O(1) eviction from tail | G7: O(1) per operation | H7: F4: uses array/list -> O(n) moves; or forgets to update the map on eviction | I7: TTL eviction; thread-safe LRU; LFU; write-through/write-back | J7: O(1) ordered access = hash map + doubly linked list
A8: LC 460 LFU Cache | B8: Design composition | C8: 'O(1) get and put with LFU eviction' | E8: freq -> OrderedDict bucket map + key -> (val,freq) map + minFreq pointer | G8: O(1) per operation | H8: F3: scans for min frequency O(n); loses the minFreq invariant on edge cases | I8: Aging/decay of counts; window LFU; hybrid ARC policy | J8: Frequency-ordered eviction = bucketed frequency lists with a minFreq pointer
A9: LC 124 Binary Tree Maximum Path Sum | B9: Tree DP post-order | C9: 'maximum path sum' where path can bend at any node | E9: at each node, return max(0, node.val + best_downward) for parent; update global answer with left+node+right | G9: O(n): one visit per node | H9: F3: returns the bent path upward; forgets to clamp negative downward gains to 0 | I9: Path with at most k turns; count of maximum paths; k-ary tree variant | J9: Global answer updated at node != value returned to parent
A10: LC 297 Serialize/Deserialize Tree | B10: Encoding design | C10: 'serialize a tree to a string and deserialize it back' | E10: preorder traversal + null markers; use a queue/index cursor during deserialization | G10: O(n) both directions | H10: F1: improvises the format; cannot parse back an ambiguous encoding | I10: N-ary tree; BST-optimized encoding (no nulls needed); compact binary format | J10: Define the grammar BEFORE writing code -> guaranteed decodability
A11: LC 207 Course Schedule (topological sort) | B11: Topological sort | C11: 'prerequisites exist','valid ordering required','detect cycle in directed graph' | E11: Kahn: maintain in-degree array + queue; emit when in-degree reaches 0; cycle if emitted < n | G11: O(V+E) | H11: F6: cannot detect cycles; assumes unique ordering | I11: Lexicographically smallest order; parallel scheduling with k workers; critical path | J11: 'ordering with dependencies' = topological sort (Kahn or DFS-colours)
A12: LC 743 Network Delay Time | B12: Dijkstra | C12: 'minimum time for signal to reach all nodes' + non-negative weights | E12: standard Dijkstra; answer = max of all shortest distances; -1 if any node unreachable | G12: O(E log V) | H12: F3: uses plain BFS on weighted edges; or forgets to skip stale heap entries | I12: Negative weights (use Bellman-Ford); k-hop limit (add hop dimension); multi-source | J12: Weighted min cost + non-negative weights = Dijkstra
A13: LC 787 Cheapest Flights Within K Stops | B13: Layered DP / Bellman-Ford | C13: 'cheapest path with at most k stops' = extra constraint on path length | E13: dp[t][v] = min cost to reach v using at most t hops; iterate t from 1 to k+1 | G13: O(k | E): k+1 rounds of edge relaxation | H13: F3: runs plain Dijkstra and ignores the stop constraint; or modifies dist in-place breaking the layer | I13: Exactly k stops; time windows; multiple path constraints | J13: Extra constraint on a path = add a state dimension (hops, resources, keys)
... A31: Count-Min Sketch & Misra-Gries | B31: Streaming algorithms | C31: 'estimate item frequencies and find top-K heavy hitters in sub-linear space' | E31: d x w 2D counter array with independent hash functions; Misra-Gries k-1 candidate pool | G31: O(1) per update, O(w * d) space | H31: F4: stores all unique keys in hash map -> O(N) memory explosion on streaming big data | I31: HyperLogLog cardinality; Bloom filter set membership; Reservoir sampling | J31: Streaming top-K and frequency in bounded space = Count-Min Sketch + Misra-Gries

Sheet ProblemDB
A1: Problem | B1: Platform | C1: Difficulty | D1: Pattern | E1: Sub-pattern | F1: First Attempt | G1: Solved Independently? | H1: Time Taken (min) | I1: Hints Used | J1: Solution Viewed? | K1: TC | L1: SC | M1: Mistake Category | N1: Key Insight (one line) | O1: Recognition Cue | P1: Next Review | Q1: Review 2 | R1: Review 3 | S1: Mastered? | T1: Notes | U1: Week | V1: Priority Score | W1: Days To Due | X1: 2nd Solution Found?
A2: LC 1 Two Sum | B2: LeetCode | C2: E | D2: Frequency/hashing | E2: complement lookup | F2: 46296 | G2: Yes | H2: 12 | I2: 0 | J2: No | K2: O(n) | L2: O(n) | N2: Store the complement you need, not the values you have seen | O2: 'pair sums to target' + unsorted -> hash complement | P2: =IF($F2="","",IF($J2="Yes",$F2+1,IF($G2="No",$F2+2,IF(N($I2)>2,$F2+3,IF(N($I2)>0,$F2+5,$F2+7))))) | Q2: =IF($P2="","",IF($J2="Yes",$P2+3,IF($G2="No",$P2+5,IF(N($I2)>0,$P2+7,$P2+14)))) | R2: =IF($Q2="","",IF($J2="Yes",$Q2+7,IF($G2="No",$Q2+14,$Q2+30))) | S2: No | T2: Starter example entry | U2: =IF($F2="","",MIN(24,MAX(1,ROUNDUP(($F2-DayPlan!$C$2+1)/7,0)))) | V2: =IF($A2=""," ",4*($J2="Yes")+3*($G2="No")+2*(N($I2)>0)+1*(AND(ISNUMBER($H2),$H2>45))+3*(AND(ISNUMBER($P2),$P2<=TODAY()))-6*($S2="Yes")+(750-ROW())/100000) | W2: =IF(OR($A2="",NOT(ISNUMBER($P2))),"",INT($P2-TODAY())) | X2: No
P3: =IF($F3="","",IF($J3="Yes",$F3+1,IF($G3="No",$F3+2,IF(N($I3)>2,$F3+3,IF(N($I3)>0,$F3+5,$F3+7))))) | Q3: =IF($P3="","",IF($J3="Yes",$P3+3,IF($G3="No",$P3+5,IF(N($I3)>0,$P3+7,$P3+14)))) | R3: =IF($Q3="","",IF($J3="Yes",$Q3+7,IF($G3="No",$Q3+14,$Q3+30))) | U3: =IF($F3="","",MIN(24,MAX(1,ROUNDUP(($F3-DayPlan!$C$2+1)/7,0)))) | V3: =IF($A3=""," ",4*($J3="Yes")+3*($G3="No")+2*(N($I3)>0)+1*(AND(ISNUMBER($H3),$H3>45))+3*(AND(ISNUMBER($P3),$P3<=TODAY()))-6*($S3="Yes")+(750-ROW())/100000) | W3: =IF(OR($A3="",NOT(ISNUMBER($P3))),"",INT($P3-TODAY()))
P4: =IF($F4="","",IF($J4="Yes",$F4+1,IF($G4="No",$F4+2,IF(N($I4)>2,$F4+3,IF(N($I4)>0,$F4+5,$F4+7))))) | Q4: =IF($P4="","",IF($J4="Yes",$P4+3,IF($G4="No",$P4+5,IF(N($I4)>0,$P4+7,$P4+14)))) | R4: =IF($Q4="","",IF($J4="Yes",$Q4+7,IF($G4="No",$Q4+14,$Q4+30))) | U4: =IF($F4="","",MIN(24,MAX(1,ROUNDUP(($F4-DayPlan!$C$2+1)/7,0)))) | V4: =IF($A4=""," ",4*($J4="Yes")+3*($G4="No")+2*(N($I4)>0)+1*(AND(ISNUMBER($H4),$H4>45))+3*(AND(ISNUMBER($P4),$P4<=TODAY()))-6*($S4="Yes")+(750-ROW())/100000) | W4: =IF(OR($A4="",NOT(ISNUMBER($P4))),"",INT($P4-TODAY()))
P5: =IF($F5="","",IF($J5="Yes",$F5+1,IF($G5="No",$F5+2,IF(N($I5)>2,$F5+3,IF(N($I5)>0,$F5+5,$F5+7))))) | Q5: =IF($P5="","",IF($J5="Yes",$P5+3,IF($G5="No",$P5+5,IF(N($I5)>0,$P5+7,$P5+14)))) | R5: =IF($Q5="","",IF($J5="Yes",$Q5+7,IF($G5="No",$Q5+14,$Q5+30))) | U5: =IF($F5="","",MIN(24,MAX(1,ROUNDUP(($F5-DayPlan!$C$2+1)/7,0)))) | V5: =IF($A5=""," ",4*($J5="Yes")+3*($G5="No")+2*(N($I5)>0)+1*(AND(ISNUMBER($H5),$H5>45))+3*(AND(ISNUMBER($P5),$P5<=TODAY()))-6*($S5="Yes")+(750-ROW())/100000) | W5: =IF(OR($A5="",NOT(ISNUMBER($P5))),"",INT($P5-TODAY()))
P6: =IF($F6="","",IF($J6="Yes",$F6+1,IF($G6="No",$F6+2,IF(N($I6)>2,$F6+3,IF(N($I6)>0,$F6+5,$F6+7))))) | Q6: =IF($P6="","",IF($J6="Yes",$P6+3,IF($G6="No",$P6+5,IF(N($I6)>0,$P6+7,$P6+14)))) | R6: =IF($Q6="","",IF($J6="Yes",$Q6+7,IF($G6="No",$Q6+14,$Q6+30))) | U6: =IF($F6="","",MIN(24,MAX(1,ROUNDUP(($F6-DayPlan!$C$2+1)/7,0)))) | V6: =IF($A6=""," ",4*($J6="Yes")+3*($G6="No")+2*(N($I6)>0)+1*(AND(ISNUMBER($H6),$H6>45))+3*(AND(ISNUMBER($P6),$P6<=TODAY()))-6*($S6="Yes")+(750-ROW())/100000) | W6: =IF(OR($A6="",NOT(ISNUMBER($P6))),"",INT($P6-TODAY()))
P7: =IF($F7="","",IF($J7="Yes",$F7+1,IF($G7="No",$F7+2,IF(N($I7)>2,$F7+3,IF(N($I7)>0,$F7+5,$F7+7))))) | Q7: =IF($P7="","",IF($J7="Yes",$P7+3,IF($G7="No",$P7+5,IF(N($I7)>0,$P7+7,$P7+14)))) | R7: =IF($Q7="","",IF($J7="Yes",$Q7+7,IF($G7="No",$Q7+14,$Q7+30))) | U7: =IF($F7="","",MIN(24,MAX(1,ROUNDUP(($F7-DayPlan!$C$2+1)/7,0)))) | V7: =IF($A7=""," ",4*($J7="Yes")+3*($G7="No")+2*(N($I7)>0)+1*(AND(ISNUMBER($H7),$H7>45))+3*(AND(ISNUMBER($P7),$P7<=TODAY()))-6*($S7="Yes")+(750-ROW())/100000) | W7: =IF(OR($A7="",NOT(ISNUMBER($P7))),"",INT($P7-TODAY()))
P8: =IF($F8="","",IF($J8="Yes",$F8+1,IF($G8="No",$F8+2,IF(N($I8)>2,$F8+3,IF(N($I8)>0,$F8+5,$F8+7))))) | Q8: =IF($P8="","",IF($J8="Yes",$P8+3,IF($G8="No",$P8+5,IF(N($I8)>0,$P8+7,$P8+14)))) | R8: =IF($Q8="","",IF($J8="Yes",$Q8+7,IF($G8="No",$Q8+14,$Q8+30))) | U8: =IF($F8="","",MIN(24,MAX(1,ROUNDUP(($F8-DayPlan!$C$2+1)/7,0)))) | V8: =IF($A8=""," ",4*($J8="Yes")+3*($G8="No")+2*(N($I8)>0)+1*(AND(ISNUMBER($H8),$H8>45))+3*(AND(ISNUMBER($P8),$P8<=TODAY()))-6*($S8="Yes")+(750-ROW())/100000) | W8: =IF(OR($A8="",NOT(ISNUMBER($P8))),"",INT($P8-TODAY()))
P9: =IF($F9="","",IF($J9="Yes",$F9+1,IF($G9="No",$F9+2,IF(N($I9)>2,$F9+3,IF(N($I9)>0,$F9+5,$F9+7))))) | Q9: =IF($P9="","",IF($J9="Yes",$P9+3,IF($G9="No",$P9+5,IF(N($I9)>0,$P9+7,$P9+14)))) | R9: =IF($Q9="","",IF($J9="Yes",$Q9+7,IF($G9="No",$Q9+14,$Q9+30))) | U9: =IF($F9="","",MIN(24,MAX(1,ROUNDUP(($F9-DayPlan!$C$2+1)/7,0)))) | V9: =IF($A9=""," ",4*($J9="Yes")+3*($G9="No")+2*(N($I9)>0)+1*(AND(ISNUMBER($H9),$H9>45))+3*(AND(ISNUMBER($P9),$P9<=TODAY()))-6*($S9="Yes")+(750-ROW())/100000) | W9: =IF(OR($A9="",NOT(ISNUMBER($P9))),"",INT($P9-TODAY()))
P10: =IF($F10="","",IF($J10="Yes",$F10+1,IF($G10="No",$F10+2,IF(N($I10)>2,$F10+3,IF(N($I10)>0,$F10+5,$F10+7))))) | Q10: =IF($P10="","",IF($J10="Yes",$P10+3,IF($G10="No",$P10+5,IF(N($I10)>0,$P10+7,$P10+14)))) | R10: =IF($Q10="","",IF($J10="Yes",$Q10+7,IF($G10="No",$Q10+14,$Q10+30))) | U10: =IF($F10="","",MIN(24,MAX(1,ROUNDUP(($F10-DayPlan!$C$2+1)/7,0)))) | V10: =IF($A10=""," ",4*($J10="Yes")+3*($G10="No")+2*(N($I10)>0)+1*(AND(ISNUMBER($H10),$H10>45))+3*(AND(ISNUMBER($P10),$P10<=TODAY()))-6*($S10="Yes")+(750-ROW())/100000) | W10: =IF(OR($A10="",NOT(ISNUMBER($P10))),"",INT($P10-TODAY()))
P11: =IF($F11="","",IF($J11="Yes",$F11+1,IF($G11="No",$F11+2,IF(N($I11)>2,$F11+3,IF(N($I11)>0,$F11+5,$F11+7))))) | Q11: =IF($P11="","",IF($J11="Yes",$P11+3,IF($G11="No",$P11+5,IF(N($I11)>0,$P11+7,$P11+14)))) | R11: =IF($Q11="","",IF($J11="Yes",$Q11+7,IF($G11="No",$Q11+14,$Q11+30))) | U11: =IF($F11="","",MIN(24,MAX(1,ROUNDUP(($F11-DayPlan!$C$2+1)/7,0)))) | V11: =IF($A11=""," ",4*($J11="Yes")+3*($G11="No")+2*(N($I11)>0)+1*(AND(ISNUMBER($H11),$H11>45))+3*(AND(ISNUMBER($P11),$P11<=TODAY()))-6*($S11="Yes")+(750-ROW())/100000) | W11: =IF(OR($A11="",NOT(ISNUMBER($P11))),"",INT($P11-TODAY()))
P12: =IF($F12="","",IF($J12="Yes",$F12+1,IF($G12="No",$F12+2,IF(N($I12)>2,$F12+3,IF(N($I12)>0,$F12+5,$F12+7))))) | Q12: =IF($P12="","",IF($J12="Yes",$P12+3,IF($G12="No",$P12+5,IF(N($I12)>0,$P12+7,$P12+14)))) | R12: =IF($Q12="","",IF($J12="Yes",$Q12+7,IF($G12="No",$Q12+14,$Q12+30))) | U12: =IF($F12="","",MIN(24,MAX(1,ROUNDUP(($F12-DayPlan!$C$2+1)/7,0)))) | V12: =IF($A12=""," ",4*($J12="Yes")+3*($G12="No")+2*(N($I12)>0)+1*(AND(ISNUMBER($H12),$H12>45))+3*(AND(ISNUMBER($P12),$P12<=TODAY()))-6*($S12="Yes")+(750-ROW())/100000) | W12: =IF(OR($A12="",NOT(ISNUMBER($P12))),"",INT($P12-TODAY()))
P13: =IF($F13="","",IF($J13="Yes",$F13+1,IF($G13="No",$F13+2,IF(N($I13)>2,$F13+3,IF(N($I13)>0,$F13+5,$F13+7))))) | Q13: =IF($P13="","",IF($J13="Yes",$P13+3,IF($G13="No",$P13+5,IF(N($I13)>0,$P13+7,$P13+14)))) | R13: =IF($Q13="","",IF($J13="Yes",$Q13+7,IF($G13="No",$Q13+14,$Q13+30))) | U13: =IF($F13="","",MIN(24,MAX(1,ROUNDUP(($F13-DayPlan!$C$2+1)/7,0)))) | V13: =IF($A13=""," ",4*($J13="Yes")+3*($G13="No")+2*(N($I13)>0)+1*(AND(ISNUMBER($H13),$H13>45))+3*(AND(ISNUMBER($P13),$P13<=TODAY()))-6*($S13="Yes")+(750-ROW())/100000) | W13: =IF(OR($A13="",NOT(ISNUMBER($P13))),"",INT($P13-TODAY()))
P14: =IF($F14="","",IF($J14="Yes",$F14+1,IF($G14="No",$F14+2,IF(N($I14)>2,$F14+3,IF(N($I14)>0,$F14+5,$F14+7))))) | Q14: =IF($P14="","",IF($J14="Yes",$P14+3,IF($G14="No",$P14+5,IF(N($I14)>0,$P14+7,$P14+14)))) | R14: =IF($Q14="","",IF($J14="Yes",$Q14+7,IF($G14="No",$Q14+14,$Q14+30))) | U14: =IF($F14="","",MIN(24,MAX(1,ROUNDUP(($F14-DayPlan!$C$2+1)/7,0)))) | V14: =IF($A14=""," ",4*($J14="Yes")+3*($G14="No")+2*(N($I14)>0)+1*(AND(ISNUMBER($H14),$H14>45))+3*(AND(ISNUMBER($P14),$P14<=TODAY()))-6*($S14="Yes")+(750-ROW())/100000) | W14: =IF(OR($A14="",NOT(ISNUMBER($P14))),"",INT($P14-TODAY()))
... P750: =IF($F750="","",IF($J750="Yes",$F750+1,IF($G750="No",$F750+2,IF(N($I750)>2,$F750+3,IF(N($I750)>0,$F750+5,$F750+7))))) | Q750: =IF($P750="","",IF($J750="Yes",$P750+3,IF($G750="No",$P750+5,IF(N($I750)>0,$P750+7,$P750+14)))) | R750: =IF($Q750="","",IF($J750="Yes",$Q750+7,IF($G750="No",$Q750+14,$Q750+30))) | U750: =IF($F750="","",MIN(24,MAX(1,ROUNDUP(($F750-DayPlan!$C$2+1)/7,0)))) | V750: =IF($A750=""," ",4*($J750="Yes")+3*($G750="No")+2*(N($I750)>0)+1*(AND(ISNUMBER($H750),$H750>45))+3*(AND(ISNUMBER($P750),$P750<=TODAY()))-6*($S750="Yes")+(750-ROW())/100000) | W750: =IF(OR($A750="",NOT(ISNUMBER($P750))),"",INT($P750-TODAY()))

Sheet FailureLog
A1: Date | B1: Week | C1: Problem | D1: Failure Type | E1: What I thought (my model) | F1: What was actually wrong | G1: Correct mental model | H1: Preventive rule (one sentence, actionable) | I1: Related problems | J1: Re-test Date | K1: Retest Result | L1: Rule fired on retest?
B2: =IF($A2="","",MIN(24,MAX(1,ROUNDUP(($A2-DayPlan!$C$2+1)/7,0)))) | J2: =IF($A2="","",$A2+3)
B3: =IF($A3="","",MIN(24,MAX(1,ROUNDUP(($A3-DayPlan!$C$2+1)/7,0)))) | J3: =IF($A3="","",$A3+3)
B4: =IF($A4="","",MIN(24,MAX(1,ROUNDUP(($A4-DayPlan!$C$2+1)/7,0)))) | J4: =IF($A4="","",$A4+3)
B5: =IF($A5="","",MIN(24,MAX(1,ROUNDUP(($A5-DayPlan!$C$2+1)/7,0)))) | J5: =IF($A5="","",$A5+3)
B6: =IF($A6="","",MIN(24,MAX(1,ROUNDUP(($A6-DayPlan!$C$2+1)/7,0)))) | J6: =IF($A6="","",$A6+3)
B7: =IF($A7="","",MIN(24,MAX(1,ROUNDUP(($A7-DayPlan!$C$2+1)/7,0)))) | J7: =IF($A7="","",$A7+3)
B8: =IF($A8="","",MIN(24,MAX(1,ROUNDUP(($A8-DayPlan!$C$2+1)/7,0)))) | J8: =IF($A8="","",$A8+3)
B9: =IF($A9="","",MIN(24,MAX(1,ROUNDUP(($A9-DayPlan!$C$2+1)/7,0)))) | J9: =IF($A9="","",$A9+3)
B10: =IF($A10="","",MIN(24,MAX(1,ROUNDUP(($A10-DayPlan!$C$2+1)/7,0)))) | J10: =IF($A10="","",$A10+3)
B11: =IF($A11="","",MIN(24,MAX(1,ROUNDUP(($A11-DayPlan!$C$2+1)/7,0)))) | J11: =IF($A11="","",$A11+3)
B12: =IF($A12="","",MIN(24,MAX(1,ROUNDUP(($A12-DayPlan!$C$2+1)/7,0)))) | J12: =IF($A12="","",$A12+3)
B13: =IF($A13="","",MIN(24,MAX(1,ROUNDUP(($A13-DayPlan!$C$2+1)/7,0)))) | J13: =IF($A13="","",$A13+3)
... B500: =IF($A500="","",MIN(24,MAX(1,ROUNDUP(($A500-DayPlan!$C$2+1)/7,0)))) | J500: =IF($A500="","",$A500+3)

Sheet ReviewQueue
A1: Rank | B1: Problem | C1: Pattern | D1: Diff | E1: Priority | F1: Due Date | G1: Days Overdue | H1: Why Queued | I1: Required Action | J1: Priority Key | L1: PRIORITY FORMULA: 4*(solution viewed) + 3*(not independent) + 2*(hints>0) + 1*(slow >45min) + 3*(overdue) - 6*(mastered). Autosorts by priority. Top 25 shown.
A2: 1 | B2: =IFERROR(INDEX(ProblemDB!$A$2:$A$750,MATCH($J2,ProblemDB!$V$2:$V$750,0)),"") | C2: =IFERROR(INDEX(ProblemDB!$D$2:$D$750,MATCH($J2,ProblemDB!$V$2:$V$750,0)),"") | D2: =IFERROR(INDEX(ProblemDB!$C$2:$C$750,MATCH($J2,ProblemDB!$V$2:$V$750,0)),"") | E2: =IFERROR(INT(IFERROR(INDEX(ProblemDB!$V$2:$V$750,MATCH($J2,ProblemDB!$V$2:$V$750,0)),"")),"") | F2: =IFERROR(INDEX(ProblemDB!$P$2:$P$750,MATCH($J2,ProblemDB!$V$2:$V$750,0)),"") | G2: =IF(OR($F2="",$B2=""),"",INT(TODAY()-$F2)) | H2: =IF($B2="","",IF(IFERROR(INDEX(ProblemDB!$J$2:$J$750,MATCH($J2,ProblemDB!$V$2:$V$750,0)),"")="Yes","Needed the solution (highest priority)",IF(IFERROR(INDEX(ProblemDB!$G$2:$G$750,MATCH($J2,ProblemDB!$V$2:$V$750,0)),"")="No","Not solved independently",IF(N(IFERROR(INDEX(ProblemDB!$I$2:$I$750,MATCH($J2,ProblemDB!$V$2:$V$750,0)),""))>0,"Hint-assisted",IF(AND(ISNUMBER(IFERROR(INDEX(ProblemDB!$H$2:$H$750,MATCH($J2,ProblemDB!$V$2:$V$750,0)),"")),IFERROR(INDEX(ProblemDB!$H$2:$H$750,MATCH($J2,ProblemDB!$V$2:$V$750,0)),"")>45),"Solved slowly (>45 min)","Spaced repetition due"))))) | I2: =IF($B2="","",IF($E2>=7,"Blank editor + timed. Rebuild from scratch. Explain aloud.",IF($E2>=4,"Rederive on paper first, then code clean. No notes.","Retrieval: state trigger + invariant + TC in 60 seconds only."))) | J2: =IFERROR(LARGE(ProblemDB!$V$2:$V$750,A2),"")
A3: 2 | B3: =IFERROR(INDEX(ProblemDB!$A$2:$A$750,MATCH($J3,ProblemDB!$V$2:$V$750,0)),"") | C3: =IFERROR(INDEX(ProblemDB!$D$2:$D$750,MATCH($J3,ProblemDB!$V$2:$V$750,0)),"") | D3: =IFERROR(INDEX(ProblemDB!$C$2:$C$750,MATCH($J3,ProblemDB!$V$2:$V$750,0)),"") | E3: =IFERROR(INT(IFERROR(INDEX(ProblemDB!$V$2:$V$750,MATCH($J3,ProblemDB!$V$2:$V$750,0)),"")),"") | F3: =IFERROR(INDEX(ProblemDB!$P$2:$P$750,MATCH($J3,ProblemDB!$V$2:$V$750,0)),"") | G3: =IF(OR($F3="",$B3=""),"",INT(TODAY()-$F3)) | H3: =IF($B3="","",IF(IFERROR(INDEX(ProblemDB!$J$2:$J$750,MATCH($J3,ProblemDB!$V$2:$V$750,0)),"")="Yes","Needed the solution (highest priority)",IF(IFERROR(INDEX(ProblemDB!$G$2:$G$750,MATCH($J3,ProblemDB!$V$2:$V$750,0)),"")="No","Not solved independently",IF(N(IFERROR(INDEX(ProblemDB!$I$2:$I$750,MATCH($J3,ProblemDB!$V$2:$V$750,0)),""))>0,"Hint-assisted",IF(AND(ISNUMBER(IFERROR(INDEX(ProblemDB!$H$2:$H$750,MATCH($J3,ProblemDB!$V$2:$V$750,0)),"")),IFERROR(INDEX(ProblemDB!$H$2:$H$750,MATCH($J3,ProblemDB!$V$2:$V$750,0)),"")>45),"Solved slowly (>45 min)","Spaced repetition due"))))) | I3: =IF($B3="","",IF($E3>=7,"Blank editor + timed. Rebuild from scratch. Explain aloud.",IF($E3>=4,"Rederive on paper first, then code clean. No notes.","Retrieval: state trigger + invariant + TC in 60 seconds only."))) | J3: =IFERROR(LARGE(ProblemDB!$V$2:$V$750,A3),"")
A4: 3 | B4: =IFERROR(INDEX(ProblemDB!$A$2:$A$750,MATCH($J4,ProblemDB!$V$2:$V$750,0)),"") | C4: =IFERROR(INDEX(ProblemDB!$D$2:$D$750,MATCH($J4,ProblemDB!$V$2:$V$750,0)),"") | D4: =IFERROR(INDEX(ProblemDB!$C$2:$C$750,MATCH($J4,ProblemDB!$V$2:$V$750,0)),"") | E4: =IFERROR(INT(IFERROR(INDEX(ProblemDB!$V$2:$V$750,MATCH($J4,ProblemDB!$V$2:$V$750,0)),"")),"") | F4: =IFERROR(INDEX(ProblemDB!$P$2:$P$750,MATCH($J4,ProblemDB!$V$2:$V$750,0)),"") | G4: =IF(OR($F4="",$B4=""),"",INT(TODAY()-$F4)) | H4: =IF($B4="","",IF(IFERROR(INDEX(ProblemDB!$J$2:$J$750,MATCH($J4,ProblemDB!$V$2:$V$750,0)),"")="Yes","Needed the solution (highest priority)",IF(IFERROR(INDEX(ProblemDB!$G$2:$G$750,MATCH($J4,ProblemDB!$V$2:$V$750,0)),"")="No","Not solved independently",IF(N(IFERROR(INDEX(ProblemDB!$I$2:$I$750,MATCH($J4,ProblemDB!$V$2:$V$750,0)),""))>0,"Hint-assisted",IF(AND(ISNUMBER(IFERROR(INDEX(ProblemDB!$H$2:$H$750,MATCH($J4,ProblemDB!$V$2:$V$750,0)),"")),IFERROR(INDEX(ProblemDB!$H$2:$H$750,MATCH($J4,ProblemDB!$V$2:$V$750,0)),"")>45),"Solved slowly (>45 min)","Spaced repetition due"))))) | I4: =IF($B4="","",IF($E4>=7,"Blank editor + timed. Rebuild from scratch. Explain aloud.",IF($E4>=4,"Rederive on paper first, then code clean. No notes.","Retrieval: state trigger + invariant + TC in 60 seconds only."))) | J4: =IFERROR(LARGE(ProblemDB!$V$2:$V$750,A4),"")
A5: 4 | B5: =IFERROR(INDEX(ProblemDB!$A$2:$A$750,MATCH($J5,ProblemDB!$V$2:$V$750,0)),"") | C5: =IFERROR(INDEX(ProblemDB!$D$2:$D$750,MATCH($J5,ProblemDB!$V$2:$V$750,0)),"") | D5: =IFERROR(INDEX(ProblemDB!$C$2:$C$750,MATCH($J5,ProblemDB!$V$2:$V$750,0)),"") | E5: =IFERROR(INT(IFERROR(INDEX(ProblemDB!$V$2:$V$750,MATCH($J5,ProblemDB!$V$2:$V$750,0)),"")),"") | F5: =IFERROR(INDEX(ProblemDB!$P$2:$P$750,MATCH($J5,ProblemDB!$V$2:$V$750,0)),"") | G5: =IF(OR($F5="",$B5=""),"",INT(TODAY()-$F5)) | H5: =IF($B5="","",IF(IFERROR(INDEX(ProblemDB!$J$2:$J$750,MATCH($J5,ProblemDB!$V$2:$V$750,0)),"")="Yes","Needed the solution (highest priority)",IF(IFERROR(INDEX(ProblemDB!$G$2:$G$750,MATCH($J5,ProblemDB!$V$2:$V$750,0)),"")="No","Not solved independently",IF(N(IFERROR(INDEX(ProblemDB!$I$2:$I$750,MATCH($J5,ProblemDB!$V$2:$V$750,0)),""))>0,"Hint-assisted",IF(AND(ISNUMBER(IFERROR(INDEX(ProblemDB!$H$2:$H$750,MATCH($J5,ProblemDB!$V$2:$V$750,0)),"")),IFERROR(INDEX(ProblemDB!$H$2:$H$750,MATCH($J5,ProblemDB!$V$2:$V$750,0)),"")>45),"Solved slowly (>45 min)","Spaced repetition due"))))) | I5: =IF($B5="","",IF($E5>=7,"Blank editor + timed. Rebuild from scratch. Explain aloud.",IF($E5>=4,"Rederive on paper first, then code clean. No notes.","Retrieval: state trigger + invariant + TC in 60 seconds only."))) | J5: =IFERROR(LARGE(ProblemDB!$V$2:$V$750,A5),"")
A6: 5 | B6: =IFERROR(INDEX(ProblemDB!$A$2:$A$750,MATCH($J6,ProblemDB!$V$2:$V$750,0)),"") | C6: =IFERROR(INDEX(ProblemDB!$D$2:$D$750,MATCH($J6,ProblemDB!$V$2:$V$750,0)),"") | D6: =IFERROR(INDEX(ProblemDB!$C$2:$C$750,MATCH($J6,ProblemDB!$V$2:$V$750,0)),"") | E6: =IFERROR(INT(IFERROR(INDEX(ProblemDB!$V$2:$V$750,MATCH($J6,ProblemDB!$V$2:$V$750,0)),"")),"") | F6: =IFERROR(INDEX(ProblemDB!$P$2:$P$750,MATCH($J6,ProblemDB!$V$2:$V$750,0)),"") | G6: =IF(OR($F6="",$B6=""),"",INT(TODAY()-$F6)) | H6: =IF($B6="","",IF(IFERROR(INDEX(ProblemDB!$J$2:$J$750,MATCH($J6,ProblemDB!$V$2:$V$750,0)),"")="Yes","Needed the solution (highest priority)",IF(IFERROR(INDEX(ProblemDB!$G$2:$G$750,MATCH($J6,ProblemDB!$V$2:$V$750,0)),"")="No","Not solved independently",IF(N(IFERROR(INDEX(ProblemDB!$I$2:$I$750,MATCH($J6,ProblemDB!$V$2:$V$750,0)),""))>0,"Hint-assisted",IF(AND(ISNUMBER(IFERROR(INDEX(ProblemDB!$H$2:$H$750,MATCH($J6,ProblemDB!$V$2:$V$750,0)),"")),IFERROR(INDEX(ProblemDB!$H$2:$H$750,MATCH($J6,ProblemDB!$V$2:$V$750,0)),"")>45),"Solved slowly (>45 min)","Spaced repetition due"))))) | I6: =IF($B6="","",IF($E6>=7,"Blank editor + timed. Rebuild from scratch. Explain aloud.",IF($E6>=4,"Rederive on paper first, then code clean. No notes.","Retrieval: state trigger + invariant + TC in 60 seconds only."))) | J6: =IFERROR(LARGE(ProblemDB!$V$2:$V$750,A6),"")
A7: 6 | B7: =IFERROR(INDEX(ProblemDB!$A$2:$A$750,MATCH($J7,ProblemDB!$V$2:$V$750,0)),"") | C7: =IFERROR(INDEX(ProblemDB!$D$2:$D$750,MATCH($J7,ProblemDB!$V$2:$V$750,0)),"") | D7: =IFERROR(INDEX(ProblemDB!$C$2:$C$750,MATCH($J7,ProblemDB!$V$2:$V$750,0)),"") | E7: =IFERROR(INT(IFERROR(INDEX(ProblemDB!$V$2:$V$750,MATCH($J7,ProblemDB!$V$2:$V$750,0)),"")),"") | F7: =IFERROR(INDEX(ProblemDB!$P$2:$P$750,MATCH($J7,ProblemDB!$V$2:$V$750,0)),"") | G7: =IF(OR($F7="",$B7=""),"",INT(TODAY()-$F7)) | H7: =IF($B7="","",IF(IFERROR(INDEX(ProblemDB!$J$2:$J$750,MATCH($J7,ProblemDB!$V$2:$V$750,0)),"")="Yes","Needed the solution (highest priority)",IF(IFERROR(INDEX(ProblemDB!$G$2:$G$750,MATCH($J7,ProblemDB!$V$2:$V$750,0)),"")="No","Not solved independently",IF(N(IFERROR(INDEX(ProblemDB!$I$2:$I$750,MATCH($J7,ProblemDB!$V$2:$V$750,0)),""))>0,"Hint-assisted",IF(AND(ISNUMBER(IFERROR(INDEX(ProblemDB!$H$2:$H$750,MATCH($J7,ProblemDB!$V$2:$V$750,0)),"")),IFERROR(INDEX(ProblemDB!$H$2:$H$750,MATCH($J7,ProblemDB!$V$2:$V$750,0)),"")>45),"Solved slowly (>45 min)","Spaced repetition due"))))) | I7: =IF($B7="","",IF($E7>=7,"Blank editor + timed. Rebuild from scratch. Explain aloud.",IF($E7>=4,"Rederive on paper first, then code clean. No notes.","Retrieval: state trigger + invariant + TC in 60 seconds only."))) | J7: =IFERROR(LARGE(ProblemDB!$V$2:$V$750,A7),"")
A8: 7 | B8: =IFERROR(INDEX(ProblemDB!$A$2:$A$750,MATCH($J8,ProblemDB!$V$2:$V$750,0)),"") | C8: =IFERROR(INDEX(ProblemDB!$D$2:$D$750,MATCH($J8,ProblemDB!$V$2:$V$750,0)),"") | D8: =IFERROR(INDEX(ProblemDB!$C$2:$C$750,MATCH($J8,ProblemDB!$V$2:$V$750,0)),"") | E8: =IFERROR(INT(IFERROR(INDEX(ProblemDB!$V$2:$V$750,MATCH($J8,ProblemDB!$V$2:$V$750,0)),"")),"") | F8: =IFERROR(INDEX(ProblemDB!$P$2:$P$750,MATCH($J8,ProblemDB!$V$2:$V$750,0)),"") | G8: =IF(OR($F8="",$B8=""),"",INT(TODAY()-$F8)) | H8: =IF($B8="","",IF(IFERROR(INDEX(ProblemDB!$J$2:$J$750,MATCH($J8,ProblemDB!$V$2:$V$750,0)),"")="Yes","Needed the solution (highest priority)",IF(IFERROR(INDEX(ProblemDB!$G$2:$G$750,MATCH($J8,ProblemDB!$V$2:$V$750,0)),"")="No","Not solved independently",IF(N(IFERROR(INDEX(ProblemDB!$I$2:$I$750,MATCH($J8,ProblemDB!$V$2:$V$750,0)),""))>0,"Hint-assisted",IF(AND(ISNUMBER(IFERROR(INDEX(ProblemDB!$H$2:$H$750,MATCH($J8,ProblemDB!$V$2:$V$750,0)),"")),IFERROR(INDEX(ProblemDB!$H$2:$H$750,MATCH($J8,ProblemDB!$V$2:$V$750,0)),"")>45),"Solved slowly (>45 min)","Spaced repetition due"))))) | I8: =IF($B8="","",IF($E8>=7,"Blank editor + timed. Rebuild from scratch. Explain aloud.",IF($E8>=4,"Rederive on paper first, then code clean. No notes.","Retrieval: state trigger + invariant + TC in 60 seconds only."))) | J8: =IFERROR(LARGE(ProblemDB!$V$2:$V$750,A8),"")
A9: 8 | B9: =IFERROR(INDEX(ProblemDB!$A$2:$A$750,MATCH($J9,ProblemDB!$V$2:$V$750,0)),"") | C9: =IFERROR(INDEX(ProblemDB!$D$2:$D$750,MATCH($J9,ProblemDB!$V$2:$V$750,0)),"") | D9: =IFERROR(INDEX(ProblemDB!$C$2:$C$750,MATCH($J9,ProblemDB!$V$2:$V$750,0)),"") | E9: =IFERROR(INT(IFERROR(INDEX(ProblemDB!$V$2:$V$750,MATCH($J9,ProblemDB!$V$2:$V$750,0)),"")),"") | F9: =IFERROR(INDEX(ProblemDB!$P$2:$P$750,MATCH($J9,ProblemDB!$V$2:$V$750,0)),"") | G9: =IF(OR($F9="",$B9=""),"",INT(TODAY()-$F9)) | H9: =IF($B9="","",IF(IFERROR(INDEX(ProblemDB!$J$2:$J$750,MATCH($J9,ProblemDB!$V$2:$V$750,0)),"")="Yes","Needed the solution (highest priority)",IF(IFERROR(INDEX(ProblemDB!$G$2:$G$750,MATCH($J9,ProblemDB!$V$2:$V$750,0)),"")="No","Not solved independently",IF(N(IFERROR(INDEX(ProblemDB!$I$2:$I$750,MATCH($J9,ProblemDB!$V$2:$V$750,0)),""))>0,"Hint-assisted",IF(AND(ISNUMBER(IFERROR(INDEX(ProblemDB!$H$2:$H$750,MATCH($J9,ProblemDB!$V$2:$V$750,0)),"")),IFERROR(INDEX(ProblemDB!$H$2:$H$750,MATCH($J9,ProblemDB!$V$2:$V$750,0)),"")>45),"Solved slowly (>45 min)","Spaced repetition due"))))) | I9: =IF($B9="","",IF($E9>=7,"Blank editor + timed. Rebuild from scratch. Explain aloud.",IF($E9>=4,"Rederive on paper first, then code clean. No notes.","Retrieval: state trigger + invariant + TC in 60 seconds only."))) | J9: =IFERROR(LARGE(ProblemDB!$V$2:$V$750,A9),"")
A10: 9 | B10: =IFERROR(INDEX(ProblemDB!$A$2:$A$750,MATCH($J10,ProblemDB!$V$2:$V$750,0)),"") | C10: =IFERROR(INDEX(ProblemDB!$D$2:$D$750,MATCH($J10,ProblemDB!$V$2:$V$750,0)),"") | D10: =IFERROR(INDEX(ProblemDB!$C$2:$C$750,MATCH($J10,ProblemDB!$V$2:$V$750,0)),"") | E10: =IFERROR(INT(IFERROR(INDEX(ProblemDB!$V$2:$V$750,MATCH($J10,ProblemDB!$V$2:$V$750,0)),"")),"") | F10: =IFERROR(INDEX(ProblemDB!$P$2:$P$750,MATCH($J10,ProblemDB!$V$2:$V$750,0)),"") | G10: =IF(OR($F10="",$B10=""),"",INT(TODAY()-$F10)) | H10: =IF($B10="","",IF(IFERROR(INDEX(ProblemDB!$J$2:$J$750,MATCH($J10,ProblemDB!$V$2:$V$750,0)),"")="Yes","Needed the solution (highest priority)",IF(IFERROR(INDEX(ProblemDB!$G$2:$G$750,MATCH($J10,ProblemDB!$V$2:$V$750,0)),"")="No","Not solved independently",IF(N(IFERROR(INDEX(ProblemDB!$I$2:$I$750,MATCH($J10,ProblemDB!$V$2:$V$750,0)),""))>0,"Hint-assisted",IF(AND(ISNUMBER(IFERROR(INDEX(ProblemDB!$H$2:$H$750,MATCH($J10,ProblemDB!$V$2:$V$750,0)),"")),IFERROR(INDEX(ProblemDB!$H$2:$H$750,MATCH($J10,ProblemDB!$V$2:$V$750,0)),"")>45),"Solved slowly (>45 min)","Spaced repetition due"))))) | I10: =IF($B10="","",IF($E10>=7,"Blank editor + timed. Rebuild from scratch. Explain aloud.",IF($E10>=4,"Rederive on paper first, then code clean. No notes.","Retrieval: state trigger + invariant + TC in 60 seconds only."))) | J10: =IFERROR(LARGE(ProblemDB!$V$2:$V$750,A10),"")
A11: 10 | B11: =IFERROR(INDEX(ProblemDB!$A$2:$A$750,MATCH($J11,ProblemDB!$V$2:$V$750,0)),"") | C11: =IFERROR(INDEX(ProblemDB!$D$2:$D$750,MATCH($J11,ProblemDB!$V$2:$V$750,0)),"") | D11: =IFERROR(INDEX(ProblemDB!$C$2:$C$750,MATCH($J11,ProblemDB!$V$2:$V$750,0)),"") | E11: =IFERROR(INT(IFERROR(INDEX(ProblemDB!$V$2:$V$750,MATCH($J11,ProblemDB!$V$2:$V$750,0)),"")),"") | F11: =IFERROR(INDEX(ProblemDB!$P$2:$P$750,MATCH($J11,ProblemDB!$V$2:$V$750,0)),"") | G11: =IF(OR($F11="",$B11=""),"",INT(TODAY()-$F11)) | H11: =IF($B11="","",IF(IFERROR(INDEX(ProblemDB!$J$2:$J$750,MATCH($J11,ProblemDB!$V$2:$V$750,0)),"")="Yes","Needed the solution (highest priority)",IF(IFERROR(INDEX(ProblemDB!$G$2:$G$750,MATCH($J11,ProblemDB!$V$2:$V$750,0)),"")="No","Not solved independently",IF(N(IFERROR(INDEX(ProblemDB!$I$2:$I$750,MATCH($J11,ProblemDB!$V$2:$V$750,0)),""))>0,"Hint-assisted",IF(AND(ISNUMBER(IFERROR(INDEX(ProblemDB!$H$2:$H$750,MATCH($J11,ProblemDB!$V$2:$V$750,0)),"")),IFERROR(INDEX(ProblemDB!$H$2:$H$750,MATCH($J11,ProblemDB!$V$2:$V$750,0)),"")>45),"Solved slowly (>45 min)","Spaced repetition due"))))) | I11: =IF($B11="","",IF($E11>=7,"Blank editor + timed. Rebuild from scratch. Explain aloud.",IF($E11>=4,"Rederive on paper first, then code clean. No notes.","Retrieval: state trigger + invariant + TC in 60 seconds only."))) | J11: =IFERROR(LARGE(ProblemDB!$V$2:$V$750,A11),"")
A12: 11 | B12: =IFERROR(INDEX(ProblemDB!$A$2:$A$750,MATCH($J12,ProblemDB!$V$2:$V$750,0)),"") | C12: =IFERROR(INDEX(ProblemDB!$D$2:$D$750,MATCH($J12,ProblemDB!$V$2:$V$750,0)),"") | D12: =IFERROR(INDEX(ProblemDB!$C$2:$C$750,MATCH($J12,ProblemDB!$V$2:$V$750,0)),"") | E12: =IFERROR(INT(IFERROR(INDEX(ProblemDB!$V$2:$V$750,MATCH($J12,ProblemDB!$V$2:$V$750,0)),"")),"") | F12: =IFERROR(INDEX(ProblemDB!$P$2:$P$750,MATCH($J12,ProblemDB!$V$2:$V$750,0)),"") | G12: =IF(OR($F12="",$B12=""),"",INT(TODAY()-$F12)) | H12: =IF($B12="","",IF(IFERROR(INDEX(ProblemDB!$J$2:$J$750,MATCH($J12,ProblemDB!$V$2:$V$750,0)),"")="Yes","Needed the solution (highest priority)",IF(IFERROR(INDEX(ProblemDB!$G$2:$G$750,MATCH($J12,ProblemDB!$V$2:$V$750,0)),"")="No","Not solved independently",IF(N(IFERROR(INDEX(ProblemDB!$I$2:$I$750,MATCH($J12,ProblemDB!$V$2:$V$750,0)),""))>0,"Hint-assisted",IF(AND(ISNUMBER(IFERROR(INDEX(ProblemDB!$H$2:$H$750,MATCH($J12,ProblemDB!$V$2:$V$750,0)),"")),IFERROR(INDEX(ProblemDB!$H$2:$H$750,MATCH($J12,ProblemDB!$V$2:$V$750,0)),"")>45),"Solved slowly (>45 min)","Spaced repetition due"))))) | I12: =IF($B12="","",IF($E12>=7,"Blank editor + timed. Rebuild from scratch. Explain aloud.",IF($E12>=4,"Rederive on paper first, then code clean. No notes.","Retrieval: state trigger + invariant + TC in 60 seconds only."))) | J12: =IFERROR(LARGE(ProblemDB!$V$2:$V$750,A12),"")
A13: 12 | B13: =IFERROR(INDEX(ProblemDB!$A$2:$A$750,MATCH($J13,ProblemDB!$V$2:$V$750,0)),"") | C13: =IFERROR(INDEX(ProblemDB!$D$2:$D$750,MATCH($J13,ProblemDB!$V$2:$V$750,0)),"") | D13: =IFERROR(INDEX(ProblemDB!$C$2:$C$750,MATCH($J13,ProblemDB!$V$2:$V$750,0)),"") | E13: =IFERROR(INT(IFERROR(INDEX(ProblemDB!$V$2:$V$750,MATCH($J13,ProblemDB!$V$2:$V$750,0)),"")),"") | F13: =IFERROR(INDEX(ProblemDB!$P$2:$P$750,MATCH($J13,ProblemDB!$V$2:$V$750,0)),"") | G13: =IF(OR($F13="",$B13=""),"",INT(TODAY()-$F13)) | H13: =IF($B13="","",IF(IFERROR(INDEX(ProblemDB!$J$2:$J$750,MATCH($J13,ProblemDB!$V$2:$V$750,0)),"")="Yes","Needed the solution (highest priority)",IF(IFERROR(INDEX(ProblemDB!$G$2:$G$750,MATCH($J13,ProblemDB!$V$2:$V$750,0)),"")="No","Not solved independently",IF(N(IFERROR(INDEX(ProblemDB!$I$2:$I$750,MATCH($J13,ProblemDB!$V$2:$V$750,0)),""))>0,"Hint-assisted",IF(AND(ISNUMBER(IFERROR(INDEX(ProblemDB!$H$2:$H$750,MATCH($J13,ProblemDB!$V$2:$V$750,0)),"")),IFERROR(INDEX(ProblemDB!$H$2:$H$750,MATCH($J13,ProblemDB!$V$2:$V$750,0)),"")>45),"Solved slowly (>45 min)","Spaced repetition due"))))) | I13: =IF($B13="","",IF($E13>=7,"Blank editor + timed. Rebuild from scratch. Explain aloud.",IF($E13>=4,"Rederive on paper first, then code clean. No notes.","Retrieval: state trigger + invariant + TC in 60 seconds only."))) | J13: =IFERROR(LARGE(ProblemDB!$V$2:$V$750,A13),"")
... A26: 25 | B26: =IFERROR(INDEX(ProblemDB!$A$2:$A$750,MATCH($J26,ProblemDB!$V$2:$V$750,0)),"") | C26: =IFERROR(INDEX(ProblemDB!$D$2:$D$750,MATCH($J26,ProblemDB!$V$2:$V$750,0)),"") | D26: =IFERROR(INDEX(ProblemDB!$C$2:$C$750,MATCH($J26,ProblemDB!$V$2:$V$750,0)),"") | E26: =IFERROR(INT(IFERROR(INDEX(ProblemDB!$V$2:$V$750,MATCH($J26,ProblemDB!$V$2:$V$750,0)),"")),"") | F26: =IFERROR(INDEX(ProblemDB!$P$2:$P$750,MATCH($J26,ProblemDB!$V$2:$V$750,0)),"") | G26: =IF(OR($F26="",$B26=""),"",INT(TODAY()-$F26)) | H26: =IF($B26="","",IF(IFERROR(INDEX(ProblemDB!$J$2:$J$750,MATCH($J26,ProblemDB!$V$2:$V$750,0)),"")="Yes","Needed the solution (highest priority)",IF(IFERROR(INDEX(ProblemDB!$G$2:$G$750,MATCH($J26,ProblemDB!$V$2:$V$750,0)),"")="No","Not solved independently",IF(N(IFERROR(INDEX(ProblemDB!$I$2:$I$750,MATCH($J26,ProblemDB!$V$2:$V$750,0)),""))>0,"Hint-assisted",IF(AND(ISNUMBER(IFERROR(INDEX(ProblemDB!$H$2:$H$750,MATCH($J26,ProblemDB!$V$2:$V$750,0)),"")),IFERROR(INDEX(ProblemDB!$H$2:$H$750,MATCH($J26,ProblemDB!$V$2:$V$750,0)),"")>45),"Solved slowly (>45 min)","Spaced repetition due"))))) | I26: =IF($B26="","",IF($E26>=7,"Blank editor + timed. Rebuild from scratch. Explain aloud.",IF($E26>=4,"Rederive on paper first, then code clean. No notes.","Retrieval: state trigger + invariant + TC in 60 seconds only."))) | J26: =IFERROR(LARGE(ProblemDB!$V$2:$V$750,A26),"")

Sheet WeeklyAssessment
A1: Week | B1: Theme | C1: Attempted | D1: Independent | E1: Hint-assisted | F1: Solution needed | G1: Avg time (min) | H1: Pattern recog (1-5) | I1: Complexity (1-5) | J1: Coding accuracy (1-5) | K1: Debugging (1-5) | L1: Explanation (1-5) | M1: Retention (1-5) | N1: Week score (/5) | O1: Dominant failure | P1: Biggest weakness | Q1: Next week focus | R1: F2 count | S1: F3 count | T1: F5 count | U1: F10 count | V1: Auto-escalation triggered?
A2: 1 | B2: Constraints + Counting + Hashing + Prefix | C2: =COUNTIFS(ProblemDB!$U$2:$U$750,$A2) | D2: =COUNTIFS(ProblemDB!$U$2:$U$750,$A2,ProblemDB!$G$2:$G$750,"Yes") | E2: =COUNTIFS(ProblemDB!$U$2:$U$750,$A2,ProblemDB!$I$2:$I$750,">0") | F2: =COUNTIFS(ProblemDB!$U$2:$U$750,$A2,ProblemDB!$J$2:$J$750,"Yes") | G2: =IFERROR(ROUND(AVERAGEIFS(ProblemDB!$H$2:$H$750,ProblemDB!$U$2:$U$750,$A2),0),"") | N2: =IFERROR(ROUND(AVERAGE($H2:$M2),1),"") | R2: =COUNTIFS(FailureLog!$D$2:$D$500,"F2-Pattern",FailureLog!$B$2:$B$500,$A2) | S2: =COUNTIFS(FailureLog!$D$2:$D$500,"F3-Derive",FailureLog!$B$2:$B$500,$A2) | T2: =COUNTIFS(FailureLog!$D$2:$D$500,"F5-Complexity",FailureLog!$B$2:$B$500,$A2) | U2: =COUNTIFS(FailureLog!$D$2:$D$500,"F10-Pressure",FailureLog!$B$2:$B$500,$A2) | V2: =IF(OR($R2>=3,$S2>=3,$T2>=3,$U2>=3),"YES - see README","No")
A3: 2 | B3: Two Pointers + Sliding Window (variable + counting + fixed) | C3: =COUNTIFS(ProblemDB!$U$2:$U$750,$A3) | D3: =COUNTIFS(ProblemDB!$U$2:$U$750,$A3,ProblemDB!$G$2:$G$750,"Yes") | E3: =COUNTIFS(ProblemDB!$U$2:$U$750,$A3,ProblemDB!$I$2:$I$750,">0") | F3: =COUNTIFS(ProblemDB!$U$2:$U$750,$A3,ProblemDB!$J$2:$J$750,"Yes") | G3: =IFERROR(ROUND(AVERAGEIFS(ProblemDB!$H$2:$H$750,ProblemDB!$U$2:$U$750,$A3),0),"") | N3: =IFERROR(ROUND(AVERAGE($H3:$M3),1),"") | R3: =COUNTIFS(FailureLog!$D$2:$D$500,"F2-Pattern",FailureLog!$B$2:$B$500,$A3) | S3: =COUNTIFS(FailureLog!$D$2:$D$500,"F3-Derive",FailureLog!$B$2:$B$500,$A3) | T3: =COUNTIFS(FailureLog!$D$2:$D$500,"F5-Complexity",FailureLog!$B$2:$B$500,$A3) | U3: =COUNTIFS(FailureLog!$D$2:$D$500,"F10-Pressure",FailureLog!$B$2:$B$500,$A3) | V3: =IF(OR($R3>=3,$S3>=3,$T3>=3,$U3>=3),"YES - see README","No")
A4: 3 | B4: Binary Search (index + rotated + on-answer) | C4: =COUNTIFS(ProblemDB!$U$2:$U$750,$A4) | D4: =COUNTIFS(ProblemDB!$U$2:$U$750,$A4,ProblemDB!$G$2:$G$750,"Yes") | E4: =COUNTIFS(ProblemDB!$U$2:$U$750,$A4,ProblemDB!$I$2:$I$750,">0") | F4: =COUNTIFS(ProblemDB!$U$2:$U$750,$A4,ProblemDB!$J$2:$J$750,"Yes") | G4: =IFERROR(ROUND(AVERAGEIFS(ProblemDB!$H$2:$H$750,ProblemDB!$U$2:$U$750,$A4),0),"") | N4: =IFERROR(ROUND(AVERAGE($H4:$M4),1),"") | R4: =COUNTIFS(FailureLog!$D$2:$D$500,"F2-Pattern",FailureLog!$B$2:$B$500,$A4) | S4: =COUNTIFS(FailureLog!$D$2:$D$500,"F3-Derive",FailureLog!$B$2:$B$500,$A4) | T4: =COUNTIFS(FailureLog!$D$2:$D$500,"F5-Complexity",FailureLog!$B$2:$B$500,$A4) | U4: =COUNTIFS(FailureLog!$D$2:$D$500,"F10-Pressure",FailureLog!$B$2:$B$500,$A4) | V4: =IF(OR($R4>=3,$S4>=3,$T4>=3,$U4>=3),"YES - see README","No")
A5: 4 | B5: Sort + Intervals/Sweep + Monotonic Stack/Deque + Diagnostic 1 | C5: =COUNTIFS(ProblemDB!$U$2:$U$750,$A5) | D5: =COUNTIFS(ProblemDB!$U$2:$U$750,$A5,ProblemDB!$G$2:$G$750,"Yes") | E5: =COUNTIFS(ProblemDB!$U$2:$U$750,$A5,ProblemDB!$I$2:$I$750,">0") | F5: =COUNTIFS(ProblemDB!$U$2:$U$750,$A5,ProblemDB!$J$2:$J$750,"Yes") | G5: =IFERROR(ROUND(AVERAGEIFS(ProblemDB!$H$2:$H$750,ProblemDB!$U$2:$U$750,$A5),0),"") | N5: =IFERROR(ROUND(AVERAGE($H5:$M5),1),"") | R5: =COUNTIFS(FailureLog!$D$2:$D$500,"F2-Pattern",FailureLog!$B$2:$B$500,$A5) | S5: =COUNTIFS(FailureLog!$D$2:$D$500,"F3-Derive",FailureLog!$B$2:$B$500,$A5) | T5: =COUNTIFS(FailureLog!$D$2:$D$500,"F5-Complexity",FailureLog!$B$2:$B$500,$A5) | U5: =COUNTIFS(FailureLog!$D$2:$D$500,"F10-Pressure",FailureLog!$B$2:$B$500,$A5) | V5: =IF(OR($R5>=3,$S5>=3,$T5>=3,$U5>=3),"YES - see README","No")
A6: 5 | B6: Heaps + Streaming Statistics + Greedy (proof-based) | C6: =COUNTIFS(ProblemDB!$U$2:$U$750,$A6) | D6: =COUNTIFS(ProblemDB!$U$2:$U$750,$A6,ProblemDB!$G$2:$G$750,"Yes") | E6: =COUNTIFS(ProblemDB!$U$2:$U$750,$A6,ProblemDB!$I$2:$I$750,">0") | F6: =COUNTIFS(ProblemDB!$U$2:$U$750,$A6,ProblemDB!$J$2:$J$750,"Yes") | G6: =IFERROR(ROUND(AVERAGEIFS(ProblemDB!$H$2:$H$750,ProblemDB!$U$2:$U$750,$A6),0),"") | N6: =IFERROR(ROUND(AVERAGE($H6:$M6),1),"") | R6: =COUNTIFS(FailureLog!$D$2:$D$500,"F2-Pattern",FailureLog!$B$2:$B$500,$A6) | S6: =COUNTIFS(FailureLog!$D$2:$D$500,"F3-Derive",FailureLog!$B$2:$B$500,$A6) | T6: =COUNTIFS(FailureLog!$D$2:$D$500,"F5-Complexity",FailureLog!$B$2:$B$500,$A6) | U6: =COUNTIFS(FailureLog!$D$2:$D$500,"F10-Pressure",FailureLog!$B$2:$B$500,$A6) | V6: =IF(OR($R6>=3,$S6>=3,$T6>=3,$U6>=3),"YES - see README","No")
A7: 6 | B7: Design (LRU/LFU) + Linked List Pointers + Bit Manipulation | C7: =COUNTIFS(ProblemDB!$U$2:$U$750,$A7) | D7: =COUNTIFS(ProblemDB!$U$2:$U$750,$A7,ProblemDB!$G$2:$G$750,"Yes") | E7: =COUNTIFS(ProblemDB!$U$2:$U$750,$A7,ProblemDB!$I$2:$I$750,">0") | F7: =COUNTIFS(ProblemDB!$U$2:$U$750,$A7,ProblemDB!$J$2:$J$750,"Yes") | G7: =IFERROR(ROUND(AVERAGEIFS(ProblemDB!$H$2:$H$750,ProblemDB!$U$2:$U$750,$A7),0),"") | N7: =IFERROR(ROUND(AVERAGE($H7:$M7),1),"") | R7: =COUNTIFS(FailureLog!$D$2:$D$500,"F2-Pattern",FailureLog!$B$2:$B$500,$A7) | S7: =COUNTIFS(FailureLog!$D$2:$D$500,"F3-Derive",FailureLog!$B$2:$B$500,$A7) | T7: =COUNTIFS(FailureLog!$D$2:$D$500,"F5-Complexity",FailureLog!$B$2:$B$500,$A7) | U7: =COUNTIFS(FailureLog!$D$2:$D$500,"F10-Pressure",FailureLog!$B$2:$B$500,$A7) | V7: =IF(OR($R7>=3,$S7>=3,$T7>=3,$U7>=3),"YES - see README","No")
A8: 7 | B8: Tree Recursion (contract) + Tree DP + BST + Serialization | C8: =COUNTIFS(ProblemDB!$U$2:$U$750,$A8) | D8: =COUNTIFS(ProblemDB!$U$2:$U$750,$A8,ProblemDB!$G$2:$G$750,"Yes") | E8: =COUNTIFS(ProblemDB!$U$2:$U$750,$A8,ProblemDB!$I$2:$I$750,">0") | F8: =COUNTIFS(ProblemDB!$U$2:$U$750,$A8,ProblemDB!$J$2:$J$750,"Yes") | G8: =IFERROR(ROUND(AVERAGEIFS(ProblemDB!$H$2:$H$750,ProblemDB!$U$2:$U$750,$A8),0),"") | N8: =IFERROR(ROUND(AVERAGE($H8:$M8),1),"") | R8: =COUNTIFS(FailureLog!$D$2:$D$500,"F2-Pattern",FailureLog!$B$2:$B$500,$A8) | S8: =COUNTIFS(FailureLog!$D$2:$D$500,"F3-Derive",FailureLog!$B$2:$B$500,$A8) | T8: =COUNTIFS(FailureLog!$D$2:$D$500,"F5-Complexity",FailureLog!$B$2:$B$500,$A8) | U8: =COUNTIFS(FailureLog!$D$2:$D$500,"F10-Pressure",FailureLog!$B$2:$B$500,$A8) | V8: =IF(OR($R8>=3,$S8>=3,$T8>=3,$U8>=3),"YES - see README","No")
A9: 8 | B9: Tries + Cross-Pattern Fusion + Communication + Diagnostic 2 | C9: =COUNTIFS(ProblemDB!$U$2:$U$750,$A9) | D9: =COUNTIFS(ProblemDB!$U$2:$U$750,$A9,ProblemDB!$G$2:$G$750,"Yes") | E9: =COUNTIFS(ProblemDB!$U$2:$U$750,$A9,ProblemDB!$I$2:$I$750,">0") | F9: =COUNTIFS(ProblemDB!$U$2:$U$750,$A9,ProblemDB!$J$2:$J$750,"Yes") | G9: =IFERROR(ROUND(AVERAGEIFS(ProblemDB!$H$2:$H$750,ProblemDB!$U$2:$U$750,$A9),0),"") | N9: =IFERROR(ROUND(AVERAGE($H9:$M9),1),"") | R9: =COUNTIFS(FailureLog!$D$2:$D$500,"F2-Pattern",FailureLog!$B$2:$B$500,$A9) | S9: =COUNTIFS(FailureLog!$D$2:$D$500,"F3-Derive",FailureLog!$B$2:$B$500,$A9) | T9: =COUNTIFS(FailureLog!$D$2:$D$500,"F5-Complexity",FailureLog!$B$2:$B$500,$A9) | U9: =COUNTIFS(FailureLog!$D$2:$D$500,"F10-Pressure",FailureLog!$B$2:$B$500,$A9) | V9: =IF(OR($R9>=3,$S9>=3,$T9>=3,$U9>=3),"YES - see README","No")
A10: 9 | B10: Graph Modelling + BFS/DFS + Union Find + Topological Sort | C10: =COUNTIFS(ProblemDB!$U$2:$U$750,$A10) | D10: =COUNTIFS(ProblemDB!$U$2:$U$750,$A10,ProblemDB!$G$2:$G$750,"Yes") | E10: =COUNTIFS(ProblemDB!$U$2:$U$750,$A10,ProblemDB!$I$2:$I$750,">0") | F10: =COUNTIFS(ProblemDB!$U$2:$U$750,$A10,ProblemDB!$J$2:$J$750,"Yes") | G10: =IFERROR(ROUND(AVERAGEIFS(ProblemDB!$H$2:$H$750,ProblemDB!$U$2:$U$750,$A10),0),"") | N10: =IFERROR(ROUND(AVERAGE($H10:$M10),1),"") | R10: =COUNTIFS(FailureLog!$D$2:$D$500,"F2-Pattern",FailureLog!$B$2:$B$500,$A10) | S10: =COUNTIFS(FailureLog!$D$2:$D$500,"F3-Derive",FailureLog!$B$2:$B$500,$A10) | T10: =COUNTIFS(FailureLog!$D$2:$D$500,"F5-Complexity",FailureLog!$B$2:$B$500,$A10) | U10: =COUNTIFS(FailureLog!$D$2:$D$500,"F10-Pressure",FailureLog!$B$2:$B$500,$A10) | V10: =IF(OR($R10>=3,$S10>=3,$T10>=3,$U10>=3),"YES - see README","No")
A11: 10 | B11: BFS Shortest Path + State-Space BFS + Dijkstra + Dijkstra Variants | C11: =COUNTIFS(ProblemDB!$U$2:$U$750,$A11) | D11: =COUNTIFS(ProblemDB!$U$2:$U$750,$A11,ProblemDB!$G$2:$G$750,"Yes") | E11: =COUNTIFS(ProblemDB!$U$2:$U$750,$A11,ProblemDB!$I$2:$I$750,">0") | F11: =COUNTIFS(ProblemDB!$U$2:$U$750,$A11,ProblemDB!$J$2:$J$750,"Yes") | G11: =IFERROR(ROUND(AVERAGEIFS(ProblemDB!$H$2:$H$750,ProblemDB!$U$2:$U$750,$A11),0),"") | N11: =IFERROR(ROUND(AVERAGE($H11:$M11),1),"") | R11: =COUNTIFS(FailureLog!$D$2:$D$500,"F2-Pattern",FailureLog!$B$2:$B$500,$A11) | S11: =COUNTIFS(FailureLog!$D$2:$D$500,"F3-Derive",FailureLog!$B$2:$B$500,$A11) | T11: =COUNTIFS(FailureLog!$D$2:$D$500,"F5-Complexity",FailureLog!$B$2:$B$500,$A11) | U11: =COUNTIFS(FailureLog!$D$2:$D$500,"F10-Pressure",FailureLog!$B$2:$B$500,$A11) | V11: =IF(OR($R11>=3,$S11>=3,$T11>=3,$U11>=3),"YES - see README","No")
A12: 11 | B12: Backtracking (dedup + pruning + bitmask) + Memoisation Bridge | C12: =COUNTIFS(ProblemDB!$U$2:$U$750,$A12) | D12: =COUNTIFS(ProblemDB!$U$2:$U$750,$A12,ProblemDB!$G$2:$G$750,"Yes") | E12: =COUNTIFS(ProblemDB!$U$2:$U$750,$A12,ProblemDB!$I$2:$I$750,">0") | F12: =COUNTIFS(ProblemDB!$U$2:$U$750,$A12,ProblemDB!$J$2:$J$750,"Yes") | G12: =IFERROR(ROUND(AVERAGEIFS(ProblemDB!$H$2:$H$750,ProblemDB!$U$2:$U$750,$A12),0),"") | N12: =IFERROR(ROUND(AVERAGE($H12:$M12),1),"") | R12: =COUNTIFS(FailureLog!$D$2:$D$500,"F2-Pattern",FailureLog!$B$2:$B$500,$A12) | S12: =COUNTIFS(FailureLog!$D$2:$D$500,"F3-Derive",FailureLog!$B$2:$B$500,$A12) | T12: =COUNTIFS(FailureLog!$D$2:$D$500,"F5-Complexity",FailureLog!$B$2:$B$500,$A12) | U12: =COUNTIFS(FailureLog!$D$2:$D$500,"F10-Pressure",FailureLog!$B$2:$B$500,$A12) | V12: =IF(OR($R12>=3,$S12>=3,$T12>=3,$U12>=3),"YES - see README","No")
A13: 12 | B13: DP 1D + LIS + Knapsack + Two-Sequence + Space Optimization + Diagnostic 3 | C13: =COUNTIFS(ProblemDB!$U$2:$U$750,$A13) | D13: =COUNTIFS(ProblemDB!$U$2:$U$750,$A13,ProblemDB!$G$2:$G$750,"Yes") | E13: =COUNTIFS(ProblemDB!$U$2:$U$750,$A13,ProblemDB!$I$2:$I$750,">0") | F13: =COUNTIFS(ProblemDB!$U$2:$U$750,$A13,ProblemDB!$J$2:$J$750,"Yes") | G13: =IFERROR(ROUND(AVERAGEIFS(ProblemDB!$H$2:$H$750,ProblemDB!$U$2:$U$750,$A13),0),"") | N13: =IFERROR(ROUND(AVERAGE($H13:$M13),1),"") | R13: =COUNTIFS(FailureLog!$D$2:$D$500,"F2-Pattern",FailureLog!$B$2:$B$500,$A13) | S13: =COUNTIFS(FailureLog!$D$2:$D$500,"F3-Derive",FailureLog!$B$2:$B$500,$A13) | T13: =COUNTIFS(FailureLog!$D$2:$D$500,"F5-Complexity",FailureLog!$B$2:$B$500,$A13) | U13: =COUNTIFS(FailureLog!$D$2:$D$500,"F10-Pressure",FailureLog!$B$2:$B$500,$A13) | V13: =IF(OR($R13>=3,$S13>=3,$T13>=3,$U13>=3),"YES - see README","No")
... A25: 24 | B25: Capstone Grand Diagnostics, Memory Allocators & Systems Mastery | C25: =COUNTIFS(ProblemDB!$U$2:$U$750,$A25) | D25: =COUNTIFS(ProblemDB!$U$2:$U$750,$A25,ProblemDB!$G$2:$G$750,"Yes") | E25: =COUNTIFS(ProblemDB!$U$2:$U$750,$A25,ProblemDB!$I$2:$I$750,">0") | F25: =COUNTIFS(ProblemDB!$U$2:$U$750,$A25,ProblemDB!$J$2:$J$750,"Yes") | G25: =IFERROR(ROUND(AVERAGEIFS(ProblemDB!$H$2:$H$750,ProblemDB!$U$2:$U$750,$A25),0),"") | N25: =IFERROR(ROUND(AVERAGE($H25:$M25),1),"") | R25: =COUNTIFS(FailureLog!$D$2:$D$500,"F2-Pattern",FailureLog!$B$2:$B$500,$A25) | S25: =COUNTIFS(FailureLog!$D$2:$D$500,"F3-Derive",FailureLog!$B$2:$B$500,$A25) | T25: =COUNTIFS(FailureLog!$D$2:$D$500,"F5-Complexity",FailureLog!$B$2:$B$500,$A25) | U25: =COUNTIFS(FailureLog!$D$2:$D$500,"F10-Pressure",FailureLog!$B$2:$B$500,$A25) | V25: =IF(OR($R25>=3,$S25>=3,$T25>=3,$U25>=3),"YES - see README","No")

Sheet MockInterviews
A1: Planned Day | B1: Date | C1: Type | D1: Problem | E1: Difficulty | F1: Time Limit (min) | G1: Solved? | H1: Time Taken (min) | I1: Hints Used | J1: Time to Pattern (min) | K1: Explanation (1-5) | L1: TC/SC accuracy (1-5) | M1: Follow-up (1-5) | N1: Final Score (/10) | O1: Main Weakness | P1: Concrete Fix for Next Mock | Q1: Compared to previous mock
A2: 28 | B2: 46323 | C2: Diagnostic 1 | D2: LC 918 Max Sum Circular Subarray (unlabelled) | E2: M | F2: 30 | N2: =IFERROR(ROUND(AVERAGE($K2:$M2)*2,1),"N/A") | Q2: baseline
A3: 28 | B3: 46323 | C3: Diagnostic 1 | D3: LC 795 Subarrays with Bounded Max (unlabelled) | E3: M | F3: 30 | N3: =IFERROR(ROUND(AVERAGE($K3:$M3)*2,1),"N/A") | Q3: =IF(OR(NOT(ISNUMBER($N3)),NOT(ISNUMBER($N2))),"",IF($N3>$N2,"Improved (+"&ROUND($N3-$N2,1)&" pts)",IF($N3<$N2,"Regressed (-"&ROUND($N2-$N3,1)&" pts)","Unchanged")))
A4: 28 | B4: 46323 | C4: Diagnostic 1 | D4: LC 581 Shortest Unsorted Continuous Subarray (unlabelled) | E4: M | F4: 30 | N4: =IFERROR(ROUND(AVERAGE($K4:$M4)*2,1),"N/A") | Q4: =IF(OR(NOT(ISNUMBER($N4)),NOT(ISNUMBER($N3))),"",IF($N4>$N3,"Improved (+"&ROUND($N4-$N3,1)&" pts)",IF($N4<$N3,"Regressed (-"&ROUND($N3-$N4,1)&" pts)","Unchanged")))
A5: 42 | B5: 46337 | C5: Mock #1 (2 hints) | D5: 1 medium problem - narrate every decision aloud | E5: M | F5: 45 | N5: =IFERROR(ROUND(AVERAGE($K5:$M5)*2,1),"N/A") | Q5: =IF(OR(NOT(ISNUMBER($N5)),NOT(ISNUMBER($N4))),"",IF($N5>$N4,"Improved (+"&ROUND($N5-$N4,1)&" pts)",IF($N5<$N4,"Regressed (-"&ROUND($N4-$N5,1)&" pts)","Unchanged")))
A6: 56 | B6: 46351 | C6: Diagnostic 2 | D6: LC 315 Count of Smaller After Self (unlabelled) | E6: H | F6: 34 | N6: =IFERROR(ROUND(AVERAGE($K6:$M6)*2,1),"N/A") | Q6: =IF(OR(NOT(ISNUMBER($N6)),NOT(ISNUMBER($N5))),"",IF($N6>$N5,"Improved (+"&ROUND($N6-$N5,1)&" pts)",IF($N6<$N5,"Regressed (-"&ROUND($N5-$N6,1)&" pts)","Unchanged")))
A7: 56 | B7: 46351 | C7: Diagnostic 2 | D7: LC 1110 Delete Nodes and Return Forest (unlabelled) | E7: M | F7: 33 | N7: =IFERROR(ROUND(AVERAGE($K7:$M7)*2,1),"N/A") | Q7: =IF(OR(NOT(ISNUMBER($N7)),NOT(ISNUMBER($N6))),"",IF($N7>$N6,"Improved (+"&ROUND($N7-$N6,1)&" pts)",IF($N7<$N6,"Regressed (-"&ROUND($N6-$N7,1)&" pts)","Unchanged")))
A8: 56 | B8: 46351 | C8: Diagnostic 2 | D8: LC 1396 Design Underground System (unlabelled) | E8: M | F8: 33 | N8: =IFERROR(ROUND(AVERAGE($K8:$M8)*2,1),"N/A") | Q8: =IF(OR(NOT(ISNUMBER($N8)),NOT(ISNUMBER($N7))),"",IF($N8>$N7,"Improved (+"&ROUND($N8-$N7,1)&" pts)",IF($N8<$N7,"Regressed (-"&ROUND($N7-$N8,1)&" pts)","Unchanged")))
A9: 70 | B9: 46365 | C9: Mock #2 (1 hint) | D9: 1 medium-hard + 1 infra follow-up question | E9: H | F9: 45 | N9: =IFERROR(ROUND(AVERAGE($K9:$M9)*2,1),"N/A") | Q9: =IF(OR(NOT(ISNUMBER($N9)),NOT(ISNUMBER($N8))),"",IF($N9>$N8,"Improved (+"&ROUND($N9-$N8,1)&" pts)",IF($N9<$N8,"Regressed (-"&ROUND($N8-$N9,1)&" pts)","Unchanged")))
A10: 84 | B10: 46379 | C10: Diagnostic 3 | D10: LC 1383 Maximum Performance of a Team (unlabelled) | E10: H | F10: 37 | N10: =IFERROR(ROUND(AVERAGE($K10:$M10)*2,1),"N/A") | Q10: =IF(OR(NOT(ISNUMBER($N10)),NOT(ISNUMBER($N9))),"",IF($N10>$N9,"Improved (+"&ROUND($N10-$N9,1)&" pts)",IF($N10<$N9,"Regressed (-"&ROUND($N9-$N10,1)&" pts)","Unchanged")))
A11: 84 | B11: 46379 | C11: Diagnostic 3 | D11: LC 1326 Min Taps to Water Garden (unlabelled) | E11: H | F11: 37 | N11: =IFERROR(ROUND(AVERAGE($K11:$M11)*2,1),"N/A") | Q11: =IF(OR(NOT(ISNUMBER($N11)),NOT(ISNUMBER($N10))),"",IF($N11>$N10,"Improved (+"&ROUND($N11-$N10,1)&" pts)",IF($N11<$N10,"Regressed (-"&ROUND($N10-$N11,1)&" pts)","Unchanged")))
A12: 84 | B12: 46379 | C12: Diagnostic 3 | D12: LC 2092 Find All People With Secret (unlabelled) | E12: M | F12: 36 | N12: =IFERROR(ROUND(AVERAGE($K12:$M12)*2,1),"N/A") | Q12: =IF(OR(NOT(ISNUMBER($N12)),NOT(ISNUMBER($N11))),"",IF($N12>$N11,"Improved (+"&ROUND($N12-$N11,1)&" pts)",IF($N12<$N11,"Regressed (-"&ROUND($N11-$N12,1)&" pts)","Unchanged")))
A13: 92 | B13: 46387 | C13: Mock #3 (no hints) | D13: 1 medium + 1 hard follow-up - verbal throughout | E13: H | F13: 50 | N13: =IFERROR(ROUND(AVERAGE($K13:$M13)*2,1),"N/A") | Q13: =IF(OR(NOT(ISNUMBER($N13)),NOT(ISNUMBER($N12))),"",IF($N13>$N12,"Improved (+"&ROUND($N13-$N12,1)&" pts)",IF($N13<$N12,"Regressed (-"&ROUND($N12-$N13,1)&" pts)","Unchanged")))
A14: 95 | B14: 46390 | C14: Mock #4 (unfamiliar) | D14: 1 unfamiliar hard from blind pool - no hints | E14: H | F14: 45 | N14: =IFERROR(ROUND(AVERAGE($K14:$M14)*2,1),"N/A") | Q14: =IF(OR(NOT(ISNUMBER($N14)),NOT(ISNUMBER($N13))),"",IF($N14>$N13,"Improved (+"&ROUND($N14-$N13,1)&" pts)",IF($N14<$N13,"Regressed (-"&ROUND($N13-$N14,1)&" pts)","Unchanged")))
... A25: 168 | B25: 46463 | C25: Grand Diagnostic | D25: Final 3 Unlabelled Multi-Domain Hard Problems | E25: H | F25: 120 | N25: =IFERROR(ROUND(AVERAGE($K25:$M25)*2,1),"N/A") | Q25: =IF(OR(NOT(ISNUMBER($N25)),NOT(ISNUMBER($N24))),"",IF($N25>$N24,"Improved (+"&ROUND($N25-$N24,1)&" pts)",IF($N25<$N24,"Regressed (-"&ROUND($N24-$N25,1)&" pts)","Unchanged")))

Sheet ResourcePlan
A1: Day | B1: Resource | C1: Topic | D1: Where | E1: Duration (min) | F1: Why needed (what mental model gap) | G1: What to EXTRACT | H1: What NOT to memorize | I1: Problems immediately after | J1: What to recall next day | K1: Watched? | L1: Watch-by Date | M1: Primary YouTube Video | N1: 📺 Striver | O1: 📺 Aditya Verma | P1: 📺 Love Babbar | Q1: 📺 Padho with Pratyush | R1: 📺 NeetCode | S1: 📺 Other / Specialized | U1: RULE: 35 tutorials in 168 days = the cap. Every tutorial not on this list that you watch is procrastination. Log it as a productivity trap in FailureLog if you break this rule.
A2: 1 | B2: NeetCode / CPH ch.2 | C2: Big-O + n -> TC constraint mapping | D2: neetcode.io + CPH ch.2 | E2: 25 | F2: Without this you cannot eliminate approaches before coding - most expensive mistake in interviews | G2: The n -> feasible-TC table; how to read constraints; O(n^2) death at n=10^5 | H2: Formal limit definitions; big-O arithmetic proofs | I2: LC 1, LC 121 | J2: Recite the n -> TC table from memory | L2: =IF($A2="","",INDEX(DayPlan!$C$2:$C$169,MATCH($A2,DayPlan!$A$2:$A$169,0))) | M2: =HYPERLINK("https://www.youtube.com/watch?v=EAR7De6Goz4", "▶ Watch (Striver) ↗") | N2: =HYPERLINK("https://www.youtube.com/results?search_query=striver%20c%2B%2B%20basics%20for%20beginners%20setup", "📺 Striver ↗") | O2: — | P2: =HYPERLINK("https://www.youtube.com/results?search_query=love%20babbar%20c%2B%2B%20course%20lecture%201%20introduction", "📺 Love Babbar ↗") | Q2: — | R2: =HYPERLINK("https://www.youtube.com/results?search_query=neetcode%20getting%20started%20with%20leetcode", "📺 NeetCode ↗") | S2: =HYPERLINK("https://www.youtube.com/results?search_query=codehelp%20c%2B%2B%20first%20program", "📺 CodeHelp ↗")
A3: 3 | B3: NeetCode | C3: Prefix sums and prefix+hashmap | D3: neetcode.io (Subarray Sum Equals K) | E3: 20 | F3: Prefix+hash is non-obvious and reused for 12+ weeks; gaps here compound badly | G3: Why a COUNT map beats a seen-set; why prefix[0]=0 must be seeded; loop invariant | H3: The exact code; how to handle overflow | I3: LC 560, LC 238 | J3: Explain the prefix invariant in one sentence | L3: =IF($A3="","",INDEX(DayPlan!$C$2:$C$169,MATCH($A3,DayPlan!$A$2:$A$169,0))) | M3: =HYPERLINK("https://www.youtube.com/watch?v=9TlHvipP5yA", "▶ Watch (Abdul Bari) ↗") | N3: =HYPERLINK("https://www.youtube.com/results?search_query=striver%20time%20complexity%20big%20o%20notation", "📺 Striver ↗") | O3: — | P3: =HYPERLINK("https://www.youtube.com/results?search_query=love%20babbar%20time%20and%20space%20complexity", "📺 Love Babbar ↗") | Q3: — | R3: =HYPERLINK("https://www.youtube.com/results?search_query=neetcode%20big%20o%20notation", "📺 NeetCode ↗") | S3: =HYPERLINK("https://www.youtube.com/results?search_query=abdul%20bari%20algorithm%20analysis%20time%20complexity%20big%20o", "📺 Abdul Bari ↗")
A4: 8 | B4: NeetCode | C4: Two pointers: why the movement is valid | D4: neetcode.io (Two Sum II / 3Sum) | E4: 20 | F4: Most learners memorize the motion but cannot explain why no valid pair is skipped | G4: The discard argument for each pointer move; the duplicate-skip rule and why it is safe | H4: The loop skeleton as a template | I4: LC 167, LC 15 | J4: State the discard argument without notes | L4: =IF($A4="","",INDEX(DayPlan!$C$2:$C$169,MATCH($A4,DayPlan!$A$2:$A$169,0))) | M4: =HYPERLINK("https://www.youtube.com/watch?v=KEs5UyBJ39g", "▶ Watch (Striver) ↗") | N4: =HYPERLINK("https://www.youtube.com/results?search_query=striver%20hashing%20hashmap%20frequency%20counting", "📺 Striver ↗") | O4: =HYPERLINK("https://www.youtube.com/results?search_query=aditya%20verma%20hashing%20map%20frequency", "📺 Aditya Verma ↗") | P4: =HYPERLINK("https://www.youtube.com/results?search_query=love%20babbar%20hashing%20hashmap", "📺 Love Babbar ↗") | Q4: — | R4: =HYPERLINK("https://www.youtube.com/results?search_query=neetcode%20valid%20anagram%20contains%20duplicate", "📺 NeetCode ↗") | S4: —
A5: 10 | B5: NeetCode | C5: Sliding window: expand/shrink + when it FAILS | D5: neetcode.io (Longest Substring) | E5: 25 | F5: Knowing when the window is INVALID (non-monotone conditions) prevents silent wrong answers | G5: The monotone feasibility condition; the loop invariant; one example where window fails | H5: The while-loop skeleton | I5: LC 3, LC 209 | J5: Name a problem where sliding window fails and why | L5: =IF($A5="","",INDEX(DayPlan!$C$2:$C$169,MATCH($A5,DayPlan!$A$2:$A$169,0))) | M5: =HYPERLINK("https://www.youtube.com/watch?v=cQ1Oz4ckceM", "▶ Watch (NeetCode) ↗") | N5: =HYPERLINK("https://www.youtube.com/results?search_query=striver%20two%20pointers%20sorted%20array%20two%20sum%202", "📺 Striver ↗") | O5: — | P5: =HYPERLINK("https://www.youtube.com/results?search_query=love%20babbar%20two%20pointer%20sorted%20array", "📺 Love Babbar ↗") | Q5: — | R5: =HYPERLINK("https://www.youtube.com/results?search_query=neetcode%20two%20sum%20ii%20input%20array%20is%20sorted", "📺 NeetCode ↗") | S5: —
A6: 15 | B6: NeetCode + CPH ch.3 | C6: Binary search boundaries: invariant-first | D6: neetcode.io + CPH ch.3 | E6: 25 | F6: Off-by-one bugs here corrupt every future binary search problem silently | G6: Half-open invariant; lower_bound vs upper_bound; how to derive the correct loop condition | H6: Any memorized lo/hi template | I6: LC 704, LC 34 | J6: Write lower_bound cold with no template | L6: =IF($A6="","",INDEX(DayPlan!$C$2:$C$169,MATCH($A6,DayPlan!$A$2:$A$169,0))) | M6: =HYPERLINK("https://www.youtube.com/watch?v=DfljaUwZsOk", "▶ Watch (Padho with Pratyush) ↗") | N6: =HYPERLINK("https://www.youtube.com/results?search_query=striver%20binary%20search%20playlist", "📺 Striver ↗") | O6: =HYPERLINK("https://www.youtube.com/results?search_query=aditya%20verma%20binary%20search%20playlist", "📺 Aditya Verma ↗") | P6: =HYPERLINK("https://www.youtube.com/results?search_query=love%20babbar%20binary%20search", "📺 Love Babbar ↗") | Q6: =HYPERLINK("https://www.youtube.com/results?search_query=padho%20with%20pratyush%20binary%20search", "📺 Padho with Pratyush ↗") | R6: =HYPERLINK("https://www.youtube.com/results?search_query=neetcode%20binary%20search", "📺 NeetCode ↗") | S6: —
A7: 17 | B7: NeetCode | C7: Binary search on answer (parametric search) | D7: neetcode.io (Koko / Ship) | E7: 25 | F7: Single highest-leverage pattern in this program; appears disguised in infra interviews | G7: The 3 validity conditions; how to write feasible(); why the answer space is monotone | H7: Specific predicates from the video | I7: LC 875, LC 1011 | J7: State the 3 validity conditions | L7: =IF($A7="","",INDEX(DayPlan!$C$2:$C$169,MATCH($A7,DayPlan!$A$2:$A$169,0))) | M7: =HYPERLINK("https://www.youtube.com/watch?v=C2apEw9pgtw", "▶ Watch (Abdul Bari) ↗") | N7: =HYPERLINK("https://www.youtube.com/results?search_query=striver%20binary%20search%20on%20answers%20koko%20eating%20bananas", "📺 Striver ↗") | O7: =HYPERLINK("https://www.youtube.com/results?search_query=aditya%20verma%20allocate%20minimum%20number%20of%20pages%20binary%20search", "📺 Aditya Verma ↗") | P7: =HYPERLINK("https://www.youtube.com/results?search_query=love%20babbar%20book%20allocation%20painter%20partition%20binary%20search", "📺 Love Babbar ↗") | Q7: =HYPERLINK("https://www.youtube.com/results?search_query=padho%20with%20pratyush%20binary%20search%20on%20answers", "📺 Padho with Pratyush ↗") | R7: =HYPERLINK("https://www.youtube.com/results?search_query=neetcode%20koko%20eating%20bananas", "📺 NeetCode ↗") | S7: —
A8: 23 | B8: CPH ch.30 / cp-algorithms | C8: Sweep line and event counting | D8: CPH ch.30 | E8: 20 | F8: Interval problems collapse once you model them as a sweep; two equivalent implementations | G8: Event encoding (+1/-1); tie-breaking between end and start events at the same time | H8: Library implementations | I8: LC 253, LC 1094 | J8: Sweep vs heap equivalence proof | L8: =IF($A8="","",INDEX(DayPlan!$C$2:$C$169,MATCH($A8,DayPlan!$A$2:$A$169,0))) | M8: =HYPERLINK("https://www.youtube.com/watch?v=Nq7ok-OyEpg", "▶ Watch (Striver) ↗") | N8: =HYPERLINK("https://www.youtube.com/results?search_query=striver%20meeting%20rooms%20merge%20intervals", "📺 Striver ↗") | O8: =HYPERLINK("https://www.youtube.com/results?search_query=aditya%20verma%20interval%20merge", "📺 Aditya Verma ↗") | P8: =HYPERLINK("https://www.youtube.com/results?search_query=love%20babbar%20merge%20intervals", "📺 Love Babbar ↗") | Q8: =HYPERLINK("https://www.youtube.com/results?search_query=padho%20with%20pratyush%20line%20sweep%20intervals", "📺 Padho with Pratyush ↗") | R8: =HYPERLINK("https://www.youtube.com/results?search_query=neetcode%20meeting%20rooms%20insert%20interval", "📺 NeetCode ↗") | S8: —
A9: 24 | B9: NeetCode | C9: Monotonic stack from first principles | D9: neetcode.io (Daily Temperatures) | E9: 25 | F9: The amortized argument is the reusable, transferable part - not the specific loop | G9: Why total pops <= n; what the stack invariant is at any moment; where the answer is resolved | H9: Problem-specific loop code | I9: LC 739, LC 503 | J9: Explain amortization in 60 seconds to a sceptical listener | L9: =IF($A9="","",INDEX(DayPlan!$C$2:$C$169,MATCH($A9,DayPlan!$A$2:$A$169,0))) | M9: =HYPERLINK("https://www.youtube.com/watch?v=wiOo4DC5GGA", "▶ Watch (Padho with Pratyush) ↗") | N9: =HYPERLINK("https://www.youtube.com/results?search_query=striver%20next%20greater%20element%20monotonic%20stack", "📺 Striver ↗") | O9: =HYPERLINK("https://www.youtube.com/results?search_query=aditya%20verma%20stack%20playlist%20nearest%20greater%20to%20right", "📺 Aditya Verma ↗") | P9: =HYPERLINK("https://www.youtube.com/results?search_query=love%20babbar%20largest%20rectangle%20in%20histogram%20stack", "📺 Love Babbar ↗") | Q9: =HYPERLINK("https://www.youtube.com/results?search_query=padho%20with%20pratyush%20monotonic%20stack", "📺 Padho with Pratyush ↗") | R9: =HYPERLINK("https://www.youtube.com/results?search_query=neetcode%20daily%20temperatures%20monotonic%20stack", "📺 NeetCode ↗") | S9: —
A10: 29 | B10: NeetCode + CPH ch.4 | C10: Heaps: sift-up/down, heapify, cost comparison | D10: neetcode.io + CPH ch.4 | E10: 25 | F10: You must be able to compare heap vs sort cost on the spot; heapify being O(n) is non-obvious | G10: Partial-order insight; heapify O(n) proof sketch; when O(n log k) < O(n log n) | H10: Manual heap implementation details | I10: LC 215, LC 973 | J10: Compare heap vs sort cost for specific k/n values | L10: =IF($A10="","",INDEX(DayPlan!$C$2:$C$169,MATCH($A10,DayPlan!$A$2:$A$169,0))) | M10: =HYPERLINK("https://www.youtube.com/watch?v=NXOOYYwpbg4", "▶ Watch (Aditya Verma) ↗") | N10: =HYPERLINK("https://www.youtube.com/results?search_query=striver%20heaps%20priority%20queue%20playlist", "📺 Striver ↗") | O10: =HYPERLINK("https://www.youtube.com/results?search_query=aditya%20verma%20heap%20playlist%20kth%20smallest%20element", "📺 Aditya Verma ↗") | P10: =HYPERLINK("https://www.youtube.com/results?search_query=love%20babbar%20heap%20data%20structure%20heapify", "📺 Love Babbar ↗") | Q10: =HYPERLINK("https://www.youtube.com/results?search_query=padho%20with%20pratyush%20heap%20priority%20queue", "📺 Padho with Pratyush ↗") | R10: — | S10: =HYPERLINK("https://www.youtube.com/results?search_query=abdul%20bari%20heap%20sort%20heapify", "📺 Abdul Bari ↗")
A11: 32 | B11: CPH ch.6 | C11: Proving greedy: exchange and staying-ahead arguments | D11: CPH ch.6 | E11: 20 | F11: Unproven greedy is the top hard-interview failure; you need two reusable proof schemas | G11: Exchange argument schema; staying-ahead argument schema; how to construct counterexamples | H11: Specific greedy solutions from the chapter | I11: LC 45, LC 134 | J11: Give an exchange argument proof for LC 45 | L11: =IF($A11="","",INDEX(DayPlan!$C$2:$C$169,MATCH($A11,DayPlan!$A$2:$A$169,0))) | M11: =HYPERLINK("https://www.youtube.com/watch?v=2Rr2tW9zvRg", "▶ Watch (Abdul Bari) ↗") | N11: =HYPERLINK("https://www.youtube.com/results?search_query=striver%20greedy%20algorithms%20playlist", "📺 Striver ↗") | O11: =HYPERLINK("https://www.youtube.com/results?search_query=aditya%20verma%20greedy%20algorithms", "📺 Aditya Verma ↗") | P11: =HYPERLINK("https://www.youtube.com/results?search_query=love%20babbar%20greedy%20algorithm", "📺 Love Babbar ↗") | Q11: =HYPERLINK("https://www.youtube.com/results?search_query=padho%20with%20pratyush%20greedy%20exchange%20argument", "📺 Padho with Pratyush ↗") | R11: =HYPERLINK("https://www.youtube.com/results?search_query=neetcode%20jump%20game%20gas%20station", "📺 NeetCode ↗") | S11: =HYPERLINK("https://www.youtube.com/results?search_query=abdul%20bari%20greedy%20method%20knapsack", "📺 Abdul Bari ↗")
A12: 37 | B12: NeetCode | C12: LRU cache design: structure composition | D12: neetcode.io (LRU Cache) | E12: 20 | F12: Canonical structure-composition problem and an AI-infra interview staple | G12: Why hashmap+DLL yields O(1) on all ops; the deletion and move-to-front invariant | H12: Boilerplate node class code | I12: LC 146, LC 142 | J12: Rebuild LRU from a blank file in under 20 minutes | L12: =IF($A12="","",INDEX(DayPlan!$C$2:$C$169,MATCH($A12,DayPlan!$A$2:$A$169,0))) | M12: =HYPERLINK("https://www.youtube.com/watch?v=R_Mfw4ew-Vo", "▶ Watch (Striver) ↗") | N12: =HYPERLINK("https://www.youtube.com/results?search_query=striver%20lru%20cache%20implementation", "📺 Striver ↗") | O12: =HYPERLINK("https://www.youtube.com/results?search_query=aditya%20verma%20lru%20cache", "📺 Aditya Verma ↗") | P12: =HYPERLINK("https://www.youtube.com/results?search_query=love%20babbar%20lru%20cache", "📺 Love Babbar ↗") | Q12: =HYPERLINK("https://www.youtube.com/results?search_query=padho%20with%20pratyush%20lru%20cache", "📺 Padho with Pratyush ↗") | R12: =HYPERLINK("https://www.youtube.com/results?search_query=neetcode%20lru%20cache", "📺 NeetCode ↗") | S12: —
A13: 39 | B13: CPH ch.10 | C13: Bit manipulation that actually recurs | D13: CPH ch.10 | E13: 20 | F13: Needed for bitmask DP in week 13; also for constraint-tracking in backtracking | G13: Mask set/clear/test/iterate-all-subsets; XOR cancellation; popcount | H13: Exotic hacks that do not appear in interviews | I13: LC 137, LC 371 | J13: Write subset iteration with bitmasks | L13: =IF($A13="","",INDEX(DayPlan!$C$2:$C$169,MATCH($A13,DayPlan!$A$2:$A$169,0))) | M13: =HYPERLINK("https://www.youtube.com/watch?v=xXKL9YBWgCY", "▶ Watch (Errichto) ↗") | N13: =HYPERLINK("https://www.youtube.com/results?search_query=striver%20bit%20manipulation%20playlist", "📺 Striver ↗") | O13: =HYPERLINK("https://www.youtube.com/results?search_query=aditya%20verma%20bit%20manipulation", "📺 Aditya Verma ↗") | P13: =HYPERLINK("https://www.youtube.com/results?search_query=love%20babbar%20bitwise%20operators", "📺 Love Babbar ↗") | Q13: =HYPERLINK("https://www.youtube.com/results?search_query=padho%20with%20pratyush%20bitmask", "📺 Padho with Pratyush ↗") | R13: =HYPERLINK("https://www.youtube.com/results?search_query=neetcode%20bit%20manipulation", "📺 NeetCode ↗") | S13: —
A14: 43 | B14: NeetCode | C14: Recursion as contract + call stack | D14: neetcode.io (tree basics) | E14: 25 | F14: Contract-first recursion eliminates most tree bugs before they happen | G14: How to state a return contract precisely in English; how the call stack relates to a tree traversal | H14: Individual tree solutions from the video | I14: LC 104, LC 110 | J14: State two recursion contracts from today's problems | L14: =IF($A14="","",INDEX(DayPlan!$C$2:$C$169,MATCH($A14,DayPlan!$A$2:$A$169,0))) | M14: =HYPERLINK("https://www.youtube.com/watch?v=jmy0LaGET1I", "▶ Watch (Striver) ↗") | N14: =HYPERLINK("https://www.youtube.com/results?search_query=striver%20binary%20tree%20series%20playlist", "📺 Striver ↗") | O14: =HYPERLINK("https://www.youtube.com/results?search_query=aditya%20verma%20recursion%20playlist", "📺 Aditya Verma ↗") | P14: =HYPERLINK("https://www.youtube.com/results?search_query=love%20babbar%20binary%20tree%20recursion", "📺 Love Babbar ↗") | Q14: =HYPERLINK("https://www.youtube.com/results?search_query=padho%20with%20pratyush%20binary%20tree", "📺 Padho with Pratyush ↗") | R14: =HYPERLINK("https://www.youtube.com/results?search_query=neetcode%20binary%20tree%20maximum%20path%20sum", "📺 NeetCode ↗") | S14: —
A15: 50 | B15: NeetCode | C15: Trie construction and use | D15: neetcode.io (Implement Trie) | E15: 20 | F15: New data structure with a non-obvious memory/TC trade-off | G15: Node layout; insert/search; memory trade-off vs hashset; when trie loses | H15: Array-vs-map micro-implementation details | I15: LC 208, LC 139 | J15: State the trie vs hashset trade-off clearly | L15: =IF($A15="","",INDEX(DayPlan!$C$2:$C$169,MATCH($A15,DayPlan!$A$2:$A$169,0))) | M15: =HYPERLINK("https://www.youtube.com/watch?v=p7-9UvDQZ3w", "▶ Watch (Striver) ↗") | N15: =HYPERLINK("https://www.youtube.com/results?search_query=striver%20trie%20series%20playlist", "📺 Striver ↗") | O15: =HYPERLINK("https://www.youtube.com/results?search_query=aditya%20verma%20trie", "📺 Aditya Verma ↗") | P15: =HYPERLINK("https://www.youtube.com/results?search_query=love%20babbar%20trie%20implementation", "📺 Love Babbar ↗") | Q15: =HYPERLINK("https://www.youtube.com/results?search_query=padho%20with%20pratyush%20trie", "📺 Padho with Pratyush ↗") | R15: =HYPERLINK("https://www.youtube.com/results?search_query=neetcode%20implement%20trie", "📺 NeetCode ↗") | S15: —
A16: 57 | B16: NeetCode + CPH ch.11-12 | C16: Graph representations + BFS/DFS discipline | D16: neetcode.io + CPH ch.11 | E16: 25 | F16: Modelling errors cause more graph failures than algorithm errors; visited discipline is critical | G16: Adjacency list vs matrix trade-offs; mark on PUSH not POP; the input that breaks pop-marking | H16: Grid-specific boilerplate code | I16: LC 200, LC 133 | J16: State when to mark visited and why; construct the breaking input | L16: =IF($A16="","",INDEX(DayPlan!$C$2:$C$169,MATCH($A16,DayPlan!$A$2:$A$169,0))) | M16: =HYPERLINK("https://www.youtube.com/watch?v=13m9ZCB8gjw", "▶ Watch (Padho with Pratyush) ↗") | N16: =HYPERLINK("https://www.youtube.com/results?search_query=striver%20graph%20series%20bfs%20dfs", "📺 Striver ↗") | O16: =HYPERLINK("https://www.youtube.com/results?search_query=aditya%20verma%20graph%20bfs%20dfs", "📺 Aditya Verma ↗") | P16: =HYPERLINK("https://www.youtube.com/results?search_query=love%20babbar%20graph%20series%20bfs%20dfs", "📺 Love Babbar ↗") | Q16: =HYPERLINK("https://www.youtube.com/results?search_query=padho%20with%20pratyush%20graph", "📺 Padho with Pratyush ↗") | R16: — | S16: =HYPERLINK("https://www.youtube.com/results?search_query=williamfiset%20graph%20theory", "📺 WilliamFiset ↗")
A17: 59 | B17: WilliamFiset (YouTube) | C17: Union-Find with path compression + union by size | D17: WilliamFiset DSU video | E17: 25 | F17: DSU appears heavily in infra-style problems; must be writeable cold in 5 minutes | G17: Both optimizations and why each is needed; amortized complexity argument | H17: The complexity proof details | I17: LC 547, LC 684 | J17: Write DSU cold from memory in under 5 minutes | L17: =IF($A17="","",INDEX(DayPlan!$C$2:$C$169,MATCH($A17,DayPlan!$A$2:$A$169,0))) | M17: =HYPERLINK("https://www.youtube.com/watch?v=dBGUmUQhjaM", "▶ Watch (Striver) ↗") | N17: =HYPERLINK("https://www.youtube.com/results?search_query=striver%20disjoint%20set%20union%20find", "📺 Striver ↗") | O17: — | P17: =HYPERLINK("https://www.youtube.com/results?search_query=love%20babbar%20kruskal%20disjoint%20set", "📺 Love Babbar ↗") | Q17: =HYPERLINK("https://www.youtube.com/results?search_query=padho%20with%20pratyush%20dsu", "📺 Padho with Pratyush ↗") | R17: =HYPERLINK("https://www.youtube.com/results?search_query=neetcode%20redundant%20connection%20union%20find", "📺 NeetCode ↗") | S17: =HYPERLINK("https://www.youtube.com/results?search_query=williamfiset%20disjoint%20set%20union%20find", "📺 WilliamFiset ↗")
A18: 61 | B18: NeetCode + CPH ch.16 | C18: Topological sort: Kahn + DFS colours | D18: neetcode.io + CPH ch.16 | E18: 20 | F18: DAG scheduling is the most infra-relevant graph pattern; must know two implementations | G18: In-degree invariant; cycle detection in BOTH variants; what happens to isolated nodes | H18: One fixed implementation as a template | I18: LC 207, LC 210 | J18: Explain cycle detection in both implementations | L18: =IF($A18="","",INDEX(DayPlan!$C$2:$C$169,MATCH($A18,DayPlan!$A$2:$A$169,0))) | M18: =HYPERLINK("https://www.youtube.com/watch?v=asbcE9mZz_U", "▶ Watch (Padho with Pratyush) ↗") | N18: =HYPERLINK("https://www.youtube.com/results?search_query=striver%20topological%20sort%20kahns%20algorithm", "📺 Striver ↗") | O18: =HYPERLINK("https://www.youtube.com/results?search_query=aditya%20verma%20topological%20sort", "📺 Aditya Verma ↗") | P18: =HYPERLINK("https://www.youtube.com/results?search_query=love%20babbar%20topological%20sort%20kahn", "📺 Love Babbar ↗") | Q18: =HYPERLINK("https://www.youtube.com/results?search_query=padho%20with%20pratyush%20topological%20sort", "📺 Padho with Pratyush ↗") | R18: =HYPERLINK("https://www.youtube.com/results?search_query=neetcode%20course%20schedule%20topological%20sort", "📺 NeetCode ↗") | S18: —
A19: 65 | B19: cp-algorithms.com | C19: State-space search: state encoding and counting | D19: cp-algorithms (BFS) | E19: 20 | F19: Keying visited on partial state is a silent bug that produces wrong answers - very hard to debug | G19: How to define a full state tuple; how to count the state space and derive TC from it | H19: Puzzle-specific state encodings | I19: LC 1293, LC 433 | J19: Define a state tuple for a new problem before coding | L19: =IF($A19="","",INDEX(DayPlan!$C$2:$C$169,MATCH($A19,DayPlan!$A$2:$A$169,0))) | M19: =HYPERLINK("https://www.youtube.com/watch?v=iTBaI90lpDQ", "▶ Watch (take U forward) ↗") | N19: =HYPERLINK("https://www.youtube.com/results?search_query=striver%20word%20ladder%20bfs%20shortest%20path", "📺 Striver ↗") | O19: =HYPERLINK("https://www.youtube.com/results?search_query=aditya%20verma%20bfs%20shortest%20path", "📺 Aditya Verma ↗") | P19: =HYPERLINK("https://www.youtube.com/results?search_query=love%20babbar%20word%20ladder%20shortest%20path%20bfs", "📺 Love Babbar ↗") | Q19: =HYPERLINK("https://www.youtube.com/results?search_query=padho%20with%20pratyush%20state%20space%20search%20bfs", "📺 Padho with Pratyush ↗") | R19: =HYPERLINK("https://www.youtube.com/results?search_query=neetcode%20word%20ladder", "📺 NeetCode ↗") | S19: —
A20: 66 | B20: WilliamFiset + CPH ch.13 | C20: Dijkstra: correctness proof | D20: WilliamFiset Dijkstra + CPH ch.13 | E20: 25 | F20: You must know WHY the algorithm works, not just the code; negative edges are a common trap | G20: Relaxation; popped-distance invariant; why negative weights break the invariant | H20: Fibonacci-heap or D-ary heap variants | I20: LC 743, LC 1514 | J20: Prove the popped-node invariant; give the negative-weight counterexample | L20: =IF($A20="","",INDEX(DayPlan!$C$2:$C$169,MATCH($A20,DayPlan!$A$2:$A$169,0))) | M20: =HYPERLINK("https://www.youtube.com/watch?v=EgI5nU9etnU", "▶ Watch (NeetCode) ↗") | N20: =HYPERLINK("https://www.youtube.com/results?search_query=striver%20dijkstra%20algorithm%20priority%20queue", "📺 Striver ↗") | O20: — | P20: =HYPERLINK("https://www.youtube.com/results?search_query=love%20babbar%20dijkstra%20shortest%20path", "📺 Love Babbar ↗") | Q20: =HYPERLINK("https://www.youtube.com/results?search_query=padho%20with%20pratyush%20dijkstra", "📺 Padho with Pratyush ↗") | R20: — | S20: =HYPERLINK("https://www.youtube.com/results?search_query=abdul%20bari%20dijkstra%20algorithm", "📺 Abdul Bari ↗")
A21: 71 | B21: NeetCode | C21: Backtracking: template + complexity counting | D21: neetcode.io (Subsets) | E21: 25 | F21: Backtracking complexity counting is almost never taught; you need it for every hard interview | G21: Choose/explore/unchoose; counting recursion-tree leaves for TC; pruning effect on the tree | H21: Per-problem backtracking templates | I21: LC 78, LC 39 | J21: Count the leaves of a specific recursion tree | L21: =IF($A21="","",INDEX(DayPlan!$C$2:$C$169,MATCH($A21,DayPlan!$A$2:$A$169,0))) | M21: =HYPERLINK("https://www.youtube.com/watch?v=pcKY4hjDrxk", "▶ Watch (Abdul Bari) ↗") | N21: =HYPERLINK("https://www.youtube.com/results?search_query=striver%20backtracking%20n%20queens%20subsets", "📺 Striver ↗") | O21: =HYPERLINK("https://www.youtube.com/results?search_query=aditya%20verma%20backtracking%20playlist", "📺 Aditya Verma ↗") | P21: =HYPERLINK("https://www.youtube.com/results?search_query=love%20babbar%20backtracking%20rat%20in%20a%20maze", "📺 Love Babbar ↗") | Q21: =HYPERLINK("https://www.youtube.com/results?search_query=padho%20with%20pratyush%20backtracking", "📺 Padho with Pratyush ↗") | R21: =HYPERLINK("https://www.youtube.com/results?search_query=neetcode%20subsets%20backtracking", "📺 NeetCode ↗") | S21: —
A22: 76 | B22: NeetCode | C22: From recursion to memoisation: state identification | D22: neetcode.io (DP intro) | E22: 20 | F22: State identification is the bridge into all DP; without it you cannot design new DP | G22: How to detect overlapping subproblems; how to name and count distinct states | H22: Memoisation decorator syntax | I22: LC 140, LC 494 | J22: Name the state for 3 problems from memory | L22: =IF($A22="","",INDEX(DayPlan!$C$2:$C$169,MATCH($A22,DayPlan!$A$2:$A$169,0))) | M22: =HYPERLINK("https://www.youtube.com/watch?v=XB4MIexjvY0", "▶ Watch (Abdul Bari) ↗") | N22: =HYPERLINK("https://www.youtube.com/results?search_query=striver%20dp%20series%20introduction%20memoization", "📺 Striver ↗") | O22: =HYPERLINK("https://www.youtube.com/results?search_query=aditya%20verma%20dp%20playlist%20memoization", "📺 Aditya Verma ↗") | P22: =HYPERLINK("https://www.youtube.com/results?search_query=love%20babbar%20dp%20playlist%20memoization", "📺 Love Babbar ↗") | Q22: =HYPERLINK("https://www.youtube.com/results?search_query=padho%20with%20pratyush%20dynamic%20programming", "📺 Padho with Pratyush ↗") | R22: — | S22: =HYPERLINK("https://www.youtube.com/results?search_query=abdul%20bari%20dynamic%20programming", "📺 Abdul Bari ↗")
A23: 78 | B23: NeetCode + CPH ch.7 | C23: DP state design (5-step method) | D23: neetcode.io + CPH ch.7 | E23: 30 | F23: Templates fail on unfamiliar DP; state-first design does not - this is the critical difference | G23: State -> transition -> base case -> evaluation order -> answer location (in that order) | H23: Classic DP code from videos | I23: LC 70, LC 198, LC 91 | J23: Recite the 5 steps without notes | L23: =IF($A23="","",INDEX(DayPlan!$C$2:$C$169,MATCH($A23,DayPlan!$A$2:$A$169,0))) | M23: =HYPERLINK("https://www.youtube.com/watch?v=ibjEGG7ylHk", "▶ Watch (WilliamFiset) ↗") | N23: =HYPERLINK("https://www.youtube.com/results?search_query=striver%20dp%20series%20playlist", "📺 Striver ↗") | O23: =HYPERLINK("https://www.youtube.com/results?search_query=aditya%20verma%20dp%20playlist", "📺 Aditya Verma ↗") | P23: =HYPERLINK("https://www.youtube.com/results?search_query=love%20babbar%20dynamic%20programming", "📺 Love Babbar ↗") | Q23: =HYPERLINK("https://www.youtube.com/results?search_query=padho%20with%20pratyush%20dp%20space%20optimization", "📺 Padho with Pratyush ↗") | R23: — | S23: =HYPERLINK("https://www.youtube.com/results?search_query=abdul%20bari%20dynamic%20programming", "📺 Abdul Bari ↗")
A24: 80 | B24: CPH ch.7 / cp-algorithms | C24: Knapsack variants and loop order | D24: CPH ch.7 | E24: 25 | F24: Loop order is the single most misunderstood DP detail; most candidates guess and get wrong | G24: Why 0/1 knapsack goes descending; why unbounded goes ascending; construct the failing example | H24: Table layout diagrams | I24: LC 416, LC 322 | J24: Explain loop order by constructing the failing counterexample | L24: =IF($A24="","",INDEX(DayPlan!$C$2:$C$169,MATCH($A24,DayPlan!$A$2:$A$169,0))) | M24: =HYPERLINK("https://www.youtube.com/watch?v=4ZlRH0eK-qQ", "▶ Watch (Abdul Bari) ↗") | N24: =HYPERLINK("https://www.youtube.com/results?search_query=striver%2001%20knapsack%20subset%20sum", "📺 Striver ↗") | O24: =HYPERLINK("https://www.youtube.com/results?search_query=aditya%20verma%2001%20knapsack%20playlist", "📺 Aditya Verma ↗") | P24: =HYPERLINK("https://www.youtube.com/results?search_query=love%20babbar%20knapsack%20problem", "📺 Love Babbar ↗") | Q24: =HYPERLINK("https://www.youtube.com/results?search_query=padho%20with%20pratyush%20knapsack", "📺 Padho with Pratyush ↗") | R24: =HYPERLINK("https://www.youtube.com/results?search_query=neetcode%20coin%20change%20knapsack", "📺 NeetCode ↗") | S24: —
